Workbook
Name prevWBS: '(細部)工作任務_甘特圖'!$A1048576
Name valuevx: 42.314159
Name WBS層級名稱: 'PLM001-Active'!$C$2:$C$1048576
Name 人員: 'PLM001-Active'!$K$2:$K$1048576
Name 工期: 'PLM001-Active'!$O$2:$O$1048576
Name 任務名稱: 'PLM001-Active'!$E$2:$E$1048576
Name 任務完成度: 'PLM001-Active'!$L$2:$L$1048576
Name 任務狀態: 'PLM001-Active'!$Q$2:$Q$1048576
Name 任務負責人: 'PLM001-Active'!$H$2:$H$1048576
Name 專案名稱: 'PLM001-Active'!$B$2:$B$1048576
Name 專案指派: 'PLM001-Active'!$I$2:$I$1048576
Name 專案負責人: 'PLM001-Active'!$D$2:$D$1048576
Name 專案編號: 'PLM001-Active'!$A$2:$A$1048576
Name 部門名稱: 'PLM001-Active'!$G$2:$G$1048576
Name 描述_延遲原因: 'PLM001-Active'!$F$2:$F$1048576
Name 結案日期: 'PLM001-Active'!$V$2:$V$1048576
Name 預計工時: 'PLM001-Active'!$P$2:$P$1048576
Name 預計結束日: 'PLM001-Active'!$N$2:$N$1048576
Name 預計開始日: 'PLM001-Active'!$M$2:$M$1048576
Name 實際工時: 'PLM001-Active'!$U$2:$U$1048576
Name 實際天數: 'PLM001-Active'!$T$2:$T$1048576
Name 實際完成日: 'PLM001-Active'!$S$2:$S$1048576
Name 實際開始日: 'PLM001-Active'!$R$2:$R$1048576

Sheet 總表
A1: 查詢範圍 | B1: 45658 | C1: 46044
A2: 研發一處
A3: 專案編號 | B3: 專案名稱 | D3: 專案負責人 | E3: 專案狀態 | F3: 預計起始日 | G3: 預計完成日 | H3: 實際開始日 | I3: 實際完成日 | J3: 預計設工時 | K3: 實際設計工時 | L3: 本週投入設工 | M3: 專案是否異常 | N3: 工況試煉送樣 (來源PLM) | O3: 異常說明 | P3: 需要的協助 | Q3: 預計完成日
A4: D250703R1 | B4: =VLOOKUP(A4,專案進度表!B:DT,2,FALSE) -> EPH連板電測治具 | C4: =VLOOKUP(A4,專案進度表!$B:$DT,4,FALSE) -> 研發一處 | D4: =VLOOKUP(A4,專案進度表!$B:$DT,5,FALSE) -> 賴慶樺 | E4: =VLOOKUP(A4,專案進度表!$B:$DT,6,FALSE) -> Active | F4: =VLOOKUP(A4,專案進度表!$B:$DT,7,FALSE) -> 45862.667 | G4: =VLOOKUP(A4,專案進度表!$B:$DT,8,FALSE) -> 46051.667 | H4: =IF(VLOOKUP(A4,專案進度表!$B:$DT,12,FALSE)=0,"",VLOOKUP(A4,專案進度表!$B:$DT,12,FALSE)) -> 45866 | I4: =IF(VLOOKUP(A4,專案進度表!$B:$DT,13,FALSE)=0,"",VLOOKUP(A4,專案進度表!$B:$DT,13,FALSE)) | J4: =IF(SUMIFS('PLM001-財務計算用'!$P:$P,'PLM001-財務計算用'!$A:$A,A4)=0,"未登入",SUMIFS('PLM001-財務計算用'!$P:$P,'PLM001-財務計算用'!$A:$A,A4)) -> 未登入 | K4: =SUMIFS('PLM002'!$K:$K,'PLM002'!$F:$F,$A4) -> 76 | L4: =IF(SUMIFS('PLM002'!$K:$K,'PLM002'!$F:$F,A4,'PLM002'!$J:$J,">="&$B$1,'PLM002'!$J:$J,"<="&$C$1)=0,"未投入",SUMIFS('PLM002'!$K:$K,'PLM002'!$F:$F,A4,'PLM002'!$J:$J,">="&$B$1,'PLM002'!$J:$J,"<="&$C$1)) -> 76 | M4: =VLOOKUP(A4,專案進度表!$B:$DT,18,FALSE) -> 專案即將異常 | N4: =IF(VLOOKUP(A4,'PLM014'!$B:$R,17,FALSE)=0,"",VLOOKUP(A4,'PLM014'!$B:$R,17,FALSE))
A5: M250301C1 | B5: =VLOOKUP(A5,專案進度表!B:DT,2,FALSE) -> 一體型電磁流量計北美多重防爆認證 | C5: =VLOOKUP(A5,專案進度表!$B:$DT,4,FALSE) -> 研發一處 | D5: =VLOOKUP(A5,專案進度表!$B:$DT,5,FALSE) -> 陳威諭 | E5: =VLOOKUP(A5,專案進度表!$B:$DT,6,FALSE) -> Active | F5: =VLOOKUP(A5,專案進度表!$B:$DT,7,FALSE) -> 45725.667 | G5: =VLOOKUP(A5,專案進度表!$B:$DT,8,FALSE) -> 46190.667 | H5: =IF(VLOOKUP(A5,專案進度表!$B:$DT,12,FALSE)=0,"",VLOOKUP(A5,專案進度表!$B:$DT,12,FALSE)) -> 45727 | I5: =IF(VLOOKUP(A5,專案進度表!$B:$DT,13,FALSE)=0,"",VLOOKUP(A5,專案進度表!$B:$DT,13,FALSE)) | J5: =IF(SUMIFS('PLM001-財務計算用'!$P:$P,'PLM001-財務計算用'!$A:$A,A5)=0,"未登入",SUMIFS('PLM001-財務計算用'!$P:$P,'PLM001-財務計算用'!$A:$A,A5)) -> 416 | K5: =SUMIFS('PLM002'!$K:$K,'PLM002'!$F:$F,$A5) -> 1314.5 | L5: =IF(SUMIFS('PLM002'!$K:$K,'PLM002'!$F:$F,A5,'PLM002'!$J:$J,">="&$B$1,'PLM002'!$J:$J,"<="&$C$1)=0,"未投入",SUMIFS('PLM002'!$K:$K,'PLM002'!$F:$F,A5,'PLM002'!$J:$J,">="&$B$1,'PLM002'!$J:$J,"<="&$C$1)) -> 1314.5 | M5: =VLOOKUP(A5,專案進度表!$B:$DT,18,FALSE) | N5: =IF(VLOOKUP(A5,'PLM014'!$B:$R,17,FALSE)=0,"",VLOOKUP(A5,'PLM014'!$B:$R,17,FALSE)) | O5: 9/26 CSA對於本安隔離柵的變壓器認定與過去的IECEX及NEPSI認定不同，會造成需要多3組zener 8W的保護零件，嚴重影響電路設計及空間需求。已請CSA工程師重新審視。 10/28 電路板發包打件、膠塊耐候性測試樣品CSA已收到。 11/4 膠體耐受性測試矽膠通過，黑色橡膠沒過，前蓋膠體更新後送件做耐壓測試。 11/14 目前合適的膠體正在確認。 11/14 電路板打件，預計11/19備料完成，12/3 打件回廠。
A6: M251201C1 | B6: =VLOOKUP(A6,專案進度表!B:DT,2,FALSE) -> GPX 申請UL-61010認證 | C6: =VLOOKUP(A6,專案進度表!$B:$DT,4,FALSE) -> 研發一處 | D6: =VLOOKUP(A6,專案進度表!$B:$DT,5,FALSE) -> 賴慶樺 | E6: =VLOOKUP(A6,專案進度表!$B:$DT,6,FALSE) -> Active | F6: =VLOOKUP(A6,專案進度表!$B:$DT,7,FALSE) -> 46019.667 | G6: =VLOOKUP(A6,專案進度表!$B:$DT,8,FALSE) -> 46111.667 | H6: =IF(VLOOKUP(A6,專案進度表!$B:$DT,12,FALSE)=0,"",VLOOKUP(A6,專案進度表!$B:$DT,12,FALSE)) -> 46024 | I6: =IF(VLOOKUP(A6,專案進度表!$B:$DT,13,FALSE)=0,"",VLOOKUP(A6,專案進度表!$B:$DT,13,FALSE)) | J6: =IF(SUMIFS('PLM001-財務計算用'!$P:$P,'PLM001-財務計算用'!$A:$A,A6)=0,"未登入",SUMIFS('PLM001-財務計算用'!$P:$P,'PLM001-財務計算用'!$A:$A,A6)) -> 未登入 | K6: =SUMIFS('PLM002'!$K:$K,'PLM002'!$F:$F,$A6) -> 36 | L6: =IF(SUMIFS('PLM002'!$K:$K,'PLM002'!$F:$F,A6,'PLM002'!$J:$J,">="&$B$1,'PLM002'!$J:$J,"<="&$C$1)=0,"未投入",SUMIFS('PLM002'!$K:$K,'PLM002'!$F:$F,A6,'PLM002'!$J:$J,">="&$B$1,'PLM002'!$J:$J,"<="&$C$1)) -> 36 | M6: =VLOOKUP(A6,專案進度表!$B:$DT,18,FALSE) -> 專案即將異常 | N6: =IF(VLOOKUP(A6,'PLM014'!$B:$R,17,FALSE)=0,"",VLOOKUP(A6,'PLM014'!$B:$R,17,FALSE))
A8: 技術中心
A9: 專案編號 | B9: 專案名稱 | D9: 專案負責人 | E9: 專案狀態 | F9: 預計起始日 | G9: 預計完成日 | H9: 實際開始日 | I9: 實際完成日 | J9: 預計設工時 | K9: 實際設計工時 | M9: 專案是否異常 | N9: 工況試煉送樣 | O9: 異常說明
A10: M230701R1 | B10: =VLOOKUP(A10,專案進度表!B:DT,2,FALSE) -> #N/A | C10: =VLOOKUP(A10,專案進度表!$B:$DT,4,FALSE) -> #N/A | D10: =VLOOKUP(A10,專案進度表!$B:$DT,5,FALSE) -> #N/A | E10: =VLOOKUP(A10,專案進度表!$B:$DT,6,FALSE) -> #N/A | F10: =VLOOKUP(A10,專案進度表!$B:$DT,7,FALSE) -> #N/A | G10: =VLOOKUP(A10,專案進度表!$B:$DT,8,FALSE) -> #N/A | H10: =VLOOKUP(A10,專案進度表!$B:$DT,12,FALSE) -> #N/A | I10: =VLOOKUP(A10,專案進度表!$B:$DT,13,FALSE) -> #N/A | J10: =IF(SUMIFS('PLM001-財務計算用'!$P:$P,'PLM001-財務計算用'!$A:$A,A10)=0,"未登入",SUMIFS('PLM001-財務計算用'!$P:$P,'PLM001-財務計算用'!$A:$A,A10)) -> 未登入 | K10: =SUMIFS('PLM002'!#REF!,'PLM002'!$F:$F,$A10) -> #REF! | M10: =VLOOKUP(A10,專案進度表!$B:$DT,18,FALSE) -> #N/A | N10: =IF(VLOOKUP(A10,'PLM014'!$B:$R,17,FALSE)=0,"",VLOOKUP(A10,'PLM014'!$B:$R,17,FALSE)) -> #N/A
A11: M230102R1 | B11: =VLOOKUP(A11,專案進度表!B:DT,2,FALSE) -> #N/A | C11: =VLOOKUP(A11,專案進度表!$B:$DT,4,FALSE) -> #N/A | D11: =VLOOKUP(A11,專案進度表!$B:$DT,5,FALSE) -> #N/A | E11: =VLOOKUP(A11,專案進度表!$B:$DT,6,FALSE) -> #N/A | F11: =VLOOKUP(A11,專案進度表!$B:$DT,7,FALSE) -> #N/A | G11: =VLOOKUP(A11,專案進度表!$B:$DT,8,FALSE) -> #N/A | H11: =VLOOKUP(A11,專案進度表!$B:$DT,12,FALSE) -> #N/A | I11: =VLOOKUP(A11,專案進度表!$B:$DT,13,FALSE) -> #N/A | J11: =IF(SUMIFS('PLM001-財務計算用'!$P:$P,'PLM001-財務計算用'!$A:$A,A11)=0,"未登入",SUMIFS('PLM001-財務計算用'!$P:$P,'PLM001-財務計算用'!$A:$A,A11)) -> 未登入 | K11: =SUMIFS('PLM002'!#REF!,'PLM002'!$F:$F,$A11) -> #REF! | M11: =VLOOKUP(A11,專案進度表!$B:$DT,18,FALSE) -> #N/A | N11: =IF(VLOOKUP(A11,'PLM014'!$B:$R,17,FALSE)=0,"",VLOOKUP(A11,'PLM014'!$B:$R,17,FALSE)) -> #N/A
A13: RD1
A14: 專案編號 | B14: 專案名稱 | D14: 專案負責人 | E14: 專案狀態 | F14: 預計起始日 | G14: 預計完成日 | H14: 實際開始日 | I14: 實際完成日 | J14: 預計設工時 | K14: 實際設計工時 | L14: 本週投入設工 | M14: 專案是否異常 | N14: 工況試煉送樣 | O14: 異常說明 | P14: 需要的協助 | Q14: 預計完成日
A15: D250802R1 | B15: =VLOOKUP(A15,專案進度表!B:DT,2,FALSE) -> 申請量桶量槽製作資格 | C15: =VLOOKUP(A15,專案進度表!$B:$DT,4,FALSE) -> 研一部 | D15: =VLOOKUP(A15,專案進度表!$B:$DT,5,FALSE) -> 何昆達 | E15: =VLOOKUP(A15,專案進度表!$B:$DT,6,FALSE) -> Active | F15: =VLOOKUP(A15,專案進度表!$B:$DT,7,FALSE) -> 45886.667 | G15: =VLOOKUP(A15,專案進度表!$B:$DT,8,FALSE) -> 46049.667 | H15: =IF(VLOOKUP(A15,專案進度表!$B:$DT,12,FALSE)=0,"",VLOOKUP(A15,專案進度表!$B:$DT,12,FALSE)) -> 45887 | I15: =IF(VLOOKUP(A15,專案進度表!$B:$DT,13,FALSE)=0,"",VLOOKUP(A15,專案進度表!$B:$DT,13,FALSE)) | J15: =IF(SUMIFS('PLM001-財務計算用'!$P:$P,'PLM001-財務計算用'!$A:$A,A15)=0,"未登入",SUMIFS('PLM001-財務計算用'!$P:$P,'PLM001-財務計算用'!$A:$A,A15)) -> 184 | K15: =SUMIFS('PLM002'!$K:$K,'PLM002'!$F:$F,$A15) -> 172.7 | L15: =IF(SUMIFS('PLM002'!$K:$K,'PLM002'!$F:$F,A15,'PLM002'!$J:$J,">="&$B$1,'PLM002'!$J:$J,"<="&$C$1)=0,"未投入",SUMIFS('PLM002'!$K:$K,'PLM002'!$F:$F,A15,'PLM002'!$J:$J,">="&$B$1,'PLM002'!$J:$J,"<="&$C$1)) -> 172.7 | M15: =VLOOKUP(A15,專案進度表!$B:$DT,18,FALSE) -> 專案即將異常 | N15: =IF(VLOOKUP(A15,'PLM014'!$B:$R,17,FALSE)=0,"",VLOOKUP(A15,'PLM014'!$B:$R,17,FALSE)) | O15: 1. 已取得電子天平校正報告 2. 電磁流量計校正9/26日完成，10/2日報告審查簽核完成。 3. 10/3日提供至標檢局文件覆核 10/17, 標檢局通知已經完成文件審核，待通知實地查核的時間，預定10/30進行。 10/31,標檢局31日已完成實地查核，預計兩周後發證。 11/13日已取得證書 4. 本周提交標準局標定文件，安排量筒標定日期 12/1, 今日申請量桶標定付款，安排12/8日標定 工研院校正安排於12/17~18日，預計12月份可完成量桶導入使用。 12/19, 工研院量筒校正已完成
A16: K240801R2 | B16: =VLOOKUP(A16,專案進度表!B:DT,2,FALSE) -> PCB濕製程用插入式壓力感測器 | C16: =VLOOKUP(A16,專案進度表!$B:$DT,4,FALSE) -> 研一部 | D16: =VLOOKUP(A16,專案進度表!$B:$DT,5,FALSE) -> 張良琪 | E16: =VLOOKUP(A16,專案進度表!$B:$DT,6,FALSE) -> Active | F16: =VLOOKUP(A16,專案進度表!$B:$DT,7,FALSE) -> 45641.667 | G16: =VLOOKUP(A16,專案進度表!$B:$DT,8,FALSE) -> 45807.667 | H16: =IF(VLOOKUP(A16,專案進度表!$B:$DT,12,FALSE)=0,"",VLOOKUP(A16,專案進度表!$B:$DT,12,FALSE)) -> 45524 | I16: =IF(VLOOKUP(A16,專案進度表!$B:$DT,13,FALSE)=0,"",VLOOKUP(A16,專案進度表!$B:$DT,13,FALSE)) | J16: =IF(SUMIFS('PLM001-財務計算用'!$P:$P,'PLM001-財務計算用'!$A:$A,A16)=0,"未登入",SUMIFS('PLM001-財務計算用'!$P:$P,'PLM001-財務計算用'!$A:$A,A16)) -> 1146 | K16: =SUMIFS('PLM002'!$K:$K,'PLM002'!$F:$F,$A16) -> 2762.3 | L16: =IF(SUMIFS('PLM002'!$K:$K,'PLM002'!$F:$F,A16,'PLM002'!$J:$J,">="&$B$1,'PLM002'!$J:$J,"<="&$C$1)=0,"未投入",SUMIFS('PLM002'!$K:$K,'PLM002'!$F:$F,A16,'PLM002'!$J:$J,">="&$B$1,'PLM002'!$J:$J,"<="&$C$1)) -> 2649.3 | M16: =VLOOKUP(A16,專案進度表!$B:$DT,18,FALSE) -> 專案延遲 237 天 | N16: =IF(VLOOKUP(A16,'PLM014'!$B:$R,17,FALSE)=0,"",VLOOKUP(A16,'PLM014'!$B:$R,17,FALSE)) -> 45709 | O16: 12/1, 200PCS結構已到上海，本週海運寄出，預計兩週到土城 11/20, 本週已準備6PCS樣品供上海展覽使用 本週拜訪永煜機械，為PCB製程末端電鍍設備製造商，壓力表材質可使用陶瓷+PVDF，目前使用表頭直徑2"，我司83mm安裝於過濾桶上空間不足。 12/19, 12/16工程試製會議完成,本周一會議決議修改文件及製程,生管開單生產50套安排於月底進行 | Q16: 預計9月份進行工程試製10月份技轉關案。 9/5,備料延至9/30，工程試製時間延後製10月份 外殼預計11/7日到200套，工程試製延至11月 供應商尺寸製作錯誤，延至12/5日到貨，工程試製延至12月份。
A17: M251201R1 | B17: =VLOOKUP(A17,專案進度表!B:DT,2,FALSE) -> 緊湊型渦街流量計導入專案 | C17: =VLOOKUP(A17,專案進度表!$B:$DT,4,FALSE) -> 研一部 | D17: =VLOOKUP(A17,專案進度表!$B:$DT,5,FALSE) -> 陳奕宏 | E17: =VLOOKUP(A17,專案進度表!$B:$DT,6,FALSE) -> Active | F17: =VLOOKUP(A17,專案進度表!$B:$DT,7,FALSE) -> 46005.667 | G17: =VLOOKUP(A17,專案進度表!$B:$DT,8,FALSE) -> 46079.667 | H17: =IF(VLOOKUP(A17,專案進度表!$B:$DT,12,FALSE)=0,"",VLOOKUP(A17,專案進度表!$B:$DT,12,FALSE)) | I17: =IF(VLOOKUP(A17,專案進度表!$B:$DT,13,FALSE)=0,"",VLOOKUP(A17,專案進度表!$B:$DT,13,FALSE)) | J17: =IF(SUMIFS('PLM001-財務計算用'!$P:$P,'PLM001-財務計算用'!$A:$A,A17)=0,"未登入",SUMIFS('PLM001-財務計算用'!$P:$P,'PLM001-財務計算用'!$A:$A,A17)) -> 436 | K17: =SUMIFS('PLM002'!$K:$K,'PLM002'!$F:$F,$A17) -> 1 | L17: =IF(SUMIFS('PLM002'!$K:$K,'PLM002'!$F:$F,A17,'PLM002'!$J:$J,">="&$B$1,'PLM002'!$J:$J,"<="&$C$1)=0,"未投入",SUMIFS('PLM002'!$K:$K,'PLM002'!$F:$F,A17,'PLM002'!$J:$J,">="&$B$1,'PLM002'!$J:$J,"<="&$C$1)) -> 1 | M17: =VLOOKUP(A17,專案進度表!$B:$DT,18,FALSE) -> 專案即將異常 | N17: =IF(VLOOKUP(A17,'PLM014'!$B:$R,17,FALSE)=0,"",VLOOKUP(A17,'PLM014'!$B:$R,17,FALSE)) -> 46062
A19: RD2
A20: 專案編號 | B20: 專案名稱 | D20: 專案負責人 | E20: 專案狀態 | F20: 預計起始日 | G20: 預計完成日 | H20: 實際開始日 | I20: 實際完成日 | J20: 預計設工時 | K20: 實際設計工時 | L20: 本週投入設工 | M20: 專案是否異常 | N20: 工況試煉送樣 | O20: 異常說明 | P20: 需要的協助 | Q20: 預計完成日
A21: D250101R1 | B21: =VLOOKUP(A21,專案進度表!B:DT,2,FALSE) -> AI冷卻系統數位通訊溫度偵測器 | C21: =VLOOKUP(A21,專案進度表!$B:$DT,4,FALSE) -> 研二部 | D21: =VLOOKUP(A21,專案進度表!$B:$DT,5,FALSE) -> 黃胤綸 | E21: =VLOOKUP(A21,專案進度表!$B:$DT,6,FALSE) -> Active | F21: =VLOOKUP(A21,專案進度表!$B:$DT,7,FALSE) -> 45669.667 | G21: =VLOOKUP(A21,專案進度表!$B:$DT,8,FALSE) -> 45776.667 | H21: =IF(VLOOKUP(A21,專案進度表!$B:$DT,12,FALSE)=0,"",VLOOKUP(A21,專案進度表!$B:$DT,12,FALSE)) -> 45670 | I21: =IF(VLOOKUP(A21,專案進度表!$B:$DT,13,FALSE)=0,"",VLOOKUP(A21,專案進度表!$B:$DT,13,FALSE)) | J21: =IF(SUMIFS('PLM001-財務計算用'!$P:$P,'PLM001-財務計算用'!$A:$A,A21)=0,"未登入",SUMIFS('PLM001-財務計算用'!$P:$P,'PLM001-財務計算用'!$A:$A,A21)) -> 795 | K21: =SUMIFS('PLM002'!$K:$K,'PLM002'!$F:$F,$A21) -> 1258 | L21: =IF(SUMIFS('PLM002'!$K:$K,'PLM002'!$F:$F,A21,'PLM002'!$J:$J,">="&$B$1,'PLM002'!$J:$J,"<="&$C$1)=0,"未投入",SUMIFS('PLM002'!$K:$K,'PLM002'!$F:$F,A21,'PLM002'!$J:$J,">="&$B$1,'PLM002'!$J:$J,"<="&$C$1)) -> 1258 | M21: =VLOOKUP(A21,專案進度表!$B:$DT,18,FALSE) -> 專案延遲 268 天 | N21: =IF(VLOOKUP(A21,'PLM014'!$B:$R,17,FALSE)=0,"",VLOOKUP(A21,'PLM014'!$B:$R,17,FALSE)) -> 45700 | O21: 1/19 1. GPX8具RS485功能治具, 使用WIKA恆溫水槽, 安排工程試製, 預計1月底召開行前會議. 2. GPX8-PT1000量產設備試俥, 設備器差與軟體整合已測試完成, SOP已完成, 本週試俥之前170 PCS不良品同時, 請電一派人來學習使用. | P21: GPX8成品校驗治具自動化已確認, 簽核後購買設備, 預計3週後開始組裝. | Q21: 工程試製預估1個月, 完成後再2週技轉。
A22: D250702R1 | B22: =VLOOKUP(A22,專案進度表!B:DT,2,FALSE) -> 2025年度-硬體模組化專案 | C22: =VLOOKUP(A22,專案進度表!$B:$DT,4,FALSE) -> 研二部 | D22: =VLOOKUP(A22,專案進度表!$B:$DT,5,FALSE) -> 黃胤綸 | E22: =VLOOKUP(A22,專案進度表!$B:$DT,6,FALSE) -> Active | F22: =VLOOKUP(A22,專案進度表!$B:$DT,7,FALSE) -> 45657.667 | G22: =VLOOKUP(A22,專案進度表!$B:$DT,8,FALSE) -> 46021.667 | H22: =IF(VLOOKUP(A22,專案進度表!$B:$DT,12,FALSE)=0,"",VLOOKUP(A22,專案進度表!$B:$DT,12,FALSE)) -> 45847 | I22: =IF(VLOOKUP(A22,專案進度表!$B:$DT,13,FALSE)=0,"",VLOOKUP(A22,專案進度表!$B:$DT,13,FALSE)) | J22: =IF(SUMIFS('PLM001-財務計算用'!$P:$P,'PLM001-財務計算用'!$A:$A,A22)=0,"未登入",SUMIFS('PLM001-財務計算用'!$P:$P,'PLM001-財務計算用'!$A:$A,A22)) -> 488 | K22: =SUMIFS('PLM002'!$K:$K,'PLM002'!$F:$F,$A22) -> 589.6 | L22: =IF(SUMIFS('PLM002'!$K:$K,'PLM002'!$F:$F,A22,'PLM002'!$J:$J,">="&$B$1,'PLM002'!$J:$J,"<="&$C$1)=0,"未投入",SUMIFS('PLM002'!$K:$K,'PLM002'!$F:$F,A22,'PLM002'!$J:$J,">="&$B$1,'PLM002'!$J:$J,"<="&$C$1)) -> 589.6 | M22: =VLOOKUP(A22,專案進度表!$B:$DT,18,FALSE) -> 專案延遲 23 天 | N22: =IF(VLOOKUP(A22,'PLM014'!$B:$R,17,FALSE)=0,"",VLOOKUP(A22,'PLM014'!$B:$R,17,FALSE))
A23: M250201C1 | B23: =VLOOKUP(A23,專案進度表!B:DT,2,FALSE) -> 工業爆炸環境防爆型音叉感測器 | C23: =VLOOKUP(A23,專案進度表!$B:$DT,4,FALSE) -> 研二部 | D23: =VLOOKUP(A23,專案進度表!$B:$DT,5,FALSE) -> 黃胤綸 | E23: =VLOOKUP(A23,專案進度表!$B:$DT,6,FALSE) -> Active | F23: =VLOOKUP(A23,專案進度表!$B:$DT,7,FALSE) -> 45713.667 | G23: =VLOOKUP(A23,專案進度表!$B:$DT,8,FALSE) -> 45922.667 | H23: =IF(VLOOKUP(A23,專案進度表!$B:$DT,12,FALSE)=0,"",VLOOKUP(A23,專案進度表!$B:$DT,12,FALSE)) -> 45713 | I23: =IF(VLOOKUP(A23,專案進度表!$B:$DT,13,FALSE)=0,"",VLOOKUP(A23,專案進度表!$B:$DT,13,FALSE)) | J23: =IF(SUMIFS('PLM001-財務計算用'!$P:$P,'PLM001-財務計算用'!$A:$A,A23)=0,"未登入",SUMIFS('PLM001-財務計算用'!$P:$P,'PLM001-財務計算用'!$A:$A,A23)) -> 708 | K23: =SUMIFS('PLM002'!$K:$K,'PLM002'!$F:$F,$A23) -> 1030 | L23: =IF(SUMIFS('PLM002'!$K:$K,'PLM002'!$F:$F,A23,'PLM002'!$J:$J,">="&$B$1,'PLM002'!$J:$J,"<="&$C$1)=0,"未投入",SUMIFS('PLM002'!$K:$K,'PLM002'!$F:$F,A23,'PLM002'!$J:$J,">="&$B$1,'PLM002'!$J:$J,"<="&$C$1)) -> 1030 | M23: =VLOOKUP(A23,專案進度表!$B:$DT,18,FALSE) -> 專案延遲 122 天 | N23: =IF(VLOOKUP(A23,'PLM014'!$B:$R,17,FALSE)=0,"",VLOOKUP(A23,'PLM014'!$B:$R,17,FALSE)) | O23: 1/19 1. 溫昇測試11/20完成. 2. 高溫220度C/高壓200bar測試完成. 3. 老化測試後IP67 1/16測試PASS, 剩水壓與非傳測試, 預計1/23前完成. | Q23: 預計2026/2月底取證
A24: M251001R1 | B24: =VLOOKUP(A24,專案進度表!B:DT,2,FALSE) -> SDX光電開關微型化設計 | C24: =VLOOKUP(A24,專案進度表!$B:$DT,4,FALSE) -> 研二部 | D24: =VLOOKUP(A24,專案進度表!$B:$DT,5,FALSE) -> 彭志豪 | E24: =VLOOKUP(A24,專案進度表!$B:$DT,6,FALSE) -> Active | F24: =VLOOKUP(A24,專案進度表!$B:$DT,7,FALSE) -> 45966.667 | G24: =VLOOKUP(A24,專案進度表!$B:$DT,8,FALSE) -> 46128.667 | H24: =IF(VLOOKUP(A24,專案進度表!$B:$DT,12,FALSE)=0,"",VLOOKUP(A24,專案進度表!$B:$DT,12,FALSE)) -> 45950 | I24: =IF(VLOOKUP(A24,專案進度表!$B:$DT,13,FALSE)=0,"",VLOOKUP(A24,專案進度表!$B:$DT,13,FALSE)) | J24: =IF(SUMIFS('PLM001-財務計算用'!$P:$P,'PLM001-財務計算用'!$A:$A,A24)=0,"未登入",SUMIFS('PLM001-財務計算用'!$P:$P,'PLM001-財務計算用'!$A:$A,A24)) -> 419 | K24: =SUMIFS('PLM002'!$K:$K,'PLM002'!$F:$F,$A24) -> 794 | L24: =IF(SUMIFS('PLM002'!$K:$K,'PLM002'!$F:$F,A24,'PLM002'!$J:$J,">="&$B$1,'PLM002'!$J:$J,"<="&$C$1)=0,"未投入",SUMIFS('PLM002'!$K:$K,'PLM002'!$F:$F,A24,'PLM002'!$J:$J,">="&$B$1,'PLM002'!$J:$J,"<="&$C$1)) -> 794 | M24: =VLOOKUP(A24,專案進度表!$B:$DT,18,FALSE) | N24: =IF(VLOOKUP(A24,'PLM014'!$B:$R,17,FALSE)=0,"",VLOOKUP(A24,'PLM014'!$B:$R,17,FALSE)) -> 46065 | O24: 1/19 1. 開模(太陽片)預計2026/1/23回廠. 2. 電路已驗證完成, 會再改一版與新增PNP型. 3. 本週試低壓射出模具並試裝成品測功能. | Q24: 樣品預計2026/2/12提供
A26: RD3
A27: 專案編號 | B27: 專案名稱 | D27: 專案負責人 | E27: 專案狀態 | F27: 預計起始日 | G27: 預計完成日 | H27: 實際開始日 | I27: 實際完成日 | J27: 預計設工時 | K27: 實際設計工時 | L27: 本週投入設工 | M27: 專案是否異常 | N27: 工況試煉送樣 | O27: 異常說明 | P27: 需要的協助 | Q27: 預計完成日
A28: M240704R1 | B28: =VLOOKUP(A28,專案進度表!B:DT,2,FALSE) -> 一體式夾管超音波流量計(DN25)[RD4] | C28: =VLOOKUP(A28,專案進度表!$B:$DT,4,FALSE) -> 研三部 | D28: =VLOOKUP(A28,專案進度表!$B:$DT,5,FALSE) -> 陳俊儒 | E28: =VLOOKUP(A28,專案進度表!$B:$DT,6,FALSE) -> Active | F28: =VLOOKUP(A28,專案進度表!$B:$DT,7,FALSE) -> 45536.667 | G28: =VLOOKUP(A28,專案進度表!$B:$DT,8,FALSE) -> 45755.667 | H28: =IF(VLOOKUP(A28,專案進度表!$B:$DT,12,FALSE)=0,"",VLOOKUP(A28,專案進度表!$B:$DT,12,FALSE)) -> 45537 | I28: =IF(VLOOKUP(A28,專案進度表!$B:$DT,13,FALSE)=0,"",VLOOKUP(A28,專案進度表!$B:$DT,13,FALSE)) | J28: =IF(SUMIFS('PLM001-財務計算用'!$P:$P,'PLM001-財務計算用'!$A:$A,A28)=0,"未登入",SUMIFS('PLM001-財務計算用'!$P:$P,'PLM001-財務計算用'!$A:$A,A28)) -> 1896 | K28: =SUMIFS('PLM002'!$K:$K,'PLM002'!$F:$F,$A28) -> 7306.6 | L28: =IF(SUMIFS('PLM002'!$K:$K,'PLM002'!$F:$F,A28,'PLM002'!$J:$J,">="&$B$1,'PLM002'!$J:$J,"<="&$C$1)=0,"未投入",SUMIFS('PLM002'!$K:$K,'PLM002'!$F:$F,A28,'PLM002'!$J:$J,">="&$B$1,'PLM002'!$J:$J,"<="&$C$1)) -> 5536.1 | M28: =VLOOKUP(A28,專案進度表!$B:$DT,18,FALSE) | N28: =IF(VLOOKUP(A28,'PLM014'!$B:$R,17,FALSE)=0,"",VLOOKUP(A28,'PLM014'!$B:$R,17,FALSE)) -> 45695 | O28: 10/20 目前進度：探頭PEI + 壓電壓貼合後的訊號量測作業。 10/28 目前進度：背膠層灌膠後等待乾燥。目前確認損壞的樣品為4/60 = 7% 11/14 已完成試作，目前正在完善文件及測試結果統計分析。 11/22 資料已整理完成，待台大做結案報告(日期待定。) | P28: 11/18公司確認時間，讓台大做結案報告。 | Q28: 45991
A29: M250301R1 | B29: =VLOOKUP(A29,專案進度表!B:DT,2,FALSE) -> 軌道型顯示器夾管式超音波流量計 | C29: =VLOOKUP(A29,專案進度表!$B:$DT,4,FALSE) -> 研三部 | D29: =VLOOKUP(A29,專案進度表!$B:$DT,5,FALSE) -> 陳俊儒 | E29: =VLOOKUP(A29,專案進度表!$B:$DT,6,FALSE) -> Active | F29: =VLOOKUP(A29,專案進度表!$B:$DT,7,FALSE) -> 45747.667 | G29: =VLOOKUP(A29,專案進度表!$B:$DT,8,FALSE) -> 46008.667 | H29: =IF(VLOOKUP(A29,專案進度表!$B:$DT,12,FALSE)=0,"",VLOOKUP(A29,專案進度表!$B:$DT,12,FALSE)) -> 45748 | I29: =IF(VLOOKUP(A29,專案進度表!$B:$DT,13,FALSE)=0,"",VLOOKUP(A29,專案進度表!$B:$DT,13,FALSE)) | J29: =IF(SUMIFS('PLM001-財務計算用'!$P:$P,'PLM001-財務計算用'!$A:$A,A29)=0,"未登入",SUMIFS('PLM001-財務計算用'!$P:$P,'PLM001-財務計算用'!$A:$A,A29)) -> 722 | K29: =SUMIFS('PLM002'!$K:$K,'PLM002'!$F:$F,$A29) -> 1172.6 | L29: =IF(SUMIFS('PLM002'!$K:$K,'PLM002'!$F:$F,A29,'PLM002'!$J:$J,">="&$B$1,'PLM002'!$J:$J,"<="&$C$1)=0,"未投入",SUMIFS('PLM002'!$K:$K,'PLM002'!$F:$F,A29,'PLM002'!$J:$J,">="&$B$1,'PLM002'!$J:$J,"<="&$C$1)) -> 1172.6 | M29: =VLOOKUP(A29,專案進度表!$B:$DT,18,FALSE) -> 專案延遲 36 天 | N29: =IF(VLOOKUP(A29,'PLM014'!$B:$R,17,FALSE)=0,"",VLOOKUP(A29,'PLM014'!$B:$R,17,FALSE)) -> 45916 | O29: 9/26 召開規格變更會議，確認EUT-POWER 2KV接地也要通過。環境溫度標示，若在常溫，並且水溫80℃時可正常工作，型錄的環境溫度維持60℃的標示。 10/20 已確定高溫80℃的水溫，可以正常工作。 10/28 預計11/6投入工程試製。50PCS 11/14 外殼11/17到貨，預計11/18進產線。 11/14 DN15量測訊號問題，目前尋求探頭更改型式的方式嘗試解決。 | P29: 1.EPU2生產專用測場重新建置。 2.探頭組裝防水膠體填充耗時問題處理 | Q29: 46021
A30: D250803R1 | B30: =VLOOKUP(A30,專案進度表!B:DT,2,FALSE) -> 台大超音波探頭貼合技術技轉案 | C30: =VLOOKUP(A30,專案進度表!$B:$DT,4,FALSE) -> 研三部 | D30: =VLOOKUP(A30,專案進度表!$B:$DT,5,FALSE) -> 陳俊儒 | E30: =VLOOKUP(A30,專案進度表!$B:$DT,6,FALSE) -> Closed | F30: =VLOOKUP(A30,專案進度表!$B:$DT,7,FALSE) -> 45900.667 | G30: =VLOOKUP(A30,專案進度表!$B:$DT,8,FALSE) -> 45988.667 | H30: =IF(VLOOKUP(A30,專案進度表!$B:$DT,12,FALSE)=0,"",VLOOKUP(A30,專案進度表!$B:$DT,12,FALSE)) -> 45939 | I30: =IF(VLOOKUP(A30,專案進度表!$B:$DT,13,FALSE)=0,"",VLOOKUP(A30,專案進度表!$B:$DT,13,FALSE)) -> 46030 | J30: =IF(SUMIFS('PLM001-財務計算用'!$P:$P,'PLM001-財務計算用'!$A:$A,A30)=0,"未登入",SUMIFS('PLM001-財務計算用'!$P:$P,'PLM001-財務計算用'!$A:$A,A30)) -> 未登入 | K30: =SUMIFS('PLM002'!$K:$K,'PLM002'!$F:$F,$A30) -> 253.5 | L30: =IF(SUMIFS('PLM002'!$K:$K,'PLM002'!$F:$F,A30,'PLM002'!$J:$J,">="&$B$1,'PLM002'!$J:$J,"<="&$C$1)=0,"未投入",SUMIFS('PLM002'!$K:$K,'PLM002'!$F:$F,A30,'PLM002'!$J:$J,">="&$B$1,'PLM002'!$J:$J,"<="&$C$1)) -> 253.5 | M30: =VLOOKUP(A30,專案進度表!$B:$DT,18,FALSE) | N30: =IF(VLOOKUP(A30,'PLM014'!$B:$R,17,FALSE)=0,"",VLOOKUP(A30,'PLM014'!$B:$R,17,FALSE)) | O30: 9/26 電路已可正常工作，本週進行實際訊號測試。 10/20 電路測試正常，但EFT 3KV異常處理中。 10/28 EFT 3KV時電源12V異常，尚未查明。 11/4 目前EFT 測試已改善到畫面黑白對調，但產品運作正常的情況，預計本週可以處理完成。 11/14 已送進DVT-QA 11/25 準備Relayout 作業。 | P30: 目前人力不足Debug速度較慢 | Q30: 46021
A32: 產品開發
A33: 專案編號 | B33: 專案名稱 | D33: 專案負責人 | E33: 專案狀態 | F33: 預計起始日 | G33: 預計完成日 | H33: 實際開始日 | I33: 實際完成日 | J33: 預計設工時 | K33: 實際設計工時 | L33: 本週投入設工 | M33: 專案是否異常 | N33: 工況試煉送樣 | O33: 異常說明 | P33: 需要的協助 | Q33: 預計完成日
A34: D240902R1 | B34: =VLOOKUP(A34,專案進度表!B:DT,2,FALSE) -> EPH結構改善與提升生產良率 | C34: =VLOOKUP(A34,專案進度表!$B:$DT,4,FALSE) -> 產品開發 | D34: =VLOOKUP(A34,專案進度表!$B:$DT,5,FALSE) -> 王瀚霆 | E34: =VLOOKUP(A34,專案進度表!$B:$DT,6,FALSE) -> Active | F34: =VLOOKUP(A34,專案進度表!$B:$DT,7,FALSE) -> 45557.667 | G34: =VLOOKUP(A34,專案進度表!$B:$DT,8,FALSE) -> 45620.667 | H34: =IF(VLOOKUP(A34,專案進度表!$B:$DT,12,FALSE)=0,"",VLOOKUP(A34,專案進度表!$B:$DT,12,FALSE)) -> 45558 | I34: =IF(VLOOKUP(A34,專案進度表!$B:$DT,13,FALSE)=0,"",VLOOKUP(A34,專案進度表!$B:$DT,13,FALSE)) | J34: =IF(SUMIFS('PLM001-財務計算用'!$P:$P,'PLM001-財務計算用'!$A:$A,A34)=0,"未登入",SUMIFS('PLM001-財務計算用'!$P:$P,'PLM001-財務計算用'!$A:$A,A34)) -> 220 | K34: =SUMIFS('PLM002'!$K:$K,'PLM002'!$F:$F,$A34) -> 936.5 | L34: =IF(SUMIFS('PLM002'!$K:$K,'PLM002'!$F:$F,A34,'PLM002'!$J:$J,">="&$B$1,'PLM002'!$J:$J,"<="&$C$1)=0,"未投入",SUMIFS('PLM002'!$K:$K,'PLM002'!$F:$F,A34,'PLM002'!$J:$J,">="&$B$1,'PLM002'!$J:$J,"<="&$C$1)) -> 683.5 | M34: =VLOOKUP(A34,專案進度表!$B:$DT,18,FALSE) -> 專案延遲 424 天 | N34: =IF(VLOOKUP(A34,'PLM014'!$B:$R,17,FALSE)=0,"",VLOOKUP(A34,'PLM014'!$B:$R,17,FALSE)) | O34: DN13改善: 多孔式噴嘴(縮小入水孔高度)、氣密墊圈 DN20改善: 多孔式噴嘴(8孔改7孔入水孔、縮小入水孔距離)、氣密墊圈 DN25改善: 多孔式噴嘴(更換為舊DN20)、氣密墊圈、葉片(更換為舊DN20) DN40改善: 多孔式噴嘴(11孔改10孔入水孔、入水孔加大)、支撐環、氣密墊圈 | Q34: DN13~DN40 相關模具、已修改完成。 圖面修改完成(7/31) BOM表變更完成(7/31)
A35: K250501R1 | B35: =VLOOKUP(A35,專案進度表!B:DT,2,FALSE) -> C級奧多曼電子水表先期研究 | C35: =VLOOKUP(A35,專案進度表!$B:$DT,4,FALSE) -> 產品開發 | D35: =VLOOKUP(A35,專案進度表!$B:$DT,5,FALSE) -> 鄭貫中 | E35: =VLOOKUP(A35,專案進度表!$B:$DT,6,FALSE) -> Active | F35: =VLOOKUP(A35,專案進度表!$B:$DT,7,FALSE) -> 45816.667 | G35: =VLOOKUP(A35,專案進度表!$B:$DT,8,FALSE) -> 45883.667 | H35: =IF(VLOOKUP(A35,專案進度表!$B:$DT,12,FALSE)=0,"",VLOOKUP(A35,專案進度表!$B:$DT,12,FALSE)) -> 45811 | I35: =IF(VLOOKUP(A35,專案進度表!$B:$DT,13,FALSE)=0,"",VLOOKUP(A35,專案進度表!$B:$DT,13,FALSE)) | J35: =IF(SUMIFS('PLM001-財務計算用'!$P:$P,'PLM001-財務計算用'!$A:$A,A35)=0,"未登入",SUMIFS('PLM001-財務計算用'!$P:$P,'PLM001-財務計算用'!$A:$A,A35)) -> 462 | K35: =SUMIFS('PLM002'!$K:$K,'PLM002'!$F:$F,$A35) -> 840.5 | L35: =IF(SUMIFS('PLM002'!$K:$K,'PLM002'!$F:$F,A35,'PLM002'!$J:$J,">="&$B$1,'PLM002'!$J:$J,"<="&$C$1)=0,"未投入",SUMIFS('PLM002'!$K:$K,'PLM002'!$F:$F,A35,'PLM002'!$J:$J,">="&$B$1,'PLM002'!$J:$J,"<="&$C$1)) -> 840.5 | M35: =VLOOKUP(A35,專案進度表!$B:$DT,18,FALSE) -> 專案延遲 161 天 | N35: =IF(VLOOKUP(A35,'PLM014'!$B:$R,17,FALSE)=0,"",VLOOKUP(A35,'PLM014'!$B:$R,17,FALSE)) | O35: 結案報告撰寫中
A36: K250501R2 | B36: =VLOOKUP(A36,專案進度表!B:DT,2,FALSE) -> C級奧多曼電子水量計 | C36: =VLOOKUP(A36,專案進度表!$B:$DT,4,FALSE) -> 產品開發 | D36: =VLOOKUP(A36,專案進度表!$B:$DT,5,FALSE) -> 鄭貫中 | E36: =VLOOKUP(A36,專案進度表!$B:$DT,6,FALSE) -> Active | F36: =VLOOKUP(A36,專案進度表!$B:$DT,7,FALSE) -> 46001.667 | G36: =VLOOKUP(A36,專案進度表!$B:$DT,8,FALSE) -> 46324.667 | H36: =IF(VLOOKUP(A36,專案進度表!$B:$DT,12,FALSE)=0,"",VLOOKUP(A36,專案進度表!$B:$DT,12,FALSE)) -> 46013 | I36: =IF(VLOOKUP(A36,專案進度表!$B:$DT,13,FALSE)=0,"",VLOOKUP(A36,專案進度表!$B:$DT,13,FALSE)) | J36: =IF(SUMIFS('PLM001-財務計算用'!$P:$P,'PLM001-財務計算用'!$A:$A,A36)=0,"未登入",SUMIFS('PLM001-財務計算用'!$P:$P,'PLM001-財務計算用'!$A:$A,A36)) -> 840 | K36: =SUMIFS('PLM002'!$K:$K,'PLM002'!$F:$F,$A36) -> 258.5 | L36: =IF(SUMIFS('PLM002'!$K:$K,'PLM002'!$F:$F,A36,'PLM002'!$J:$J,">="&$B$1,'PLM002'!$J:$J,"<="&$C$1)=0,"未投入",SUMIFS('PLM002'!$K:$K,'PLM002'!$F:$F,A36,'PLM002'!$J:$J,">="&$B$1,'PLM002'!$J:$J,"<="&$C$1)) -> 258.5 | M36: =VLOOKUP(A36,專案進度表!$B:$DT,18,FALSE) | N36: =IF(VLOOKUP(A36,'PLM014'!$B:$R,17,FALSE)=0,"",VLOOKUP(A36,'PLM014'!$B:$R,17,FALSE))
A37: K251001R1 | B37: =VLOOKUP(A37,專案進度表!B:DT,2,FALSE) -> EPH水量計型式認證技術規範CNPA49第4版結構驗證與改善 | C37: =VLOOKUP(A37,專案進度表!$B:$DT,4,FALSE) -> 產品開發 | D37: =VLOOKUP(A37,專案進度表!$B:$DT,5,FALSE) -> 王瀚霆 | E37: =VLOOKUP(A37,專案進度表!$B:$DT,6,FALSE) -> Active | F37: =VLOOKUP(A37,專案進度表!$B:$DT,7,FALSE) -> 45985.667 | G37: =VLOOKUP(A37,專案進度表!$B:$DT,8,FALSE) -> 46202.667 | H37: =IF(VLOOKUP(A37,專案進度表!$B:$DT,12,FALSE)=0,"",VLOOKUP(A37,專案進度表!$B:$DT,12,FALSE)) -> 46036 | I37: =IF(VLOOKUP(A37,專案進度表!$B:$DT,13,FALSE)=0,"",VLOOKUP(A37,專案進度表!$B:$DT,13,FALSE)) | J37: =IF(SUMIFS('PLM001-財務計算用'!$P:$P,'PLM001-財務計算用'!$A:$A,A37)=0,"未登入",SUMIFS('PLM001-財務計算用'!$P:$P,'PLM001-財務計算用'!$A:$A,A37)) -> 1011 | K37: =SUMIFS('PLM002'!$K:$K,'PLM002'!$F:$F,$A37) -> 24.5 | L37: =IF(SUMIFS('PLM002'!$K:$K,'PLM002'!$F:$F,A37,'PLM002'!$J:$J,">="&$B$1,'PLM002'!$J:$J,"<="&$C$1)=0,"未投入",SUMIFS('PLM002'!$K:$K,'PLM002'!$F:$F,A37,'PLM002'!$J:$J,">="&$B$1,'PLM002'!$J:$J,"<="&$C$1)) -> 24.5 | M37: =VLOOKUP(A37,專案進度表!$B:$DT,18,FALSE) | N37: =IF(VLOOKUP(A37,'PLM014'!$B:$R,17,FALSE)=0,"",VLOOKUP(A37,'PLM014'!$B:$R,17,FALSE))
A38: M240804R1 | B38: =VLOOKUP(A38,專案進度表!B:DT,2,FALSE) -> PVD二口二位閥展型(DN15、DN20) | C38: =VLOOKUP(A38,專案進度表!$B:$DT,4,FALSE) -> 產品開發 | D38: =VLOOKUP(A38,專案進度表!$B:$DT,5,FALSE) -> 葉宏政 | E38: =VLOOKUP(A38,專案進度表!$B:$DT,6,FALSE) -> Active | F38: =VLOOKUP(A38,專案進度表!$B:$DT,7,FALSE) -> 45529.667 | G38: =VLOOKUP(A38,專案進度表!$B:$DT,8,FALSE) -> 45896.667 | H38: =IF(VLOOKUP(A38,專案進度表!$B:$DT,12,FALSE)=0,"",VLOOKUP(A38,專案進度表!$B:$DT,12,FALSE)) -> 45531 | I38: =IF(VLOOKUP(A38,專案進度表!$B:$DT,13,FALSE)=0,"",VLOOKUP(A38,專案進度表!$B:$DT,13,FALSE)) | J38: =IF(SUMIFS('PLM001-財務計算用'!$P:$P,'PLM001-財務計算用'!$A:$A,A38)=0,"未登入",SUMIFS('PLM001-財務計算用'!$P:$P,'PLM001-財務計算用'!$A:$A,A38)) -> 532 | K38: =SUMIFS('PLM002'!$K:$K,'PLM002'!$F:$F,$A38) -> 1318.5 | L38: =IF(SUMIFS('PLM002'!$K:$K,'PLM002'!$F:$F,A38,'PLM002'!$J:$J,">="&$B$1,'PLM002'!$J:$J,"<="&$C$1)=0,"未投入",SUMIFS('PLM002'!$K:$K,'PLM002'!$F:$F,A38,'PLM002'!$J:$J,">="&$B$1,'PLM002'!$J:$J,"<="&$C$1)) -> 745.5 | M38: =VLOOKUP(A38,專案進度表!$B:$DT,18,FALSE) -> 專案延遲 148 天 | N38: =IF(VLOOKUP(A38,'PLM014'!$B:$R,17,FALSE)=0,"",VLOOKUP(A38,'PLM014'!$B:$R,17,FALSE)) -> 45841
A40: FAE
A41: 專案編號 | B41: 專案名稱 | D41: 專案負責人 | E41: 專案狀態 | F41: 預計起始日 | G41: 預計完成日 | H41: 實際開始日 | I41: 實際完成日 | J41: 預計設工時 | K41: 實際設計工時 | L41: 本週投入設工 | M41: 專案是否異常 | N41: 工況試煉送樣 | O41: 異常說明 | P41: 需要的協助 | Q41: 預計完成日
A42: K240801C1 | B42: =VLOOKUP(A42,專案進度表!B:DT,2,FALSE) -> TS認證查核點-設備監控保護裝置(防爆燈拉繩開關125VDC) | C42: =VLOOKUP(A42,專案進度表!$B:$DT,4,FALSE) -> FAE | D42: =VLOOKUP(A42,專案進度表!$B:$DT,5,FALSE) -> 楊瑞洋 | E42: =VLOOKUP(A42,專案進度表!$B:$DT,6,FALSE) -> Active | F42: =VLOOKUP(A42,專案進度表!$B:$DT,7,FALSE) -> 45526.667 | G42: =VLOOKUP(A42,專案進度表!$B:$DT,8,FALSE) -> 46111.667 | H42: =IF(VLOOKUP(A42,專案進度表!$B:$DT,12,FALSE)=0,"",VLOOKUP(A42,專案進度表!$B:$DT,12,FALSE)) -> 45533 | I42: =IF(VLOOKUP(A42,專案進度表!$B:$DT,13,FALSE)=0,"",VLOOKUP(A42,專案進度表!$B:$DT,13,FALSE)) | J42: =IF(SUMIFS('PLM001-財務計算用'!$P:$P,'PLM001-財務計算用'!$A:$A,A42)=0,"未登入",SUMIFS('PLM001-財務計算用'!$P:$P,'PLM001-財務計算用'!$A:$A,A42)) -> 37 | K42: =SUMIFS('PLM002'!$K:$K,'PLM002'!$F:$F,$A42) -> 0 | L42: =IF(SUMIFS('PLM002'!$K:$K,'PLM002'!$F:$F,A42,'PLM002'!$J:$J,">="&$B$1,'PLM002'!$J:$J,"<="&$C$1)=0,"未投入",SUMIFS('PLM002'!$K:$K,'PLM002'!$F:$F,A42,'PLM002'!$J:$J,">="&$B$1,'PLM002'!$J:$J,"<="&$C$1)) -> 未投入 | M42: =VLOOKUP(A42,專案進度表!$B:$DT,18,FALSE) | N42: =IF(VLOOKUP(A42,'PLM014'!$B:$R,17,FALSE)=0,"",VLOOKUP(A42,'PLM014'!$B:$R,17,FALSE))
A44: 上海
A45: 專案編號 | B45: 專案名稱 | D45: 專案負責人 | E45: 專案狀態 | F45: 預計起始日 | G45: 預計完成日 | H45: 實際開始日 | I45: 實際完成日 | J45: 預計設工時 | K45: 實際設計工時 | L45: 本週投入設工 | M45: 專案是否異常 | N45: 工況試煉送樣 | O45: 異常說明 | P45: 需要的協助 | Q45: 預計完成日
A46: D250301R1 | B46: =VLOOKUP(A46,專案進度表!B:DT,2,FALSE) -> EPD電磁流量計技转 | C46: =VLOOKUP(A46,專案進度表!$B:$DT,4,FALSE) -> 研发一部 | D46: =VLOOKUP(A46,專案進度表!$B:$DT,5,FALSE) -> 汪佳凯 | E46: =VLOOKUP(A46,專案進度表!$B:$DT,6,FALSE) -> Active | F46: =VLOOKUP(A46,專案進度表!$B:$DT,7,FALSE) -> 45872.667 | G46: =VLOOKUP(A46,專案進度表!$B:$DT,8,FALSE) -> 46147.667 | H46: =IF(VLOOKUP(A46,專案進度表!$B:$DT,12,FALSE)=0,"",VLOOKUP(A46,專案進度表!$B:$DT,12,FALSE)) -> 45873 | I46: =IF(VLOOKUP(A46,專案進度表!$B:$DT,13,FALSE)=0,"",VLOOKUP(A46,專案進度表!$B:$DT,13,FALSE)) | J46: =IF(SUMIFS('PLM001-財務計算用'!$P:$P,'PLM001-財務計算用'!$A:$A,A46)=0,"未登入",SUMIFS('PLM001-財務計算用'!$P:$P,'PLM001-財務計算用'!$A:$A,A46)) -> 779 | K46: =SUMIFS('PLM002'!$K:$K,'PLM002'!$F:$F,$A46) -> 0 | L46: =IF(SUMIFS('PLM002'!$K:$K,'PLM002'!$F:$F,A46,'PLM002'!$J:$J,">="&$B$1,'PLM002'!$J:$J,"<="&$C$1)=0,"未投入",SUMIFS('PLM002'!$K:$K,'PLM002'!$F:$F,A46,'PLM002'!$J:$J,">="&$B$1,'PLM002'!$J:$J,"<="&$C$1)) -> 未投入 | M46: =VLOOKUP(A46,專案進度表!$B:$DT,18,FALSE) | N46: =IF(VLOOKUP(A46,'PLM014'!$B:$R,17,FALSE)=0,"",VLOOKUP(A46,'PLM014'!$B:$R,17,FALSE))
A47: D250701R1 | B47: =VLOOKUP(A47,專案進度表!B:DT,2,FALSE) -> EGX5标准型技转 | C47: =VLOOKUP(A47,專案進度表!$B:$DT,4,FALSE) -> 研发一部 | D47: =VLOOKUP(A47,專案進度表!$B:$DT,5,FALSE) -> 汪佳凯 | E47: =VLOOKUP(A47,專案進度表!$B:$DT,6,FALSE) -> Active | F47: =VLOOKUP(A47,專案進度表!$B:$DT,7,FALSE) -> 45872.667 | G47: =VLOOKUP(A47,專案進度表!$B:$DT,8,FALSE) -> 46076.667 | H47: =IF(VLOOKUP(A47,專案進度表!$B:$DT,12,FALSE)=0,"",VLOOKUP(A47,專案進度表!$B:$DT,12,FALSE)) -> 45873 | I47: =IF(VLOOKUP(A47,專案進度表!$B:$DT,13,FALSE)=0,"",VLOOKUP(A47,專案進度表!$B:$DT,13,FALSE)) | J47: =IF(SUMIFS('PLM001-財務計算用'!$P:$P,'PLM001-財務計算用'!$A:$A,A47)=0,"未登入",SUMIFS('PLM001-財務計算用'!$P:$P,'PLM001-財務計算用'!$A:$A,A47)) -> 839 | K47: =SUMIFS('PLM002'!$K:$K,'PLM002'!$F:$F,$A47) -> 0 | L47: =IF(SUMIFS('PLM002'!$K:$K,'PLM002'!$F:$F,A47,'PLM002'!$J:$J,">="&$B$1,'PLM002'!$J:$J,"<="&$C$1)=0,"未投入",SUMIFS('PLM002'!$K:$K,'PLM002'!$F:$F,A47,'PLM002'!$J:$J,">="&$B$1,'PLM002'!$J:$J,"<="&$C$1)) -> 未投入 | M47: =VLOOKUP(A47,專案進度表!$B:$DT,18,FALSE) | N47: =IF(VLOOKUP(A47,'PLM014'!$B:$R,17,FALSE)=0,"",VLOOKUP(A47,'PLM014'!$B:$R,17,FALSE))
A48: D250801R1 | B48: =VLOOKUP(A48,專案進度表!B:DT,2,FALSE) -> SCX6标准/加长型技转 | C48: =VLOOKUP(A48,專案進度表!$B:$DT,4,FALSE) -> 研发一部 | D48: =VLOOKUP(A48,專案進度表!$B:$DT,5,FALSE) -> 郑仁春 | E48: =VLOOKUP(A48,專案進度表!$B:$DT,6,FALSE) -> Active | F48: =VLOOKUP(A48,專案進度表!$B:$DT,7,FALSE) -> 45869.667 | G48: =VLOOKUP(A48,專案進度表!$B:$DT,8,FALSE) -> 45970.667 | H48: =IF(VLOOKUP(A48,專案進度表!$B:$DT,12,FALSE)=0,"",VLOOKUP(A48,專案進度表!$B:$DT,12,FALSE)) -> 45870 | I48: =IF(VLOOKUP(A48,專案進度表!$B:$DT,13,FALSE)=0,"",VLOOKUP(A48,專案進度表!$B:$DT,13,FALSE)) | J48: =IF(SUMIFS('PLM001-財務計算用'!$P:$P,'PLM001-財務計算用'!$A:$A,A48)=0,"未登入",SUMIFS('PLM001-財務計算用'!$P:$P,'PLM001-財務計算用'!$A:$A,A48)) -> 未登入 | K48: =SUMIFS('PLM002'!$K:$K,'PLM002'!$F:$F,$A48) -> 0 | L48: =IF(SUMIFS('PLM002'!$K:$K,'PLM002'!$F:$F,A48,'PLM002'!$J:$J,">="&$B$1,'PLM002'!$J:$J,"<="&$C$1)=0,"未投入",SUMIFS('PLM002'!$K:$K,'PLM002'!$F:$F,A48,'PLM002'!$J:$J,">="&$B$1,'PLM002'!$J:$J,"<="&$C$1)) -> 未投入 | M48: =VLOOKUP(A48,專案進度表!$B:$DT,18,FALSE) -> 專案延遲 74 天 | N48: =IF(VLOOKUP(A48,'PLM014'!$B:$R,17,FALSE)=0,"",VLOOKUP(A48,'PLM014'!$B:$R,17,FALSE))
A49: M240803P1 | B49: =VLOOKUP(A49,專案進度表!B:DT,2,FALSE) -> EGX5防腐型技转 | C49: =VLOOKUP(A49,專案進度表!$B:$DT,4,FALSE) -> 研发一部 | D49: =VLOOKUP(A49,專案進度表!$B:$DT,5,FALSE) -> 汪佳凯 | E49: =VLOOKUP(A49,專案進度表!$B:$DT,6,FALSE) -> Active | F49: =VLOOKUP(A49,專案進度表!$B:$DT,7,FALSE) -> 45963.667 | G49: =VLOOKUP(A49,專案進度表!$B:$DT,8,FALSE) -> 46106.667 | H49: =IF(VLOOKUP(A49,專案進度表!$B:$DT,12,FALSE)=0,"",VLOOKUP(A49,專案進度表!$B:$DT,12,FALSE)) -> 45961 | I49: =IF(VLOOKUP(A49,專案進度表!$B:$DT,13,FALSE)=0,"",VLOOKUP(A49,專案進度表!$B:$DT,13,FALSE)) | J49: =IF(SUMIFS('PLM001-財務計算用'!$P:$P,'PLM001-財務計算用'!$A:$A,A49)=0,"未登入",SUMIFS('PLM001-財務計算用'!$P:$P,'PLM001-財務計算用'!$A:$A,A49)) -> 未登入 | K49: =SUMIFS('PLM002'!$K:$K,'PLM002'!$F:$F,$A49) -> 0 | L49: =IF(SUMIFS('PLM002'!$K:$K,'PLM002'!$F:$F,A49,'PLM002'!$J:$J,">="&$B$1,'PLM002'!$J:$J,"<="&$C$1)=0,"未投入",SUMIFS('PLM002'!$K:$K,'PLM002'!$F:$F,A49,'PLM002'!$J:$J,">="&$B$1,'PLM002'!$J:$J,"<="&$C$1)) -> 未投入 | M49: =VLOOKUP(A49,專案進度表!$B:$DT,18,FALSE) | N49: =IF(VLOOKUP(A49,'PLM014'!$B:$R,17,FALSE)=0,"",VLOOKUP(A49,'PLM014'!$B:$R,17,FALSE))
A52: 自動化
A53: 專案編號 | B53: 專案名稱 | D53: 專案負責人 | E53: 專案狀態 | F53: 預計起始日 | G53: 預計完成日 | H53: 實際開始日 | I53: 實際完成日 | J53: 預計設工時 | K53: 實際設計工時 | L53: 本週投入設工 | M53: 專案是否異常 | N53: 工況試煉送樣 | O53: 異常說明 | P53: 需要的協助 | Q53: 預計完成日
A54: E250101I1 | B54: =VLOOKUP(A54,專案進度表!B:DT,2,FALSE) -> SQ壓力開關調校設備(單顆+步進馬達) | C54: =VLOOKUP(A54,專案進度表!$B:$DT,4,FALSE) -> 自動化 | D54: =VLOOKUP(A54,專案進度表!$B:$DT,5,FALSE) -> 羅友彥 | E54: =VLOOKUP(A54,專案進度表!$B:$DT,6,FALSE) -> Active | F54: =VLOOKUP(A54,專案進度表!$B:$DT,7,FALSE) -> 45788.667 | G54: =VLOOKUP(A54,專案進度表!$B:$DT,8,FALSE) -> 46021.667 | H54: =IF(VLOOKUP(A54,專案進度表!$B:$DT,12,FALSE)=0,"",VLOOKUP(A54,專案進度表!$B:$DT,12,FALSE)) -> 45789 | I54: =IF(VLOOKUP(A54,專案進度表!$B:$DT,13,FALSE)=0,"",VLOOKUP(A54,專案進度表!$B:$DT,13,FALSE)) | J54: =IF(SUMIFS('PLM001-財務計算用'!$P:$P,'PLM001-財務計算用'!$A:$A,A54)=0,"未登入",SUMIFS('PLM001-財務計算用'!$P:$P,'PLM001-財務計算用'!$A:$A,A54)) -> 480 | K54: =SUMIFS('PLM002'!$K:$K,'PLM002'!$F:$F,$A54) -> 304 | L54: =IF(SUMIFS('PLM002'!$K:$K,'PLM002'!$F:$F,A54,'PLM002'!$J:$J,">="&$B$1,'PLM002'!$J:$J,"<="&$C$1)=0,"未投入",SUMIFS('PLM002'!$K:$K,'PLM002'!$F:$F,A54,'PLM002'!$J:$J,">="&$B$1,'PLM002'!$J:$J,"<="&$C$1)) -> 304 | M54: =VLOOKUP(A54,專案進度表!$B:$DT,18,FALSE) -> 專案延遲 23 天 | N54: =IF(VLOOKUP(A54,'PLM014'!$B:$R,17,FALSE)=0,"",VLOOKUP(A54,'PLM014'!$B:$R,17,FALSE))
A55: E251001I1 | B55: =VLOOKUP(A55,專案進度表!B:DT,2,FALSE) -> GPX8溫度校正設備 | C55: =VLOOKUP(A55,專案進度表!$B:$DT,4,FALSE) -> 自動化 | D55: =VLOOKUP(A55,專案進度表!$B:$DT,5,FALSE) -> 羅友彥 | E55: =VLOOKUP(A55,專案進度表!$B:$DT,6,FALSE) -> Active | F55: =VLOOKUP(A55,專案進度表!$B:$DT,7,FALSE) -> 45945.667 | G55: =VLOOKUP(A55,專案進度表!$B:$DT,8,FALSE) -> 46041.667 | H55: =IF(VLOOKUP(A55,專案進度表!$B:$DT,12,FALSE)=0,"",VLOOKUP(A55,專案進度表!$B:$DT,12,FALSE)) -> 45898 | I55: =IF(VLOOKUP(A55,專案進度表!$B:$DT,13,FALSE)=0,"",VLOOKUP(A55,專案進度表!$B:$DT,13,FALSE)) | J55: =IF(SUMIFS('PLM001-財務計算用'!$P:$P,'PLM001-財務計算用'!$A:$A,A55)=0,"未登入",SUMIFS('PLM001-財務計算用'!$P:$P,'PLM001-財務計算用'!$A:$A,A55)) -> 557 | K55: =SUMIFS('PLM002'!$K:$K,'PLM002'!$F:$F,$A55) -> 163 | L55: =IF(SUMIFS('PLM002'!$K:$K,'PLM002'!$F:$F,A55,'PLM002'!$J:$J,">="&$B$1,'PLM002'!$J:$J,"<="&$C$1)=0,"未投入",SUMIFS('PLM002'!$K:$K,'PLM002'!$F:$F,A55,'PLM002'!$J:$J,">="&$B$1,'PLM002'!$J:$J,"<="&$C$1)) -> 163 | M55: =VLOOKUP(A55,專案進度表!$B:$DT,18,FALSE) -> 專案延遲 3 天 | N55: =IF(VLOOKUP(A55,'PLM014'!$B:$R,17,FALSE)=0,"",VLOOKUP(A55,'PLM014'!$B:$R,17,FALSE))
A56: E251002I1 | B56: =VLOOKUP(A56,專案進度表!B:DT,2,FALSE) -> EPT測試台-400cm/s | C56: =VLOOKUP(A56,專案進度表!$B:$DT,4,FALSE) -> 自動化 | D56: =VLOOKUP(A56,專案進度表!$B:$DT,5,FALSE) -> 蘇漢城 | E56: =VLOOKUP(A56,專案進度表!$B:$DT,6,FALSE) -> Active | F56: =VLOOKUP(A56,專案進度表!$B:$DT,7,FALSE) -> 45952.667 | G56: =VLOOKUP(A56,專案進度表!$B:$DT,8,FALSE) -> 46013.667 | H56: =IF(VLOOKUP(A56,專案進度表!$B:$DT,12,FALSE)=0,"",VLOOKUP(A56,專案進度表!$B:$DT,12,FALSE)) | I56: =IF(VLOOKUP(A56,專案進度表!$B:$DT,13,FALSE)=0,"",VLOOKUP(A56,專案進度表!$B:$DT,13,FALSE)) | J56: =IF(SUMIFS('PLM001-財務計算用'!$P:$P,'PLM001-財務計算用'!$A:$A,A56)=0,"未登入",SUMIFS('PLM001-財務計算用'!$P:$P,'PLM001-財務計算用'!$A:$A,A56)) -> 350 | K56: =SUMIFS('PLM002'!$K:$K,'PLM002'!$F:$F,$A56) -> 190.7 | L56: =IF(SUMIFS('PLM002'!$K:$K,'PLM002'!$F:$F,A56,'PLM002'!$J:$J,">="&$B$1,'PLM002'!$J:$J,"<="&$C$1)=0,"未投入",SUMIFS('PLM002'!$K:$K,'PLM002'!$F:$F,A56,'PLM002'!$J:$J,">="&$B$1,'PLM002'!$J:$J,"<="&$C$1)) -> 190.7 | M56: =VLOOKUP(A56,專案進度表!$B:$DT,18,FALSE) -> 專案延遲 31 天 | N56: =IF(VLOOKUP(A56,'PLM014'!$B:$R,17,FALSE)=0,"",VLOOKUP(A56,'PLM014'!$B:$R,17,FALSE))
A57: E251003I1 | B57: =VLOOKUP(A57,專案進度表!B:DT,2,FALSE) -> 小口徑EPH測試台 | C57: =VLOOKUP(A57,專案進度表!$B:$DT,4,FALSE) -> 自動化 | D57: =VLOOKUP(A57,專案進度表!$B:$DT,5,FALSE) -> 蘇漢城 | E57: =VLOOKUP(A57,專案進度表!$B:$DT,6,FALSE) -> Active | F57: =VLOOKUP(A57,專案進度表!$B:$DT,7,FALSE) -> 45952.667 | G57: =VLOOKUP(A57,專案進度表!$B:$DT,8,FALSE) -> 46054.667 | H57: =IF(VLOOKUP(A57,專案進度表!$B:$DT,12,FALSE)=0,"",VLOOKUP(A57,專案進度表!$B:$DT,12,FALSE)) -> 45953 | I57: =IF(VLOOKUP(A57,專案進度表!$B:$DT,13,FALSE)=0,"",VLOOKUP(A57,專案進度表!$B:$DT,13,FALSE)) | J57: =IF(SUMIFS('PLM001-財務計算用'!$P:$P,'PLM001-財務計算用'!$A:$A,A57)=0,"未登入",SUMIFS('PLM001-財務計算用'!$P:$P,'PLM001-財務計算用'!$A:$A,A57)) -> 64 | K57: =SUMIFS('PLM002'!$K:$K,'PLM002'!$F:$F,$A57) -> 432.5 | L57: =IF(SUMIFS('PLM002'!$K:$K,'PLM002'!$F:$F,A57,'PLM002'!$J:$J,">="&$B$1,'PLM002'!$J:$J,"<="&$C$1)=0,"未投入",SUMIFS('PLM002'!$K:$K,'PLM002'!$F:$F,A57,'PLM002'!$J:$J,">="&$B$1,'PLM002'!$J:$J,"<="&$C$1)) -> 432.5 | M57: =VLOOKUP(A57,專案進度表!$B:$DT,18,FALSE) | N57: =IF(VLOOKUP(A57,'PLM014'!$B:$R,17,FALSE)=0,"",VLOOKUP(A57,'PLM014'!$B:$R,17,FALSE))
A58: K201002P2 | B58: =VLOOKUP(A58,專案進度表!B:DT,2,FALSE) -> (K201002R2)SP數位熱質式開關-DC一體型II | C58: =VLOOKUP(A58,專案進度表!$B:$DT,4,FALSE) -> 自動化 | D58: =VLOOKUP(A58,專案進度表!$B:$DT,5,FALSE) -> 蘇漢城 | E58: =VLOOKUP(A58,專案進度表!$B:$DT,6,FALSE) -> Active | F58: =VLOOKUP(A58,專案進度表!$B:$DT,7,FALSE) -> 45665.667 | G58: =VLOOKUP(A58,專案進度表!$B:$DT,8,FALSE) -> 46112.667 | H58: =IF(VLOOKUP(A58,專案進度表!$B:$DT,12,FALSE)=0,"",VLOOKUP(A58,專案進度表!$B:$DT,12,FALSE)) -> 45659 | I58: =IF(VLOOKUP(A58,專案進度表!$B:$DT,13,FALSE)=0,"",VLOOKUP(A58,專案進度表!$B:$DT,13,FALSE)) | J58: =IF(SUMIFS('PLM001-財務計算用'!$P:$P,'PLM001-財務計算用'!$A:$A,A58)=0,"未登入",SUMIFS('PLM001-財務計算用'!$P:$P,'PLM001-財務計算用'!$A:$A,A58)) -> 1598 | K58: =SUMIFS('PLM002'!$K:$K,'PLM002'!$F:$F,$A58) -> 145.8 | L58: =IF(SUMIFS('PLM002'!$K:$K,'PLM002'!$F:$F,A58,'PLM002'!$J:$J,">="&$B$1,'PLM002'!$J:$J,"<="&$C$1)=0,"未投入",SUMIFS('PLM002'!$K:$K,'PLM002'!$F:$F,A58,'PLM002'!$J:$J,">="&$B$1,'PLM002'!$J:$J,"<="&$C$1)) -> 145.8 | M58: =VLOOKUP(A58,專案進度表!$B:$DT,18,FALSE) -> 專案即將異常 | N58: =IF(VLOOKUP(A58,'PLM014'!$B:$R,17,FALSE)=0,"",VLOOKUP(A58,'PLM014'!$B:$R,17,FALSE))
A59: K231101P1 | B59: =VLOOKUP(A59,專案進度表!B:DT,2,FALSE) -> 首次生產-AI伺服器用熱質流量計 | C59: =VLOOKUP(A59,專案進度表!$B:$DT,4,FALSE) -> 自動化 | D59: =VLOOKUP(A59,專案進度表!$B:$DT,5,FALSE) -> 蘇漢城 | E59: =VLOOKUP(A59,專案進度表!$B:$DT,6,FALSE) -> Active | F59: =VLOOKUP(A59,專案進度表!$B:$DT,7,FALSE) -> 45470.667 | G59: =VLOOKUP(A59,專案進度表!$B:$DT,8,FALSE) -> 46021.667 | H59: =IF(VLOOKUP(A59,專案進度表!$B:$DT,12,FALSE)=0,"",VLOOKUP(A59,專案進度表!$B:$DT,12,FALSE)) -> 45481 | I59: =IF(VLOOKUP(A59,專案進度表!$B:$DT,13,FALSE)=0,"",VLOOKUP(A59,專案進度表!$B:$DT,13,FALSE)) | J59: =IF(SUMIFS('PLM001-財務計算用'!$P:$P,'PLM001-財務計算用'!$A:$A,A59)=0,"未登入",SUMIFS('PLM001-財務計算用'!$P:$P,'PLM001-財務計算用'!$A:$A,A59)) -> 728 | K59: =SUMIFS('PLM002'!$K:$K,'PLM002'!$F:$F,$A59) -> 1076.9 | L59: =IF(SUMIFS('PLM002'!$K:$K,'PLM002'!$F:$F,A59,'PLM002'!$J:$J,">="&$B$1,'PLM002'!$J:$J,"<="&$C$1)=0,"未投入",SUMIFS('PLM002'!$K:$K,'PLM002'!$F:$F,A59,'PLM002'!$J:$J,">="&$B$1,'PLM002'!$J:$J,"<="&$C$1)) -> 1032.4 | M59: =VLOOKUP(A59,專案進度表!$B:$DT,18,FALSE) -> 專案延遲 23 天 | N59: =IF(VLOOKUP(A59,'PLM014'!$B:$R,17,FALSE)=0,"",VLOOKUP(A59,'PLM014'!$B:$R,17,FALSE))
A60: K240101P1 | B60: =VLOOKUP(A60,專案進度表!B:DT,2,FALSE) -> 首次生產-渦街流量計商品化 | C60: =VLOOKUP(A60,專案進度表!$B:$DT,4,FALSE) -> 自動化 | D60: =VLOOKUP(A60,專案進度表!$B:$DT,5,FALSE) -> 蘇漢城 | E60: =VLOOKUP(A60,專案進度表!$B:$DT,6,FALSE) -> Active | F60: =VLOOKUP(A60,專案進度表!$B:$DT,7,FALSE) -> 45580.667 | G60: =VLOOKUP(A60,專案進度表!$B:$DT,8,FALSE) -> 46023.667 | H60: =IF(VLOOKUP(A60,專案進度表!$B:$DT,12,FALSE)=0,"",VLOOKUP(A60,專案進度表!$B:$DT,12,FALSE)) -> 45597 | I60: =IF(VLOOKUP(A60,專案進度表!$B:$DT,13,FALSE)=0,"",VLOOKUP(A60,專案進度表!$B:$DT,13,FALSE)) | J60: =IF(SUMIFS('PLM001-財務計算用'!$P:$P,'PLM001-財務計算用'!$A:$A,A60)=0,"未登入",SUMIFS('PLM001-財務計算用'!$P:$P,'PLM001-財務計算用'!$A:$A,A60)) -> 822 | K60: =SUMIFS('PLM002'!$K:$K,'PLM002'!$F:$F,$A60) -> 8 | L60: =IF(SUMIFS('PLM002'!$K:$K,'PLM002'!$F:$F,A60,'PLM002'!$J:$J,">="&$B$1,'PLM002'!$J:$J,"<="&$C$1)=0,"未投入",SUMIFS('PLM002'!$K:$K,'PLM002'!$F:$F,A60,'PLM002'!$J:$J,">="&$B$1,'PLM002'!$J:$J,"<="&$C$1)) -> 未投入 | M60: =VLOOKUP(A60,專案進度表!$B:$DT,18,FALSE) -> 專案延遲 21 天 | N60: =IF(VLOOKUP(A60,'PLM014'!$B:$R,17,FALSE)=0,"",VLOOKUP(A60,'PLM014'!$B:$R,17,FALSE))
A61: M240101P1 | B61: =VLOOKUP(A61,專案進度表!B:DT,2,FALSE) -> 首次生產-液體洩漏偵測器 | C61: =VLOOKUP(A61,專案進度表!$B:$DT,4,FALSE) -> 自動化 | D61: =VLOOKUP(A61,專案進度表!$B:$DT,5,FALSE) -> 蘇漢城 | E61: =VLOOKUP(A61,專案進度表!$B:$DT,6,FALSE) -> Active | F61: =VLOOKUP(A61,專案進度表!$B:$DT,7,FALSE) -> 45580.667 | G61: =VLOOKUP(A61,專案進度表!$B:$DT,8,FALSE) -> 46113.667 | H61: =IF(VLOOKUP(A61,專案進度表!$B:$DT,12,FALSE)=0,"",VLOOKUP(A61,專案進度表!$B:$DT,12,FALSE)) -> 45597 | I61: =IF(VLOOKUP(A61,專案進度表!$B:$DT,13,FALSE)=0,"",VLOOKUP(A61,專案進度表!$B:$DT,13,FALSE)) | J61: =IF(SUMIFS('PLM001-財務計算用'!$P:$P,'PLM001-財務計算用'!$A:$A,A61)=0,"未登入",SUMIFS('PLM001-財務計算用'!$P:$P,'PLM001-財務計算用'!$A:$A,A61)) -> 1823 | K61: =SUMIFS('PLM002'!$K:$K,'PLM002'!$F:$F,$A61) -> 107.5 | L61: =IF(SUMIFS('PLM002'!$K:$K,'PLM002'!$F:$F,A61,'PLM002'!$J:$J,">="&$B$1,'PLM002'!$J:$J,"<="&$C$1)=0,"未投入",SUMIFS('PLM002'!$K:$K,'PLM002'!$F:$F,A61,'PLM002'!$J:$J,">="&$B$1,'PLM002'!$J:$J,"<="&$C$1)) -> 52.5 | M61: =VLOOKUP(A61,專案進度表!$B:$DT,18,FALSE) -> 專案即將異常 | N61: =IF(VLOOKUP(A61,'PLM014'!$B:$R,17,FALSE)=0,"",VLOOKUP(A61,'PLM014'!$B:$R,17,FALSE))

Sheet 專案進度表
B1: 專案總進度表(RD/FAE/上海)
P2: 今天 | Q2: =TODAY() -> 46044
Y3: 研發一處 | AI3: 技術中心 | AS3: 研一部 | BC3: 研二部 | BK3: 研三部 | BS3: 產品開發 | BY3: 離職人員 | CW3: QA | DE3: 行銷 | DI3: FAE | DM3: 上海 | DQ3: 生管 | DS3: 自動化
A4: 專案類別 | B4: 專案編號 | C4: 專案名稱 | D4: 專案名稱 | E4: 部門名稱 | F4: 專案負責人 | G4: 專案狀態 | H4: 預計起始日 | I4: 預計完成日 | J4: 預計專案工期 | K4: 專案(75%) 日期 | L4: 專案(95%) 日期 | M4: 實際開始日 | N4: 實際完成日 | O4: 實際專案工期 | P4: 工期計算用 | Q4: 實際專案工期 | R4: 專案總進度 | S4: 專案是否 異常 | U4: 總設計工時 (hr) | W4: 總工(含其它單位) (hr) | Y4: 許慧芝 | AA4: 林逸舒 | AC4: 王淑瑤 | AE4: 賴慶樺 | AG4: 陳威諭 | AI4: 劉子明 | AK4: 蕭金椿 | AM4: 張文魁 | AO4: 張政崙 | AQ4: 李奕澔 | AS4: 張良琪 | AU4: 何昆達 | AW4: 鄭珅易 | AY4: 陳奕宏 | BA4: 劉益瑋 | BC4: 黃胤綸 | BE4: 莊廉琯 | BG4: 彭志豪 | BI4: 李騏敬 | BK4: 陳俊儒 | BM4: 魏暉恩 | BO4: 蘇哲弘 | BQ4: 許博元 | BS4: 王瀚霆 | BU4: 葉宏政 | BW4: 鄭貫中 | BY4: 陳冠銘 | CA4: 許凱崴 | CC4: 陳子揚 | CE4: 楊浩德 | CG4: 黃价利 | CI4: 黎育誠 | CK4: 簡振芳 | CM4: 江俊毅 | CO4: 丁智軒 | CQ4: 王俊博 | CS4: 洪子芸 | CU4: 蔣永華 | CW4: 王琇眉 | CY4: 余承翰 | DA4: 陳威宏 | DC4: 朱哲演 | DE4: 吳奎雍 | DG4: 吳志嘉 | DI4: 林宏銘 | DK4: 楊瑞洋 | DM4: 郑仁春 | DO4: 汪佳凯 | DQ4: 周家儀 | DS4: 王志文 | DU4: 郭景成 | DW4: 陳威瑜 | DY4: 羅友彥 | EA4: 李育儒 | EC4: 蘇漢城
U5: 預計 | V5: 實際 | W5: 預計 | X5: 實際 | Y5: 預計 | Z5: 實際 | AA5: 預計 | AB5: 實際 | AC5: 預計 | AD5: 實際 | AE5: 預計 | AF5: 實際 | AG5: 預計 | AH5: 實際 | AI5: 預計 | AJ5: 實際 | AK5: 預計 | AL5: 實際 | AM5: 預計 | AN5: 實際 | AO5: 預計 | AP5: 實際 | AQ5: 預計 | AR5: 實際 | AS5: 預計 | AT5: 實際 | AU5: 預計 | AV5: 實際 | AW5: 預計 | AX5: 實際 | AY5: 預計 | AZ5: 實際 | BA5: 預計 | BB5: 實際 | BC5: 預計 | BD5: 實際 | BE5: 預計 | BF5: 實際 | BG5: 預計 | BH5: 實際 | BI5: 預計 | BJ5: 實際 | BK5: 預計 | BL5: 實際 | BM5: 預計 | BN5: 實際 | BO5: 預計 | BP5: 實際 | BQ5: 預計 | BR5: 實際 | BS5: 預計 | BT5: 實際 | BU5: 預計 | BV5: 實際 | BW5: 預計 | BX5: 實際 | BY5: 預計 | BZ5: 實際 | CA5: 預計 | CB5: 實際 | CC5: 預計 | CD5: 實際 | CE5: 預計 | CF5: 實際 | CG5: 預計 | CH5: 實際 | CI5: 預計 | CJ5: 實際 | CK5: 預計 | CL5: 實際 | CM5: 預計 | CN5: 實際 | CO5: 預計 | CP5: 實際 | CQ5: 預計 | CR5: 實際 | CS5: 預計 | CT5: 實際 | CU5: 預計 | CV5: 實際 | CW5: 預計 | CX5: 實際 | CY5: 預計 | CZ5: 實際 | DA5: 預計 | DB5: 實際 | DC5: 預計 | DD5: 實際 | DE5: 預計 | DF5: 實際 | DG5: 預計 | DH5: 實際 | DI5: 預計 | DJ5: 實際 | DK5: 預計 | DL5: 實際 | DM5: 預計 | DN5: 實際 | DO5: 預計 | DP5: 實際 | DQ5: 預計 | DR5: 實際 | DS5: 預計 | DT5: 實際 | DU5: 預計 | DV5: 實際 | DW5: 預計 | DX5: 實際 | DY5: 預計 | DZ5: 實際 | EA5: 預計 | EB5: 實際 | EC5: 預計 | ED5: 實際
A6: ='PLM014'!A7 -> D-協同 | B6: D240902R1 | C6: ='PLM014'!C7 -> EPH結構改善與提升生產良率 | D6: ="("&B6&")"&" "&C6 -> (D240902R1) EPH結構改善與提升生產良率 | E6: ='PLM014'!E7 -> 產品開發 | F6: ='PLM014'!F7 -> 王瀚霆 | G6: ='PLM014'!G7 -> Active | H6: ='PLM014'!H7 -> 45557.667 | I6: ='PLM014'!I7 -> 45620.667 | J6: =IF(ISERROR(DATEDIF(H6,I6,"d")),"",DATEDIF(H6,I6,"d")) -> 63 | K6: =H6+(J6*0.75) -> 45604.917 | L6: =H6+(J6*0.95) -> 45617.517 | M6: =IF(ISERROR('PLM014'!L7),"",('PLM014'!L7)) -> 45558 | N6: =IF(IF(ISERROR('PLM014'!N7),"",('PLM014'!N7))=0,"",IF(ISERROR('PLM014'!N7),"",('PLM014'!N7))) | O6: =IF(ISERROR(DATEDIF(M6,N6,"d")),"",IF(DATEDIF(M6,N6,"d")=0,"",DATEDIF(M6,N6,"d"))) | P6: =IF(N6="",TODAY(),N6) -> 46044 | Q6: =IF(ISERROR(DATEDIF(M6,P6,"d")),"",IF(DATEDIF(M6,P6,"d")=0,"",DATEDIF(M6,P6,"d"))) -> 486 | R6: ='PLM014'!Q7/100 -> 0.97 | S6: =IF(AND(TODAY()>I6,R6<>100%,G6="Active"),"專案延遲 "&DATEDIF(I6,TODAY(),"d")&" 天",IF(AND(TODAY()>K6,R6<75%,G6="Active"),"專案即將異常",IF(AND(TODAY()>L6,R6<95%,G6="Active"),"專案即將異常",""))) -> 專案延遲 424 天 | U6: =IF(SUMIF($Y$5:$CV$5,$U$5,Y6:CV6)=0,"未登入",SUMIF($Y$5:$CV$5,$U$5,Y6:CV6)) -> 220 | V6: =SUMIF($Y$5:$CV$5,$V$5,Y6:CV6) -> 936.5 | W6: =IF(SUMIFS('PLM001-財務計算用'!$P:$P,'PLM001-財務計算用'!$A:$A,B6)=0,"未登入",SUMIFS('PLM001-財務計算用'!$P:$P,'PLM001-財務計算用'!$A:$A,B6)) -> 220 | X6: =SUMIFS('PLM002'!$K:$K,'PLM002'!$F:$F,$B6) -> 936.5 | Y6: =IF(SUMIFS('PLM001-財務計算用'!$P:$P,'PLM001-財務計算用'!$J:$J,Y$4,'PLM001-財務計算用'!$A:$A,$B6)=0,"",SUMIFS('PLM001-財務計算用'!$P:$P,'PLM001-財務計算用'!$J:$J,Y$4,'PLM001-財務計算用'!$A:$A,$B6)) | Z6: =IF(SUMIFS('PLM002'!$K:$K,'PLM002'!$C:$C,Y$4,'PLM002'!$F:$F,$B6)=0,"",SUMIFS('PLM002'!$K:$K,'PLM002'!$C:$C,Y$4,'PLM002'!$F:$F,$B6)) | AA6: =IF(SUMIFS('PLM001-財務計算用'!$P:$P,'PLM001-財務計算用'!$J:$J,AA$4,'PLM001-財務計算用'!$A:$A,$B6)=0,"",SUMIFS('PLM001-財務計算用'!$P:$P,'PLM001-財務計算用'!$J:$J,AA$4,'PLM001-財務計算用'!$A:$A,$B6)) | AB6: =IF(SUMIFS('PLM002'!$K:$K,'PLM002'!$C:$C,AA$4,'PLM002'!$F:$F,$B6)=0,"",SUMIFS('PLM002'!$K:$K,'PLM002'!$C:$C,AA$4,'PLM002'!$F:$F,$B6)) | AC6: =IF(SUMIFS('PLM001-財務計算用'!$P:$P,'PLM001-財務計算用'!$J:$J,AC$4,'PLM001-財務計算用'!$A:$A,$B6)=0,"",SUMIFS('PLM001-財務計算用'!$P:$P,'PLM001-財務計算用'!$J:$J,AC$4,'PLM001-財務計算用'!$A:$A,$B6)) | AD6: =IF(SUMIFS('PLM002'!$K:$K,'PLM002'!$C:$C,AC$4,'PLM002'!$F:$F,$B6)=0,"",SUMIFS('PLM002'!$K:$K,'PLM002'!$C:$C,AC$4,'PLM002'!$F:$F,$B6)) | AE6: =IF(SUMIFS('PLM001-財務計算用'!$P:$P,'PLM001-財務計算用'!$J:$J,AE$4,'PLM001-財務計算用'!$A:$A,$B6)=0,"",SUMIFS('PLM001-財務計算用'!$P:$P,'PLM001-財務計算用'!$J:$J,AE$4,'PLM001-財務計算用'!$A:$A,$B6)) | AF6: =IF(SUMIFS('PLM002'!$K:$K,'PLM002'!$C:$C,AE$4,'PLM002'!$F:$F,$B6)=0,"",SUMIFS('PLM002'!$K:$K,'PLM002'!$C:$C,AE$4,'PLM002'!$F:$F,$B6)) | AG6: =IF(SUMIFS('PLM001-財務計算用'!$P:$P,'PLM001-財務計算用'!$J:$J,AG$4,'PLM001-財務計算用'!$A:$A,$B6)=0,"",SUMIFS('PLM001-財務計算用'!$P:$P,'PLM001-財務計算用'!$J:$J,AG$4,'PLM001-財務計算用'!$A:$A,$B6)) | AH6: =IF(SUMIFS('PLM002'!$K:$K,'PLM002'!$C:$C,AG$4,'PLM002'!$F:$F,$B6)=0,"",SUMIFS('PLM002'!$K:$K,'PLM002'!$C:$C,AG$4,'PLM002'!$F:$F,$B6)) -> 13.5 | AI6: =IF(SUMIFS('PLM001-財務計算用'!$P:$P,'PLM001-財務計算用'!$J:$J,AI$4,'PLM001-財務計算用'!$A:$A,$B6)=0,"",SUMIFS('PLM001-財務計算用'!$P:$P,'PLM001-財務計算用'!$J:$J,AI$4,'PLM001-財務計算用'!$A:$A,$B6)) | AJ6: =IF(SUMIFS('PLM002'!$K:$K,'PLM002'!$C:$C,AI$4,'PLM002'!$F:$F,$B6)=0,"",SUMIFS('PLM002'!$K:$K,'PLM002'!$C:$C,AI$4,'PLM002'!$F:$F,$B6)) | AK6: =IF(SUMIFS('PLM001-財務計算用'!$P:$P,'PLM001-財務計算用'!$J:$J,AK$4,'PLM001-財務計算用'!$A:$A,$B6)=0,"",SUMIFS('PLM001-財務計算用'!$P:$P,'PLM001-財務計算用'!$J:$J,AK$4,'PLM001-財務計算用'!$A:$A,$B6)) | AL6: =IF(SUMIFS('PLM002'!$K:$K,'PLM002'!$C:$C,AK$4,'PLM002'!$F:$F,$B6)=0,"",SUMIFS('PLM002'!$K:$K,'PLM002'!$C:$C,AK$4,'PLM002'!$F:$F,$B6)) | AM6: =IF(SUMIFS('PLM001-財務計算用'!$P:$P,'PLM001-財務計算用'!$J:$J,AM$4,'PLM001-財務計算用'!$A:$A,$B6)=0,"",SUMIFS('PLM001-財務計算用'!$P:$P,'PLM001-財務計算用'!$J:$J,AM$4,'PLM001-財務計算用'!$A:$A,$B6)) | AN6: =IF(SUMIFS('PLM002'!$K:$K,'PLM002'!$C:$C,AM$4,'PLM002'!$F:$F,$B6)=0,"",SUMIFS('PLM002'!$K:$K,'PLM002'!$C:$C,AM$4,'PLM002'!$F:$F,$B6)) | AO6: =IF(SUMIFS('PLM001-財務計算用'!$P:$P,'PLM001-財務計算用'!$J:$J,AO$4,'PLM001-財務計算用'!$A:$A,$B6)=0,"",SUMIFS('PLM001-財務計算用'!$P:$P,'PLM001-財務計算用'!$J:$J,AO$4,'PLM001-財務計算用'!$A:$A,$B6)) | AP6: =IF(SUMIFS('PLM002'!$K:$K,'PLM002'!$C:$C,AO$4,'PLM002'!$F:$F,$B6)=0,"",SUMIFS('PLM002'!$K:$K,'PLM002'!$C:$C,AO$4,'PLM002'!$F:$F,$B6)) | AQ6: =IF(SUMIFS('PLM001-財務計算用'!$P:$P,'PLM001-財務計算用'!$J:$J,AQ$4,'PLM001-財務計算用'!$A:$A,$B6)=0,"",SUMIFS('PLM001-財務計算用'!$P:$P,'PLM001-財務計算用'!$J:$J,AQ$4,'PLM001-財務計算用'!$A:$A,$B6)) | AR6: =IF(SUMIFS('PLM002'!$K:$K,'PLM002'!$C:$C,AQ$4,'PLM002'!$F:$F,$B6)=0,"",SUMIFS('PLM002'!$K:$K,'PLM002'!$C:$C,AQ$4,'PLM002'!$F:$F,$B6)) | AS6: =IF(SUMIFS('PLM001-財務計算用'!$P:$P,'PLM001-財務計算用'!$J:$J,AS$4,'PLM001-財務計算用'!$A:$A,$B6)=0,"",SUMIFS('PLM001-財務計算用'!$P:$P,'PLM001-財務計算用'!$J:$J,AS$4,'PLM001-財務計算用'!$A:$A,$B6)) | AT6: =IF(SUMIFS('PLM002'!$K:$K,'PLM002'!$C:$C,AS$4,'PLM002'!$F:$F,$B6)=0,"",SUMIFS('PLM002'!$K:$K,'PLM002'!$C:$C,AS$4,'PLM002'!$F:$F,$B6)) | AU6: =IF(SUMIFS('PLM001-財務計算用'!$P:$P,'PLM001-財務計算用'!$J:$J,AU$4,'PLM001-財務計算用'!$A:$A,$B6)=0,"",SUMIFS('PLM001-財務計算用'!$P:$P,'PLM001-財務計算用'!$J:$J,AU$4,'PLM001-財務計算用'!$A:$A,$B6)) -> 80 | AV6: =IF(SUMIFS('PLM002'!$K:$K,'PLM002'!$C:$C,AU$4,'PLM002'!$F:$F,$B6)=0,"",SUMIFS('PLM002'!$K:$K,'PLM002'!$C:$C,AU$4,'PLM002'!$F:$F,$B6)) | AW6: =IF(SUMIFS('PLM001-財務計算用'!$P:$P,'PLM001-財務計算用'!$J:$J,AW$4,'PLM001-財務計算用'!$A:$A,$B6)=0,"",SUMIFS('PLM001-財務計算用'!$P:$P,'PLM001-財務計算用'!$J:$J,AW$4,'PLM001-財務計算用'!$A:$A,$B6)) | AX6: =IF(SUMIFS('PLM002'!$K:$K,'PLM002'!$C:$C,AW$4,'PLM002'!$F:$F,$B6)=0,"",SUMIFS('PLM002'!$K:$K,'PLM002'!$C:$C,AW$4,'PLM002'!$F:$F,$B6)) | AY6: =IF(SUMIFS('PLM001-財務計算用'!$P:$P,'PLM001-財務計算用'!$J:$J,AY$4,'PLM001-財務計算用'!$A:$A,$B6)=0,"",SUMIFS('PLM001-財務計算用'!$P:$P,'PLM001-財務計算用'!$J:$J,AY$4,'PLM001-財務計算用'!$A:$A,$B6)) | AZ6: =IF(SUMIFS('PLM002'!$K:$K,'PLM002'!$C:$C,AY$4,'PLM002'!$F:$F,$B6)=0,"",SUMIFS('PLM002'!$K:$K,'PLM002'!$C:$C,AY$4,'PLM002'!$F:$F,$B6)) | BA6: =IF(SUMIFS('PLM001-財務計算用'!$P:$P,'PLM001-財務計算用'!$J:$J,BA$4,'PLM001-財務計算用'!$A:$A,$B6)=0,"",SUMIFS('PLM001-財務計算用'!$P:$P,'PLM001-財務計算用'!$J:$J,BA$4,'PLM001-財務計算用'!$A:$A,$B6)) | BB6: =IF(SUMIFS('PLM002'!$K:$K,'PLM002'!$C:$C,BA$4,'PLM002'!$F:$F,$B6)=0,"",SUMIFS('PLM002'!$K:$K,'PLM002'!$C:$C,BA$4,'PLM002'!$F:$F,$B6)) | BC6: =IF(SUMIFS('PLM001-財務計算用'!$P:$P,'PLM001-財務計算用'!$J:$J,BC$4,'PLM001-財務計算用'!$A:$A,$B6)=0,"",SUMIFS('PLM001-財務計算用'!$P:$P,'PLM001-財務計算用'!$J:$J,BC$4,'PLM001-財務計算用'!$A:$A,$B6)) | BD6: =IF(SUMIFS('PLM002'!$K:$K,'PLM002'!$C:$C,BC$4,'PLM002'!$F:$F,$B6)=0,"",SUMIFS('PLM002'!$K:$K,'PLM002'!$C:$C,BC$4,'PLM002'!$F:$F,$B6)) | BE6: =IF(SUMIFS('PLM001-財務計算用'!$P:$P,'PLM001-財務計算用'!$J:$J,BE$4,'PLM001-財務計算用'!$A:$A,$B6)=0,"",SUMIFS('PLM001-財務計算用'!$P:$P,'PLM001-財務計算用'!$J:$J,BE$4,'PLM001-財務計算用'!$A:$A,$B6)) | BF6: =IF(SUMIFS('PLM002'!$K:$K,'PLM002'!$C:$C,BE$4,'PLM002'!$F:$F,$B6)=0,"",SUMIFS('PLM002'!$K:$K,'PLM002'!$C:$C,BE$4,'PLM002'!$F:$F,$B6)) | BG6: =IF(SUMIFS('PLM001-財務計算用'!$P:$P,'PLM001-財務計算用'!$J:$J,BG$4,'PLM001-財務計算用'!$A:$A,$B6)=0,"",SUMIFS('PLM001-財務計算用'!$P:$P,'PLM001-財務計算用'!$J:$J,BG$4,'PLM001-財務計算用'!$A:$A,$B6)) | BH6: =IF(SUMIFS('PLM002'!$K:$K,'PLM002'!$C:$C,BG$4,'PLM002'!$F:$F,$B6)=0,"",SUMIFS('PLM002'!$K:$K,'PLM002'!$C:$C,BG$4,'PLM002'!$F:$F,$B6)) | BI6: =IF(SUMIFS('PLM001-財務計算用'!$P:$P,'PLM001-財務計算用'!$J:$J,BI$4,'PLM001-財務計算用'!$A:$A,$B6)=0,"",SUMIFS('PLM001-財務計算用'!$P:$P,'PLM001-財務計算用'!$J:$J,BI$4,'PLM001-財務計算用'!$A:$A,$B6)) | BJ6: =IF(SUMIFS('PLM002'!$K:$K,'PLM002'!$C:$C,BI$4,'PLM002'!$F:$F,$B6)=0,"",SUMIFS('PLM002'!$K:$K,'PLM002'!$C:$C,BI$4,'PLM002'!$F:$F,$B6)) | BK6: =IF(SUMIFS('PLM001-財務計算用'!$P:$P,'PLM001-財務計算用'!$J:$J,BK$4,'PLM001-財務計算用'!$A:$A,$B6)=0,"",SUMIFS('PLM001-財務計算用'!$P:$P,'PLM001-財務計算用'!$J:$J,BK$4,'PLM001-財務計算用'!$A:$A,$B6)) | BL6: =IF(SUMIFS('PLM002'!$K:$K,'PLM002'!$C:$C,BK$4,'PLM002'!$F:$F,$B6)=0,"",SUMIFS('PLM002'!$K:$K,'PLM002'!$C:$C,BK$4,'PLM002'!$F:$F,$B6)) | BM6: =IF(SUMIFS('PLM001-財務計算用'!$P:$P,'PLM001-財務計算用'!$J:$J,BM$4,'PLM001-財務計算用'!$A:$A,$B6)=0,"",SUMIFS('PLM001-財務計算用'!$P:$P,'PLM001-財務計算用'!$J:$J,BM$4,'PLM001-財務計算用'!$A:$A,$B6)) | BN6: =IF(SUMIFS('PLM002'!$K:$K,'PLM002'!$C:$C,BM$4,'PLM002'!$F:$F,$B6)=0,"",SUMIFS('PLM002'!$K:$K,'PLM002'!$C:$C,BM$4,'PLM002'!$F:$F,$B6)) | BO6: =IF(SUMIFS('PLM001-財務計算用'!$P:$P,'PLM001-財務計算用'!$J:$J,BO$4,'PLM001-財務計算用'!$A:$A,$B6)=0,"",SUMIFS('PLM001-財務計算用'!$P:$P,'PLM001-財務計算用'!$J:$J,BO$4,'PLM001-財務計算用'!$A:$A,$B6)) | BP6: =IF(SUMIFS('PLM002'!$K:$K,'PLM002'!$C:$C,BO$4,'PLM002'!$F:$F,$B6)=0,"",SUMIFS('PLM002'!$K:$K,'PLM002'!$C:$C,BO$4,'PLM002'!$F:$F,$B6)) | BQ6: =IF(SUMIFS('PLM001-財務計算用'!$P:$P,'PLM001-財務計算用'!$J:$J,BQ$4,'PLM001-財務計算用'!$A:$A,$B6)=0,"",SUMIFS('PLM001-財務計算用'!$P:$P,'PLM001-財務計算用'!$J:$J,BQ$4,'PLM001-財務計算用'!$A:$A,$B6)) | BR6: =IF(SUMIFS('PLM002'!$K:$K,'PLM002'!$C:$C,BQ$4,'PLM002'!$F:$F,$B6)=0,"",SUMIFS('PLM002'!$K:$K,'PLM002'!$C:$C,BQ$4,'PLM002'!$F:$F,$B6)) | BS6: =IF(SUMIFS('PLM001-財務計算用'!$P:$P,'PLM001-財務計算用'!$J:$J,BS$4,'PLM001-財務計算用'!$A:$A,$B6)=0,"",SUMIFS('PLM001-財務計算用'!$P:$P,'PLM001-財務計算用'!$J:$J,BS$4,'PLM001-財務計算用'!$A:$A,$B6)) -> 116 | BT6: =IF(SUMIFS('PLM002'!$K:$K,'PLM002'!$C:$C,BS$4,'PLM002'!$F:$F,$B6)=0,"",SUMIFS('PLM002'!$K:$K,'PLM002'!$C:$C,BS$4,'PLM002'!$F:$F,$B6)) -> 818.5 | BU6: =IF(SUMIFS('PLM001-財務計算用'!$P:$P,'PLM001-財務計算用'!$J:$J,BU$4,'PLM001-財務計算用'!$A:$A,$B6)=0,"",SUMIFS('PLM001-財務計算用'!$P:$P,'PLM001-財務計算用'!$J:$J,BU$4,'PLM001-財務計算用'!$A:$A,$B6)) | BV6: =IF(SUMIFS('PLM002'!$K:$K,'PLM002'!$C:$C,BU$4,'PLM002'!$F:$F,$B6)=0,"",SUMIFS('PLM002'!$K:$K,'PLM002'!$C:$C,BU$4,'PLM002'!$F:$F,$B6)) -> 18.5 | BW6: =IF(SUMIFS('PLM001-財務計算用'!$P:$P,'PLM001-財務計算用'!$J:$J,BW$4,'PLM001-財務計算用'!$A:$A,$B6)=0,"",SUMIFS('PLM001-財務計算用'!$P:$P,'PLM001-財務計算用'!$J:$J,BW$4,'PLM001-財務計算用'!$A:$A,$B6)) | BX6: =IF(SUMIFS('PLM002'!$K:$K,'PLM002'!$C:$C,BW$4,'PLM002'!$F:$F,$B6)=0,"",SUMIFS('PLM002'!$K:$K,'PLM002'!$C:$C,BW$4,'PLM002'!$F:$F,$B6)) -> 86 | BY6: =IF(SUMIFS('PLM001-財務計算用'!$P:$P,'PLM001-財務計算用'!$J:$J,BY$4,'PLM001-財務計算用'!$A:$A,$B6)=0,"",SUMIFS('PLM001-財務計算用'!$P:$P,'PLM001-財務計算用'!$J:$J,BY$4,'PLM001-財務計算用'!$A:$A,$B6)) | BZ6: =IF(SUMIFS('PLM002'!$K:$K,'PLM002'!$C:$C,BY$4,'PLM002'!$F:$F,$B6)=0,"",SUMIFS('PLM002'!$K:$K,'PLM002'!$C:$C,BY$4,'PLM002'!$F:$F,$B6)) | CA6: =IF(SUMIFS('PLM001-財務計算用'!$P:$P,'PLM001-財務計算用'!$J:$J,CA$4,'PLM001-財務計算用'!$A:$A,$B6)=0,"",SUMIFS('PLM001-財務計算用'!$P:$P,'PLM001-財務計算用'!$J:$J,CA$4,'PLM001-財務計算用'!$A:$A,$B6)) | CB6: =IF(SUMIFS('PLM002'!$K:$K,'PLM002'!$C:$C,CA$4,'PLM002'!$F:$F,$B6)=0,"",SUMIFS('PLM002'!$K:$K,'PLM002'!$C:$C,CA$4,'PLM002'!$F:$F,$B6)) | CC6: =IF(SUMIFS('PLM001-財務計算用'!$P:$P,'PLM001-財務計算用'!$J:$J,CC$4,'PLM001-財務計算用'!$A:$A,$B6)=0,"",SUMIFS('PLM001-財務計算用'!$P:$P,'PLM001-財務計算用'!$J:$J,CC$4,'PLM001-財務計算用'!$A:$A,$B6)) | CD6: =IF(SUMIFS('PLM002'!$K:$K,'PLM002'!$C:$C,CC$4,'PLM002'!$F:$F,$B6)=0,"",SUMIFS('PLM002'!$K:$K,'PLM002'!$C:$C,CC$4,'PLM002'!$F:$F,$B6)) | CE6: =IF(SUMIFS('PLM001-財務計算用'!$P:$P,'PLM001-財務計算用'!$J:$J,CE$4,'PLM001-財務計算用'!$A:$A,$B6)=0,"",SUMIFS('PLM001-財務計算用'!$P:$P,'PLM001-財務計算用'!$J:$J,CE$4,'PLM001-財務計算用'!$A:$A,$B6)) | CF6: =IF(SUMIFS('PLM002'!$K:$K,'PLM002'!$C:$C,CE$4,'PLM002'!$F:$F,$B6)=0,"",SUMIFS('PLM002'!$K:$K,'PLM002'!$C:$C,CE$4,'PLM002'!$F:$F,$B6)) | CG6: =IF(SUMIFS('PLM001-財務計算用'!$P:$P,'PLM001-財務計算用'!$J:$J,CG$4,'PLM001-財務計算用'!$A:$A,$B6)=0,"",SUMIFS('PLM001-財務計算用'!$P:$P,'PLM001-財務計算用'!$J:$J,CG$4,'PLM001-財務計算用'!$A:$A,$B6)) | CH6: =IF(SUMIFS('PLM002'!$K:$K,'PLM002'!$C:$C,CG$4,'PLM002'!$F:$F,$B6)=0,"",SUMIFS('PLM002'!$K:$K,'PLM002'!$C:$C,CG$4,'PLM002'!$F:$F,$B6)) | CI6: =IF(SUMIFS('PLM001-財務計算用'!$P:$P,'PLM001-財務計算用'!$J:$J,CI$4,'PLM001-財務計算用'!$A:$A,$B6)=0,"",SUMIFS('PLM001-財務計算用'!$P:$P,'PLM001-財務計算用'!$J:$J,CI$4,'PLM001-財務計算用'!$A:$A,$B6)) | CJ6: =IF(SUMIFS('PLM002'!$K:$K,'PLM002'!$C:$C,CI$4,'PLM002'!$F:$F,$B6)=0,"",SUMIFS('PLM002'!$K:$K,'PLM002'!$C:$C,CI$4,'PLM002'!$F:$F,$B6)) | CK6: =IF(SUMIFS('PLM001-財務計算用'!$P:$P,'PLM001-財務計算用'!$J:$J,CK$4,'PLM001-財務計算用'!$A:$A,$B6)=0,"",SUMIFS('PLM001-財務計算用'!$P:$P,'PLM001-財務計算用'!$J:$J,CK$4,'PLM001-財務計算用'!$A:$A,$B6)) | CL6: =IF(SUMIFS('PLM002'!$K:$K,'PLM002'!$C:$C,CK$4,'PLM002'!$F:$F,$B6)=0,"",SUMIFS('PLM002'!$K:$K,'PLM002'!$C:$C,CK$4,'PLM002'!$F:$F,$B6)) | CM6: =IF(SUMIFS('PLM001-財務計算用'!$P:$P,'PLM001-財務計算用'!$J:$J,CM$4,'PLM001-財務計算用'!$A:$A,$B6)=0,"",SUMIFS('PLM001-財務計算用'!$P:$P,'PLM001-財務計算用'!$J:$J,CM$4,'PLM001-財務計算用'!$A:$A,$B6)) | CN6: =IF(SUMIFS('PLM002'!$K:$K,'PLM002'!$C:$C,CM$4,'PLM002'!$F:$F,$B6)=0,"",SUMIFS('PLM002'!$K:$K,'PLM002'!$C:$C,CM$4,'PLM002'!$F:$F,$B6)) | CO6: =IF(SUMIFS('PLM001-財務計算用'!$P:$P,'PLM001-財務計算用'!$J:$J,CO$4,'PLM001-財務計算用'!$A:$A,$B6)=0,"",SUMIFS('PLM001-財務計算用'!$P:$P,'PLM001-財務計算用'!$J:$J,CO$4,'PLM001-財務計算用'!$A:$A,$B6)) | CP6: =IF(SUMIFS('PLM002'!$K:$K,'PLM002'!$C:$C,CO$4,'PLM002'!$F:$F,$B6)=0,"",SUMIFS('PLM002'!$K:$K,'PLM002'!$C:$C,CO$4,'PLM002'!$F:$F,$B6)) | CQ6: =IF(SUMIFS('PLM001-財務計算用'!$P:$P,'PLM001-財務計算用'!$J:$J,CQ$4,'PLM001-財務計算用'!$A:$A,$B6)=0,"",SUMIFS('PLM001-財務計算用'!$P:$P,'PLM001-財務計算用'!$J:$J,CQ$4,'PLM001-財務計算用'!$A:$A,$B6)) | CR6: =IF(SUMIFS('PLM002'!$K:$K,'PLM002'!$C:$C,CQ$4,'PLM002'!$F:$F,$B6)=0,"",SUMIFS('PLM002'!$K:$K,'PLM002'!$C:$C,CQ$4,'PLM002'!$F:$F,$B6)) | CS6: =IF(SUMIFS('PLM001-財務計算用'!$P:$P,'PLM001-財務計算用'!$J:$J,CS$4,'PLM001-財務計算用'!$A:$A,$B6)=0,"",SUMIFS('PLM001-財務計算用'!$P:$P,'PLM001-財務計算用'!$J:$J,CS$4,'PLM001-財務計算用'!$A:$A,$B6)) -> 24 | CT6: =IF(SUMIFS('PLM002'!$K:$K,'PLM002'!$C:$C,CS$4,'PLM002'!$F:$F,$B6)=0,"",SUMIFS('PLM002'!$K:$K,'PLM002'!$C:$C,CS$4,'PLM002'!$F:$F,$B6)) | CU6: =IF(SUMIFS('PLM001-財務計算用'!$P:$P,'PLM001-財務計算用'!$J:$J,CU$4,'PLM001-財務計算用'!$A:$A,$B6)=0,"",SUMIFS('PLM001-財務計算用'!$P:$P,'PLM001-財務計算用'!$J:$J,CU$4,'PLM001-財務計算用'!$A:$A,$B6)) | CV6: =IF(SUMIFS('PLM002'!$K:$K,'PLM002'!$C:$C,CU$4,'PLM002'!$F:$F,$B6)=0,"",SUMIFS('PLM002'!$K:$K,'PLM002'!$C:$C,CU$4,'PLM002'!$F:$F,$B6)) | CW6: =IF(SUMIFS('PLM001-財務計算用'!$P:$P,'PLM001-財務計算用'!$J:$J,CW$4,'PLM001-財務計算用'!$A:$A,$B6)=0,"",SUMIFS('PLM001-財務計算用'!$P:$P,'PLM001-財務計算用'!$J:$J,CW$4,'PLM001-財務計算用'!$A:$A,$B6)) | CX6: =IF(SUMIFS('PLM002'!$K:$K,'PLM002'!$C:$C,CW$4,'PLM002'!$F:$F,$B6)=0,"",SUMIFS('PLM002'!$K:$K,'PLM002'!$C:$C,CW$4,'PLM002'!$F:$F,$B6)) | CY6: =IF(SUMIFS('PLM001-財務計算用'!$P:$P,'PLM001-財務計算用'!$J:$J,CY$4,'PLM001-財務計算用'!$A:$A,$B6)=0,"",SUMIFS('PLM001-財務計算用'!$P:$P,'PLM001-財務計算用'!$J:$J,CY$4,'PLM001-財務計算用'!$A:$A,$B6)) | CZ6: =IF(SUMIFS('PLM002'!$K:$K,'PLM002'!$C:$C,CY$4,'PLM002'!$F:$F,$B6)=0,"",SUMIFS('PLM002'!$K:$K,'PLM002'!$C:$C,CY$4,'PLM002'!$F:$F,$B6)) | DA6: =IF(SUMIFS('PLM001-財務計算用'!$P:$P,'PLM001-財務計算用'!$J:$J,DA$4,'PLM001-財務計算用'!$A:$A,$B6)=0,"",SUMIFS('PLM001-財務計算用'!$P:$P,'PLM001-財務計算用'!$J:$J,DA$4,'PLM001-財務計算用'!$A:$A,$B6)) | DB6: =IF(SUMIFS('PLM002'!$K:$K,'PLM002'!$C:$C,DA$4,'PLM002'!$F:$F,$B6)=0,"",SUMIFS('PLM002'!$K:$K,'PLM002'!$C:$C,DA$4,'PLM002'!$F:$F,$B6)) | DC6: =IF(SUMIFS('PLM001-財務計算用'!$P:$P,'PLM001-財務計算用'!$J:$J,DC$4,'PLM001-財務計算用'!$A:$A,$B6)=0,"",SUMIFS('PLM001-財務計算用'!$P:$P,'PLM001-財務計算用'!$J:$J,DC$4,'PLM001-財務計算用'!$A:$A,$B6)) | DD6: =IF(SUMIFS('PLM002'!$K:$K,'PLM002'!$C:$C,DC$4,'PLM002'!$F:$F,$B6)=0,"",SUMIFS('PLM002'!$K:$K,'PLM002'!$C:$C,DC$4,'PLM002'!$F:$F,$B6)) | DE6: =IF(SUMIFS('PLM001-財務計算用'!$P:$P,'PLM001-財務計算用'!$J:$J,DE$4,'PLM001-財務計算用'!$A:$A,$B6)=0,"",SUMIFS('PLM001-財務計算用'!$P:$P,'PLM001-財務計算用'!$J:$J,DE$4,'PLM001-財務計算用'!$A:$A,$B6)) | DF6: =IF(SUMIFS('PLM002'!$K:$K,'PLM002'!$C:$C,DE$4,'PLM002'!$F:$F,$B6)=0,"",SUMIFS('PLM002'!$K:$K,'PLM002'!$C:$C,DE$4,'PLM002'!$F:$F,$B6)) | DG6: =IF(SUMIFS('PLM001-財務計算用'!$P:$P,'PLM001-財務計算用'!$J:$J,DG$4,'PLM001-財務計算用'!$A:$A,$B6)=0,"",SUMIFS('PLM001-財務計算用'!$P:$P,'PLM001-財務計算用'!$J:$J,DG$4,'PLM001-財務計算用'!$A:$A,$B6)) | DH6: =IF(SUMIFS('PLM002'!$K:$K,'PLM002'!$C:$C,DG$4,'PLM002'!$F:$F,$B6)=0,"",SUMIFS('PLM002'!$K:$K,'PLM002'!$C:$C,DG$4,'PLM002'!$F:$F,$B6)) | DI6: =IF(SUMIFS('PLM001-財務計算用'!$P:$P,'PLM001-財務計算用'!$J:$J,DI$4,'PLM001-財務計算用'!$A:$A,$B6)=0,"",SUMIFS('PLM001-財務計算用'!$P:$P,'PLM001-財務計算用'!$J:$J,DI$4,'PLM001-財務計算用'!$A:$A,$B6)) | DJ6: =IF(SUMIFS('PLM002'!$K:$K,'PLM002'!$C:$C,DI$4,'PLM002'!$F:$F,$B6)=0,"",SUMIFS('PLM002'!$K:$K,'PLM002'!$C:$C,DI$4,'PLM002'!$F:$F,$B6)) | DK6: =IF(SUMIFS('PLM001-財務計算用'!$P:$P,'PLM001-財務計算用'!$J:$J,DK$4,'PLM001-財務計算用'!$A:$A,$B6)=0,"",SUMIFS('PLM001-財務計算用'!$P:$P,'PLM001-財務計算用'!$J:$J,DK$4,'PLM001-財務計算用'!$A:$A,$B6)) | DL6: =IF(SUMIFS('PLM002'!$K:$K,'PLM002'!$C:$C,DK$4,'PLM002'!$F:$F,$B6)=0,"",SUMIFS('PLM002'!$K:$K,'PLM002'!$C:$C,DK$4,'PLM002'!$F:$F,$B6)) | DM6: =IF(SUMIFS('PLM001-財務計算用'!$P:$P,'PLM001-財務計算用'!$J:$J,DM$4,'PLM001-財務計算用'!$A:$A,$B6)=0,"",SUMIFS('PLM001-財務計算用'!$P:$P,'PLM001-財務計算用'!$J:$J,DM$4,'PLM001-財務計算用'!$A:$A,$B6)) | DN6: =IF(SUMIFS('PLM002'!$K:$K,'PLM002'!$C:$C,DM$4,'PLM002'!$F:$F,$B6)=0,"",SUMIFS('PLM002'!$K:$K,'PLM002'!$C:$C,DM$4,'PLM002'!$F:$F,$B6)) | DO6: =IF(SUMIFS('PLM001-財務計算用'!$P:$P,'PLM001-財務計算用'!$J:$J,DO$4,'PLM001-財務計算用'!$A:$A,$B6)=0,"",SUMIFS('PLM001-財務計算用'!$P:$P,'PLM001-財務計算用'!$J:$J,DO$4,'PLM001-財務計算用'!$A:$A,$B6)) | DP6: =IF(SUMIFS('PLM002'!$K:$K,'PLM002'!$C:$C,DO$4,'PLM002'!$F:$F,$B6)=0,"",SUMIFS('PLM002'!$K:$K,'PLM002'!$C:$C,DO$4,'PLM002'!$F:$F,$B6)) | DQ6: =IF(SUMIFS('PLM001-財務計算用'!$P:$P,'PLM001-財務計算用'!$J:$J,DQ$4,'PLM001-財務計算用'!$A:$A,$B6)=0,"",SUMIFS('PLM001-財務計算用'!$P:$P,'PLM001-財務計算用'!$J:$J,DQ$4,'PLM001-財務計算用'!$A:$A,$B6)) | DR6: =IF(SUMIFS('PLM002'!$K:$K,'PLM002'!$C:$C,DQ$4,'PLM002'!$F:$F,$B6)=0,"",SUMIFS('PLM002'!$K:$K,'PLM002'!$C:$C,DQ$4,'PLM002'!$F:$F,$B6)) | DS6: =IF(SUMIFS('PLM001-財務計算用'!$P:$P,'PLM001-財務計算用'!$J:$J,DS$4,'PLM001-財務計算用'!$A:$A,$B6)=0,"",SUMIFS('PLM001-財務計算用'!$P:$P,'PLM001-財務計算用'!$J:$J,DS$4,'PLM001-財務計算用'!$A:$A,$B6)) | DT6: =IF(SUMIFS('PLM002'!$K:$K,'PLM002'!$C:$C,DS$4,'PLM002'!$F:$F,$B6)=0,"",SUMIFS('PLM002'!$K:$K,'PLM002'!$C:$C,DS$4,'PLM002'!$F:$F,$B6)) | DU6: =IF(SUMIFS('PLM001-財務計算用'!$P:$P,'PLM001-財務計算用'!$J:$J,DU$4,'PLM001-財務計算用'!$A:$A,$B6)=0,"",SUMIFS('PLM001-財務計算用'!$P:$P,'PLM001-財務計算用'!$J:$J,DU$4,'PLM001-財務計算用'!$A:$A,$B6)) | DV6: =IF(SUMIFS('PLM002'!$K:$K,'PLM002'!$C:$C,DU$4,'PLM002'!$F:$F,$B6)=0,"",SUMIFS('PLM002'!$K:$K,'PLM002'!$C:$C,DU$4,'PLM002'!$F:$F,$B6)) | DW6: =IF(SUMIFS('PLM001-財務計算用'!$P:$P,'PLM001-財務計算用'!$J:$J,DW$4,'PLM001-財務計算用'!$A:$A,$B6)=0,"",SUMIFS('PLM001-財務計算用'!$P:$P,'PLM001-財務計算用'!$J:$J,DW$4,'PLM001-財務計算用'!$A:$A,$B6)) | DX6: =IF(SUMIFS('PLM002'!$K:$K,'PLM002'!$C:$C,DW$4,'PLM002'!$F:$F,$B6)=0,"",SUMIFS('PLM002'!$K:$K,'PLM002'!$C:$C,DW$4,'PLM002'!$F:$F,$B6)) | DY6: =IF(SUMIFS('PLM001-財務計算用'!$P:$P,'PLM001-財務計算用'!$J:$J,DY$4,'PLM001-財務計算用'!$A:$A,$B6)=0,"",SUMIFS('PLM001-財務計算用'!$P:$P,'PLM001-財務計算用'!$J:$J,DY$4,'PLM001-財務計算用'!$A:$A,$B6)) | DZ6: =IF(SUMIFS('PLM002'!$K:$K,'PLM002'!$C:$C,DY$4,'PLM002'!$F:$F,$B6)=0,"",SUMIFS('PLM002'!$K:$K,'PLM002'!$C:$C,DY$4,'PLM002'!$F:$F,$B6)) | EA6: =IF(SUMIFS('PLM001-財務計算用'!$P:$P,'PLM001-財務計算用'!$J:$J,EA$4,'PLM001-財務計算用'!$A:$A,$B6)=0,"",SUMIFS('PLM001-財務計算用'!$P:$P,'PLM001-財務計算用'!$J:$J,EA$4,'PLM001-財務計算用'!$A:$A,$B6)) | EB6: =IF(SUMIFS('PLM002'!$K:$K,'PLM002'!$C:$C,EA$4,'PLM002'!$F:$F,$B6)=0,"",SUMIFS('PLM002'!$K:$K,'PLM002'!$C:$C,EA$4,'PLM002'!$F:$F,$B6)) | EC6: =IF(SUMIFS('PLM001-財務計算用'!$P:$P,'PLM001-財務計算用'!$J:$J,EC$4,'PLM001-財務計算用'!$A:$A,$B6)=0,"",SUMIFS('PLM001-財務計算用'!$P:$P,'PLM001-財務計算用'!$J:$J,EC$4,'PLM001-財務計算用'!$A:$A,$B6)) | ED6: =IF(SUMIFS('PLM002'!$K:$K,'PLM002'!$C:$C,EC$4,'PLM002'!$F:$F,$B6)=0,"",SUMIFS('PLM002'!$K:$K,'PLM002'!$C:$C,EC$4,'PLM002'!$F:$F,$B6))
A7: ='PLM014'!A8 -> D-協同 | B7: D250101R1 | C7: ='PLM014'!C8 -> AI冷卻系統數位通訊溫度偵測器 | D7: ="("&B7&")"&" "&C7 -> (D250101R1) AI冷卻系統數位通訊溫度偵測器 | E7: ='PLM014'!E8 -> 研二部 | F7: ='PLM014'!F8 -> 黃胤綸 | G7: ='PLM014'!G8 -> Active | H7: ='PLM014'!H8 -> 45669.667 | I7: ='PLM014'!I8 -> 45776.667 | J7: =IF(ISERROR(DATEDIF(H7,I7,"d")),"",DATEDIF(H7,I7,"d")) -> 107 | K7: =H7+(J7*0.75) -> 45749.917 | L7: =H7+(J7*0.95) -> 45771.317 | M7: =IF(ISERROR('PLM014'!L8),"",('PLM014'!L8)) -> 45670 | N7: =IF(IF(ISERROR('PLM014'!N8),"",('PLM014'!N8))=0,"",IF(ISERROR('PLM014'!N8),"",('PLM014'!N8))) | O7: =IF(ISERROR(DATEDIF(M7,N7,"d")),"",IF(DATEDIF(M7,N7,"d")=0,"",DATEDIF(M7,N7,"d"))) | P7: =IF(N7="",TODAY(),N7) -> 46044 | Q7: =IF(ISERROR(DATEDIF(M7,P7,"d")),"",IF(DATEDIF(M7,P7,"d")=0,"",DATEDIF(M7,P7,"d"))) -> 374 | R7: ='PLM014'!Q8/100 -> 0.88 | S7: =IF(AND(TODAY()>I7,R7<>100%,G7="Active"),"專案延遲 "&DATEDIF(I7,TODAY(),"d")&" 天",IF(AND(TODAY()>K7,R7<75%,G7="Active"),"專案即將異常",IF(AND(TODAY()>L7,R7<95%,G7="Active"),"專案即將異常",""))) -> 專案延遲 268 天 | U7: =IF(SUMIF($Y$5:$CV$5,$U$5,Y7:CV7)=0,"未登入",SUMIF($Y$5:$CV$5,$U$5,Y7:CV7)) -> 695 | V7: =SUMIF($Y$5:$CV$5,$V$5,Y7:CV7) -> 1258 | W7: =IF(SUMIFS('PLM001-財務計算用'!$P:$P,'PLM001-財務計算用'!$A:$A,B7)=0,"未登入",SUMIFS('PLM001-財務計算用'!$P:$P,'PLM001-財務計算用'!$A:$A,B7)) -> 795 | X7: =SUMIFS('PLM002'!$K:$K,'PLM002'!$F:$F,$B7) -> 1258 | Y7: =IF(SUMIFS('PLM001-財務計算用'!$P:$P,'PLM001-財務計算用'!$J:$J,Y$4,'PLM001-財務計算用'!$A:$A,$B7)=0,"",SUMIFS('PLM001-財務計算用'!$P:$P,'PLM001-財務計算用'!$J:$J,Y$4,'PLM001-財務計算用'!$A:$A,$B7)) -> 18 | Z7: =IF(SUMIFS('PLM002'!$K:$K,'PLM002'!$C:$C,Y$4,'PLM002'!$F:$F,$B7)=0,"",SUMIFS('PLM002'!$K:$K,'PLM002'!$C:$C,Y$4,'PLM002'!$F:$F,$B7)) -> 57.5 | AA7: =IF(SUMIFS('PLM001-財務計算用'!$P:$P,'PLM001-財務計算用'!$J:$J,AA$4,'PLM001-財務計算用'!$A:$A,$B7)=0,"",SUMIFS('PLM001-財務計算用'!$P:$P,'PLM001-財務計算用'!$J:$J,AA$4,'PLM001-財務計算用'!$A:$A,$B7)) | AB7: =IF(SUMIFS('PLM002'!$K:$K,'PLM002'!$C:$C,AA$4,'PLM002'!$F:$F,$B7)=0,"",SUMIFS('PLM002'!$K:$K,'PLM002'!$C:$C,AA$4,'PLM002'!$F:$F,$B7)) | AC7: =IF(SUMIFS('PLM001-財務計算用'!$P:$P,'PLM001-財務計算用'!$J:$J,AC$4,'PLM001-財務計算用'!$A:$A,$B7)=0,"",SUMIFS('PLM001-財務計算用'!$P:$P,'PLM001-財務計算用'!$J:$J,AC$4,'PLM001-財務計算用'!$A:$A,$B7)) | AD7: =IF(SUMIFS('PLM002'!$K:$K,'PLM002'!$C:$C,AC$4,'PLM002'!$F:$F,$B7)=0,"",SUMIFS('PLM002'!$K:$K,'PLM002'!$C:$C,AC$4,'PLM002'!$F:$F,$B7)) | AE7: =IF(SUMIFS('PLM001-財務計算用'!$P:$P,'PLM001-財務計算用'!$J:$J,AE$4,'PLM001-財務計算用'!$A:$A,$B7)=0,"",SUMIFS('PLM001-財務計算用'!$P:$P,'PLM001-財務計算用'!$J:$J,AE$4,'PLM001-財務計算用'!$A:$A,$B7)) -> 60 | AF7: =IF(SUMIFS('PLM002'!$K:$K,'PLM002'!$C:$C,AE$4,'PLM002'!$F:$F,$B7)=0,"",SUMIFS('PLM002'!$K:$K,'PLM002'!$C:$C,AE$4,'PLM002'!$F:$F,$B7)) | AG7: =IF(SUMIFS('PLM001-財務計算用'!$P:$P,'PLM001-財務計算用'!$J:$J,AG$4,'PLM001-財務計算用'!$A:$A,$B7)=0,"",SUMIFS('PLM001-財務計算用'!$P:$P,'PLM001-財務計算用'!$J:$J,AG$4,'PLM001-財務計算用'!$A:$A,$B7)) | AH7: =IF(SUMIFS('PLM002'!$K:$K,'PLM002'!$C:$C,AG$4,'PLM002'!$F:$F,$B7)=0,"",SUMIFS('PLM002'!$K:$K,'PLM002'!$C:$C,AG$4,'PLM002'!$F:$F,$B7)) -> 66.5 | AI7: =IF(SUMIFS('PLM001-財務計算用'!$P:$P,'PLM001-財務計算用'!$J:$J,AI$4,'PLM001-財務計算用'!$A:$A,$B7)=0,"",SUMIFS('PLM001-財務計算用'!$P:$P,'PLM001-財務計算用'!$J:$J,AI$4,'PLM001-財務計算用'!$A:$A,$B7)) | AJ7: =IF(SUMIFS('PLM002'!$K:$K,'PLM002'!$C:$C,AI$4,'PLM002'!$F:$F,$B7)=0,"",SUMIFS('PLM002'!$K:$K,'PLM002'!$C:$C,AI$4,'PLM002'!$F:$F,$B7)) | AK7: =IF(SUMIFS('PLM001-財務計算用'!$P:$P,'PLM001-財務計算用'!$J:$J,AK$4,'PLM001-財務計算用'!$A:$A,$B7)=0,"",SUMIFS('PLM001-財務計算用'!$P:$P,'PLM001-財務計算用'!$J:$J,AK$4,'PLM001-財務計算用'!$A:$A,$B7)) | AL7: =IF(SUMIFS('PLM002'!$K:$K,'PLM002'!$C:$C,AK$4,'PLM002'!$F:$F,$B7)=0,"",SUMIFS('PLM002'!$K:$K,'PLM002'!$C:$C,AK$4,'PLM002'!$F:$F,$B7)) | AM7: =IF(SUMIFS('PLM001-財務計算用'!$P:$P,'PLM001-財務計算用'!$J:$J,AM$4,'PLM001-財務計算用'!$A:$A,$B7)=0,"",SUMIFS('PLM001-財務計算用'!$P:$P,'PLM001-財務計算用'!$J:$J,AM$4,'PLM001-財務計算用'!$A:$A,$B7)) | AN7: =IF(SUMIFS('PLM002'!$K:$K,'PLM002'!$C:$C,AM$4,'PLM002'!$F:$F,$B7)=0,"",SUMIFS('PLM002'!$K:$K,'PLM002'!$C:$C,AM$4,'PLM002'!$F:$F,$B7)) | AO7: =IF(SUMIFS('PLM001-財務計算用'!$P:$P,'PLM001-財務計算用'!$J:$J,AO$4,'PLM001-財務計算用'!$A:$A,$B7)=0,"",SUMIFS('PLM001-財務計算用'!$P:$P,'PLM001-財務計算用'!$J:$J,AO$4,'PLM001-財務計算用'!$A:$A,$B7)) -> 88 | AP7: =IF(SUMIFS('PLM002'!$K:$K,'PLM002'!$C:$C,AO$4,'PLM002'!$F:$F,$B7)=0,"",SUMIFS('PLM002'!$K:$K,'PLM002'!$C:$C,AO$4,'PLM002'!$F:$F,$B7)) -> 74 | AQ7: =IF(SUMIFS('PLM001-財務計算用'!$P:$P,'PLM001-財務計算用'!$J:$J,AQ$4,'PLM001-財務計算用'!$A:$A,$B7)=0,"",SUMIFS('PLM001-財務計算用'!$P:$P,'PLM001-財務計算用'!$J:$J,AQ$4,'PLM001-財務計算用'!$A:$A,$B7)) | AR7: =IF(SUMIFS('PLM002'!$K:$K,'PLM002'!$C:$C,AQ$4,'PLM002'!$F:$F,$B7)=0,"",SUMIFS('PLM002'!$K:$K,'PLM002'!$C:$C,AQ$4,'PLM002'!$F:$F,$B7)) | AS7: =IF(SUMIFS('PLM001-財務計算用'!$P:$P,'PLM001-財務計算用'!$J:$J,AS$4,'PLM001-財務計算用'!$A:$A,$B7)=0,"",SUMIFS('PLM001-財務計算用'!$P:$P,'PLM001-財務計算用'!$J:$J,AS$4,'PLM001-財務計算用'!$A:$A,$B7)) | AT7: =IF(SUMIFS('PLM002'!$K:$K,'PLM002'!$C:$C,AS$4,'PLM002'!$F:$F,$B7)=0,"",SUMIFS('PLM002'!$K:$K,'PLM002'!$C:$C,AS$4,'PLM002'!$F:$F,$B7)) | AU7: =IF(SUMIFS('PLM001-財務計算用'!$P:$P,'PLM001-財務計算用'!$J:$J,AU$4,'PLM001-財務計算用'!$A:$A,$B7)=0,"",SUMIFS('PLM001-財務計算用'!$P:$P,'PLM001-財務計算用'!$J:$J,AU$4,'PLM001-財務計算用'!$A:$A,$B7)) | AV7: =IF(SUMIFS('PLM002'!$K:$K,'PLM002'!$C:$C,AU$4,'PLM002'!$F:$F,$B7)=0,"",SUMIFS('PLM002'!$K:$K,'PLM002'!$C:$C,AU$4,'PLM002'!$F:$F,$B7)) | AW7: =IF(SUMIFS('PLM001-財務計算用'!$P:$P,'PLM001-財務計算用'!$J:$J,AW$4,'PLM001-財務計算用'!$A:$A,$B7)=0,"",SUMIFS('PLM001-財務計算用'!$P:$P,'PLM001-財務計算用'!$J:$J,AW$4,'PLM001-財務計算用'!$A:$A,$B7)) | AX7: =IF(SUMIFS('PLM002'!$K:$K,'PLM002'!$C:$C,AW$4,'PLM002'!$F:$F,$B7)=0,"",SUMIFS('PLM002'!$K:$K,'PLM002'!$C:$C,AW$4,'PLM002'!$F:$F,$B7)) | AY7: =IF(SUMIFS('PLM001-財務計算用'!$P:$P,'PLM001-財務計算用'!$J:$J,AY$4,'PLM001-財務計算用'!$A:$A,$B7)=0,"",SUMIFS('PLM001-財務計算用'!$P:$P,'PLM001-財務計算用'!$J:$J,AY$4,'PLM001-財務計算用'!$A:$A,$B7)) | AZ7: =IF(SUMIFS('PLM002'!$K:$K,'PLM002'!$C:$C,AY$4,'PLM002'!$F:$F,$B7)=0,"",SUMIFS('PLM002'!$K:$K,'PLM002'!$C:$C,AY$4,'PLM002'!$F:$F,$B7)) | BA7: =IF(SUMIFS('PLM001-財務計算用'!$P:$P,'PLM001-財務計算用'!$J:$J,BA$4,'PLM001-財務計算用'!$A:$A,$B7)=0,"",SUMIFS('PLM001-財務計算用'!$P:$P,'PLM001-財務計算用'!$J:$J,BA$4,'PLM001-財務計算用'!$A:$A,$B7)) | BB7: =IF(SUMIFS('PLM002'!$K:$K,'PLM002'!$C:$C,BA$4,'PLM002'!$F:$F,$B7)=0,"",SUMIFS('PLM002'!$K:$K,'PLM002'!$C:$C,BA$4,'PLM002'!$F:$F,$B7)) | BC7: =IF(SUMIFS('PLM001-財務計算用'!$P:$P,'PLM001-財務計算用'!$J:$J,BC$4,'PLM001-財務計算用'!$A:$A,$B7)=0,"",SUMIFS('PLM001-財務計算用'!$P:$P,'PLM001-財務計算用'!$J:$J,BC$4,'PLM001-財務計算用'!$A:$A,$B7)) -> 201 | BD7: =IF(SUMIFS('PLM002'!$K:$K,'PLM002'!$C:$C,BC$4,'PLM002'!$F:$F,$B7)=0,"",SUMIFS('PLM002'!$K:$K,'PLM002'!$C:$C,BC$4,'PLM002'!$F:$F,$B7)) -> 283.5 | BE7: =IF(SUMIFS('PLM001-財務計算用'!$P:$P,'PLM001-財務計算用'!$J:$J,BE$4,'PLM001-財務計算用'!$A:$A,$B7)=0,"",SUMIFS('PLM001-財務計算用'!$P:$P,'PLM001-財務計算用'!$J:$J,BE$4,'PLM001-財務計算用'!$A:$A,$B7)) | BF7: =IF(SUMIFS('PLM002'!$K:$K,'PLM002'!$C:$C,BE$4,'PLM002'!$F:$F,$B7)=0,"",SUMIFS('PLM002'!$K:$K,'PLM002'!$C:$C,BE$4,'PLM002'!$F:$F,$B7)) | BG7: =IF(SUMIFS('PLM001-財務計算用'!$P:$P,'PLM001-財務計算用'!$J:$J,BG$4,'PLM001-財務計算用'!$A:$A,$B7)=0,"",SUMIFS('PLM001-財務計算用'!$P:$P,'PLM001-財務計算用'!$J:$J,BG$4,'PLM001-財務計算用'!$A:$A,$B7)) | BH7: =IF(SUMIFS('PLM002'!$K:$K,'PLM002'!$C:$C,BG$4,'PLM002'!$F:$F,$B7)=0,"",SUMIFS('PLM002'!$K:$K,'PLM002'!$C:$C,BG$4,'PLM002'!$F:$F,$B7)) | BI7: =IF(SUMIFS('PLM001-財務計算用'!$P:$P,'PLM001-財務計算用'!$J:$J,BI$4,'PLM001-財務計算用'!$A:$A,$B7)=0,"",SUMIFS('PLM001-財務計算用'!$P:$P,'PLM001-財務計算用'!$J:$J,BI$4,'PLM001-財務計算用'!$A:$A,$B7)) -> 188 | BJ7: =IF(SUMIFS('PLM002'!$K:$K,'PLM002'!$C:$C,BI$4,'PLM002'!$F:$F,$B7)=0,"",SUMIFS('PLM002'!$K:$K,'PLM002'!$C:$C,BI$4,'PLM002'!$F:$F,$B7)) -> 555 | BK7: =IF(SUMIFS('PLM001-財務計算用'!$P:$P,'PLM001-財務計算用'!$J:$J,BK$4,'PLM001-財務計算用'!$A:$A,$B7)=0,"",SUMIFS('PLM001-財務計算用'!$P:$P,'PLM001-財務計算用'!$J:$J,BK$4,'PLM001-財務計算用'!$A:$A,$B7)) | BL7: =IF(SUMIFS('PLM002'!$K:$K,'PLM002'!$C:$C,BK$4,'PLM002'!$F:$F,$B7)=0,"",SUMIFS('PLM002'!$K:$K,'PLM002'!$C:$C,BK$4,'PLM002'!$F:$F,$B7)) | BM7: =IF(SUMIFS('PLM001-財務計算用'!$P:$P,'PLM001-財務計算用'!$J:$J,BM$4,'PLM001-財務計算用'!$A:$A,$B7)=0,"",SUMIFS('PLM001-財務計算用'!$P:$P,'PLM001-財務計算用'!$J:$J,BM$4,'PLM001-財務計算用'!$A:$A,$B7)) | BN7: =IF(SUMIFS('PLM002'!$K:$K,'PLM002'!$C:$C,BM$4,'PLM002'!$F:$F,$B7)=0,"",SUMIFS('PLM002'!$K:$K,'PLM002'!$C:$C,BM$4,'PLM002'!$F:$F,$B7)) | BO7: =IF(SUMIFS('PLM001-財務計算用'!$P:$P,'PLM001-財務計算用'!$J:$J,BO$4,'PLM001-財務計算用'!$A:$A,$B7)=0,"",SUMIFS('PLM001-財務計算用'!$P:$P,'PLM001-財務計算用'!$J:$J,BO$4,'PLM001-財務計算用'!$A:$A,$B7)) | BP7: =IF(SUMIFS('PLM002'!$K:$K,'PLM002'!$C:$C,BO$4,'PLM002'!$F:$F,$B7)=0,"",SUMIFS('PLM002'!$K:$K,'PLM002'!$C:$C,BO$4,'PLM002'!$F:$F,$B7)) | BQ7: =IF(SUMIFS('PLM001-財務計算用'!$P:$P,'PLM001-財務計算用'!$J:$J,BQ$4,'PLM001-財務計算用'!$A:$A,$B7)=0,"",SUMIFS('PLM001-財務計算用'!$P:$P,'PLM001-財務計算用'!$J:$J,BQ$4,'PLM001-財務計算用'!$A:$A,$B7)) | BR7: =IF(SUMIFS('PLM002'!$K:$K,'PLM002'!$C:$C,BQ$4,'PLM002'!$F:$F,$B7)=0,"",SUMIFS('PLM002'!$K:$K,'PLM002'!$C:$C,BQ$4,'PLM002'!$F:$F,$B7)) | BS7: =IF(SUMIFS('PLM001-財務計算用'!$P:$P,'PLM001-財務計算用'!$J:$J,BS$4,'PLM001-財務計算用'!$A:$A,$B7)=0,"",SUMIFS('PLM001-財務計算用'!$P:$P,'PLM001-財務計算用'!$J:$J,BS$4,'PLM001-財務計算用'!$A:$A,$B7)) | BT7: =IF(SUMIFS('PLM002'!$K:$K,'PLM002'!$C:$C,BS$4,'PLM002'!$F:$F,$B7)=0,"",SUMIFS('PLM002'!$K:$K,'PLM002'!$C:$C,BS$4,'PLM002'!$F:$F,$B7)) -> 127 | BU7: =IF(SUMIFS('PLM001-財務計算用'!$P:$P,'PLM001-財務計算用'!$J:$J,BU$4,'PLM001-財務計算用'!$A:$A,$B7)=0,"",SUMIFS('PLM001-財務計算用'!$P:$P,'PLM001-財務計算用'!$J:$J,BU$4,'PLM001-財務計算用'!$A:$A,$B7)) | BV7: =IF(SUMIFS('PLM002'!$K:$K,'PLM002'!$C:$C,BU$4,'PLM002'!$F:$F,$B7)=0,"",SUMIFS('PLM002'!$K:$K,'PLM002'!$C:$C,BU$4,'PLM002'!$F:$F,$B7)) | BW7: =IF(SUMIFS('PLM001-財務計算用'!$P:$P,'PLM001-財務計算用'!$J:$J,BW$4,'PLM001-財務計算用'!$A:$A,$B7)=0,"",SUMIFS('PLM001-財務計算用'!$P:$P,'PLM001-財務計算用'!$J:$J,BW$4,'PLM001-財務計算用'!$A:$A,$B7)) -> 140 | BX7: =IF(SUMIFS('PLM002'!$K:$K,'PLM002'!$C:$C,BW$4,'PLM002'!$F:$F,$B7)=0,"",SUMIFS('PLM002'!$K:$K,'PLM002'!$C:$C,BW$4,'PLM002'!$F:$F,$B7)) -> 94.5 | BY7: =IF(SUMIFS('PLM001-財務計算用'!$P:$P,'PLM001-財務計算用'!$J:$J,BY$4,'PLM001-財務計算用'!$A:$A,$B7)=0,"",SUMIFS('PLM001-財務計算用'!$P:$P,'PLM001-財務計算用'!$J:$J,BY$4,'PLM001-財務計算用'!$A:$A,$B7)) | BZ7: =IF(SUMIFS('PLM002'!$K:$K,'PLM002'!$C:$C,BY$4,'PLM002'!$F:$F,$B7)=0,"",SUMIFS('PLM002'!$K:$K,'PLM002'!$C:$C,BY$4,'PLM002'!$F:$F,$B7)) | CA7: =IF(SUMIFS('PLM001-財務計算用'!$P:$P,'PLM001-財務計算用'!$J:$J,CA$4,'PLM001-財務計算用'!$A:$A,$B7)=0,"",SUMIFS('PLM001-財務計算用'!$P:$P,'PLM001-財務計算用'!$J:$J,CA$4,'PLM001-財務計算用'!$A:$A,$B7)) | CB7: =IF(SUMIFS('PLM002'!$K:$K,'PLM002'!$C:$C,CA$4,'PLM002'!$F:$F,$B7)=0,"",SUMIFS('PLM002'!$K:$K,'PLM002'!$C:$C,CA$4,'PLM002'!$F:$F,$B7)) | CC7: =IF(SUMIFS('PLM001-財務計算用'!$P:$P,'PLM001-財務計算用'!$J:$J,CC$4,'PLM001-財務計算用'!$A:$A,$B7)=0,"",SUMIFS('PLM001-財務計算用'!$P:$P,'PLM001-財務計算用'!$J:$J,CC$4,'PLM001-財務計算用'!$A:$A,$B7)) | CD7: =IF(SUMIFS('PLM002'!$K:$K,'PLM002'!$C:$C,CC$4,'PLM002'!$F:$F,$B7)=0,"",SUMIFS('PLM002'!$K:$K,'PLM002'!$C:$C,CC$4,'PLM002'!$F:$F,$B7)) | CE7: =IF(SUMIFS('PLM001-財務計算用'!$P:$P,'PLM001-財務計算用'!$J:$J,CE$4,'PLM001-財務計算用'!$A:$A,$B7)=0,"",SUMIFS('PLM001-財務計算用'!$P:$P,'PLM001-財務計算用'!$J:$J,CE$4,'PLM001-財務計算用'!$A:$A,$B7)) | CF7: =IF(SUMIFS('PLM002'!$K:$K,'PLM002'!$C:$C,CE$4,'PLM002'!$F:$F,$B7)=0,"",SUMIFS('PLM002'!$K:$K,'PLM002'!$C:$C,CE$4,'PLM002'!$F:$F,$B7)) | CG7: =IF(SUMIFS('PLM001-財務計算用'!$P:$P,'PLM001-財務計算用'!$J:$J,CG$4,'PLM001-財務計算用'!$A:$A,$B7)=0,"",SUMIFS('PLM001-財務計算用'!$P:$P,'PLM001-財務計算用'!$J:$J,CG$4,'PLM001-財務計算用'!$A:$A,$B7)) | CH7: =IF(SUMIFS('PLM002'!$K:$K,'PLM002'!$C:$C,CG$4,'PLM002'!$F:$F,$B7)=0,"",SUMIFS('PLM002'!$K:$K,'PLM002'!$C:$C,CG$4,'PLM002'!$F:$F,$B7)) | CI7: =IF(SUMIFS('PLM001-財務計算用'!$P:$P,'PLM001-財務計算用'!$J:$J,CI$4,'PLM001-財務計算用'!$A:$A,$B7)=0,"",SUMIFS('PLM001-財務計算用'!$P:$P,'PLM001-財務計算用'!$J:$J,CI$4,'PLM001-財務計算用'!$A:$A,$B7)) | CJ7: =IF(SUMIFS('PLM002'!$K:$K,'PLM002'!$C:$C,CI$4,'PLM002'!$F:$F,$B7)=0,"",SUMIFS('PLM002'!$K:$K,'PLM002'!$C:$C,CI$4,'PLM002'!$F:$F,$B7)) | CK7: =IF(SUMIFS('PLM001-財務計算用'!$P:$P,'PLM001-財務計算用'!$J:$J,CK$4,'PLM001-財務計算用'!$A:$A,$B7)=0,"",SUMIFS('PLM001-財務計算用'!$P:$P,'PLM001-財務計算用'!$J:$J,CK$4,'PLM001-財務計算用'!$A:$A,$B7)) | CL7: =IF(SUMIFS('PLM002'!$K:$K,'PLM002'!$C:$C,CK$4,'PLM002'!$F:$F,$B7)=0,"",SUMIFS('PLM002'!$K:$K,'PLM002'!$C:$C,CK$4,'PLM002'!$F:$F,$B7)) | CM7: =IF(SUMIFS('PLM001-財務計算用'!$P:$P,'PLM001-財務計算用'!$J:$J,CM$4,'PLM001-財務計算用'!$A:$A,$B7)=0,"",SUMIFS('PLM001-財務計算用'!$P:$P,'PLM001-財務計算用'!$J:$J,CM$4,'PLM001-財務計算用'!$A:$A,$B7)) | CN7: =IF(SUMIFS('PLM002'!$K:$K,'PLM002'!$C:$C,CM$4,'PLM002'!$F:$F,$B7)=0,"",SUMIFS('PLM002'!$K:$K,'PLM002'!$C:$C,CM$4,'PLM002'!$F:$F,$B7)) | CO7: =IF(SUMIFS('PLM001-財務計算用'!$P:$P,'PLM001-財務計算用'!$J:$J,CO$4,'PLM001-財務計算用'!$A:$A,$B7)=0,"",SUMIFS('PLM001-財務計算用'!$P:$P,'PLM001-財務計算用'!$J:$J,CO$4,'PLM001-財務計算用'!$A:$A,$B7)) | CP7: =IF(SUMIFS('PLM002'!$K:$K,'PLM002'!$C:$C,CO$4,'PLM002'!$F:$F,$B7)=0,"",SUMIFS('PLM002'!$K:$K,'PLM002'!$C:$C,CO$4,'PLM002'!$F:$F,$B7)) | CQ7: =IF(SUMIFS('PLM001-財務計算用'!$P:$P,'PLM001-財務計算用'!$J:$J,CQ$4,'PLM001-財務計算用'!$A:$A,$B7)=0,"",SUMIFS('PLM001-財務計算用'!$P:$P,'PLM001-財務計算用'!$J:$J,CQ$4,'PLM001-財務計算用'!$A:$A,$B7)) | CR7: =IF(SUMIFS('PLM002'!$K:$K,'PLM002'!$C:$C,CQ$4,'PLM002'!$F:$F,$B7)=0,"",SUMIFS('PLM002'!$K:$K,'PLM002'!$C:$C,CQ$4,'PLM002'!$F:$F,$B7)) | CS7: =IF(SUMIFS('PLM001-財務計算用'!$P:$P,'PLM001-財務計算用'!$J:$J,CS$4,'PLM001-財務計算用'!$A:$A,$B7)=0,"",SUMIFS('PLM001-財務計算用'!$P:$P,'PLM001-財務計算用'!$J:$J,CS$4,'PLM001-財務計算用'!$A:$A,$B7)) | CT7: =IF(SUMIFS('PLM002'!$K:$K,'PLM002'!$C:$C,CS$4,'PLM002'!$F:$F,$B7)=0,"",SUMIFS('PLM002'!$K:$K,'PLM002'!$C:$C,CS$4,'PLM002'!$F:$F,$B7)) | CU7: =IF(SUMIFS('PLM001-財務計算用'!$P:$P,'PLM001-財務計算用'!$J:$J,CU$4,'PLM001-財務計算用'!$A:$A,$B7)=0,"",SUMIFS('PLM001-財務計算用'!$P:$P,'PLM001-財務計算用'!$J:$J,CU$4,'PLM001-財務計算用'!$A:$A,$B7)) | CV7: =IF(SUMIFS('PLM002'!$K:$K,'PLM002'!$C:$C,CU$4,'PLM002'!$F:$F,$B7)=0,"",SUMIFS('PLM002'!$K:$K,'PLM002'!$C:$C,CU$4,'PLM002'!$F:$F,$B7)) | CW7: =IF(SUMIFS('PLM001-財務計算用'!$P:$P,'PLM001-財務計算用'!$J:$J,CW$4,'PLM001-財務計算用'!$A:$A,$B7)=0,"",SUMIFS('PLM001-財務計算用'!$P:$P,'PLM001-財務計算用'!$J:$J,CW$4,'PLM001-財務計算用'!$A:$A,$B7)) | CX7: =IF(SUMIFS('PLM002'!$K:$K,'PLM002'!$C:$C,CW$4,'PLM002'!$F:$F,$B7)=0,"",SUMIFS('PLM002'!$K:$K,'PLM002'!$C:$C,CW$4,'PLM002'!$F:$F,$B7)) | CY7: =IF(SUMIFS('PLM001-財務計算用'!$P:$P,'PLM001-財務計算用'!$J:$J,CY$4,'PLM001-財務計算用'!$A:$A,$B7)=0,"",SUMIFS('PLM001-財務計算用'!$P:$P,'PLM001-財務計算用'!$J:$J,CY$4,'PLM001-財務計算用'!$A:$A,$B7)) | CZ7: =IF(SUMIFS('PLM002'!$K:$K,'PLM002'!$C:$C,CY$4,'PLM002'!$F:$F,$B7)=0,"",SUMIFS('PLM002'!$K:$K,'PLM002'!$C:$C,CY$4,'PLM002'!$F:$F,$B7)) | DA7: =IF(SUMIFS('PLM001-財務計算用'!$P:$P,'PLM001-財務計算用'!$J:$J,DA$4,'PLM001-財務計算用'!$A:$A,$B7)=0,"",SUMIFS('PLM001-財務計算用'!$P:$P,'PLM001-財務計算用'!$J:$J,DA$4,'PLM001-財務計算用'!$A:$A,$B7)) | DB7: =IF(SUMIFS('PLM002'!$K:$K,'PLM002'!$C:$C,DA$4,'PLM002'!$F:$F,$B7)=0,"",SUMIFS('PLM002'!$K:$K,'PLM002'!$C:$C,DA$4,'PLM002'!$F:$F,$B7)) | DC7: =IF(SUMIFS('PLM001-財務計算用'!$P:$P,'PLM001-財務計算用'!$J:$J,DC$4,'PLM001-財務計算用'!$A:$A,$B7)=0,"",SUMIFS('PLM001-財務計算用'!$P:$P,'PLM001-財務計算用'!$J:$J,DC$4,'PLM001-財務計算用'!$A:$A,$B7)) -> 100 | DD7: =IF(SUMIFS('PLM002'!$K:$K,'PLM002'!$C:$C,DC$4,'PLM002'!$F:$F,$B7)=0,"",SUMIFS('PLM002'!$K:$K,'PLM002'!$C:$C,DC$4,'PLM002'!$F:$F,$B7)) | DE7: =IF(SUMIFS('PLM001-財務計算用'!$P:$P,'PLM001-財務計算用'!$J:$J,DE$4,'PLM001-財務計算用'!$A:$A,$B7)=0,"",SUMIFS('PLM001-財務計算用'!$P:$P,'PLM001-財務計算用'!$J:$J,DE$4,'PLM001-財務計算用'!$A:$A,$B7)) | DF7: =IF(SUMIFS('PLM002'!$K:$K,'PLM002'!$C:$C,DE$4,'PLM002'!$F:$F,$B7)=0,"",SUMIFS('PLM002'!$K:$K,'PLM002'!$C:$C,DE$4,'PLM002'!$F:$F,$B7)) | DG7: =IF(SUMIFS('PLM001-財務計算用'!$P:$P,'PLM001-財務計算用'!$J:$J,DG$4,'PLM001-財務計算用'!$A:$A,$B7)=0,"",SUMIFS('PLM001-財務計算用'!$P:$P,'PLM001-財務計算用'!$J:$J,DG$4,'PLM001-財務計算用'!$A:$A,$B7)) | DH7: =IF(SUMIFS('PLM002'!$K:$K,'PLM002'!$C:$C,DG$4,'PLM002'!$F:$F,$B7)=0,"",SUMIFS('PLM002'!$K:$K,'PLM002'!$C:$C,DG$4,'PLM002'!$F:$F,$B7)) | DI7: =IF(SUMIFS('PLM001-財務計算用'!$P:$P,'PLM001-財務計算用'!$J:$J,DI$4,'PLM001-財務計算用'!$A:$A,$B7)=0,"",SUMIFS('PLM001-財務計算用'!$P:$P,'PLM001-財務計算用'!$J:$J,DI$4,'PLM001-財務計算用'!$A:$A,$B7)) | DJ7: =IF(SUMIFS('PLM002'!$K:$K,'PLM002'!$C:$C,DI$4,'PLM002'!$F:$F,$B7)=0,"",SUMIFS('PLM002'!$K:$K,'PLM002'!$C:$C,DI$4,'PLM002'!$F:$F,$B7)) | DK7: =IF(SUMIFS('PLM001-財務計算用'!$P:$P,'PLM001-財務計算用'!$J:$J,DK$4,'PLM001-財務計算用'!$A:$A,$B7)=0,"",SUMIFS('PLM001-財務計算用'!$P:$P,'PLM001-財務計算用'!$J:$J,DK$4,'PLM001-財務計算用'!$A:$A,$B7)) | DL7: =IF(SUMIFS('PLM002'!$K:$K,'PLM002'!$C:$C,DK$4,'PLM002'!$F:$F,$B7)=0,"",SUMIFS('PLM002'!$K:$K,'PLM002'!$C:$C,DK$4,'PLM002'!$F:$F,$B7)) | DM7: =IF(SUMIFS('PLM001-財務計算用'!$P:$P,'PLM001-財務計算用'!$J:$J,DM$4,'PLM001-財務計算用'!$A:$A,$B7)=0,"",SUMIFS('PLM001-財務計算用'!$P:$P,'PLM001-財務計算用'!$J:$J,DM$4,'PLM001-財務計算用'!$A:$A,$B7)) | DN7: =IF(SUMIFS('PLM002'!$K:$K,'PLM002'!$C:$C,DM$4,'PLM002'!$F:$F,$B7)=0,"",SUMIFS('PLM002'!$K:$K,'PLM002'!$C:$C,DM$4,'PLM002'!$F:$F,$B7)) | DO7: =IF(SUMIFS('PLM001-財務計算用'!$P:$P,'PLM001-財務計算用'!$J:$J,DO$4,'PLM001-財務計算用'!$A:$A,$B7)=0,"",SUMIFS('PLM001-財務計算用'!$P:$P,'PLM001-財務計算用'!$J:$J,DO$4,'PLM001-財務計算用'!$A:$A,$B7)) | DP7: =IF(SUMIFS('PLM002'!$K:$K,'PLM002'!$C:$C,DO$4,'PLM002'!$F:$F,$B7)=0,"",SUMIFS('PLM002'!$K:$K,'PLM002'!$C:$C,DO$4,'PLM002'!$F:$F,$B7)) | DQ7: =IF(SUMIFS('PLM001-財務計算用'!$P:$P,'PLM001-財務計算用'!$J:$J,DQ$4,'PLM001-財務計算用'!$A:$A,$B7)=0,"",SUMIFS('PLM001-財務計算用'!$P:$P,'PLM001-財務計算用'!$J:$J,DQ$4,'PLM001-財務計算用'!$A:$A,$B7)) | DR7: =IF(SUMIFS('PLM002'!$K:$K,'PLM002'!$C:$C,DQ$4,'PLM002'!$F:$F,$B7)=0,"",SUMIFS('PLM002'!$K:$K,'PLM002'!$C:$C,DQ$4,'PLM002'!$F:$F,$B7)) | DS7: =IF(SUMIFS('PLM001-財務計算用'!$P:$P,'PLM001-財務計算用'!$J:$J,DS$4,'PLM001-財務計算用'!$A:$A,$B7)=0,"",SUMIFS('PLM001-財務計算用'!$P:$P,'PLM001-財務計算用'!$J:$J,DS$4,'PLM001-財務計算用'!$A:$A,$B7)) | DT7: =IF(SUMIFS('PLM002'!$K:$K,'PLM002'!$C:$C,DS$4,'PLM002'!$F:$F,$B7)=0,"",SUMIFS('PLM002'!$K:$K,'PLM002'!$C:$C,DS$4,'PLM002'!$F:$F,$B7)) | DU7: =IF(SUMIFS('PLM001-財務計算用'!$P:$P,'PLM001-財務計算用'!$J:$J,DU$4,'PLM001-財務計算用'!$A:$A,$B7)=0,"",SUMIFS('PLM001-財務計算用'!$P:$P,'PLM001-財務計算用'!$J:$J,DU$4,'PLM001-財務計算用'!$A:$A,$B7)) | DV7: =IF(SUMIFS('PLM002'!$K:$K,'PLM002'!$C:$C,DU$4,'PLM002'!$F:$F,$B7)=0,"",SUMIFS('PLM002'!$K:$K,'PLM002'!$C:$C,DU$4,'PLM002'!$F:$F,$B7)) | DW7: =IF(SUMIFS('PLM001-財務計算用'!$P:$P,'PLM001-財務計算用'!$J:$J,DW$4,'PLM001-財務計算用'!$A:$A,$B7)=0,"",SUMIFS('PLM001-財務計算用'!$P:$P,'PLM001-財務計算用'!$J:$J,DW$4,'PLM001-財務計算用'!$A:$A,$B7)) | DX7: =IF(SUMIFS('PLM002'!$K:$K,'PLM002'!$C:$C,DW$4,'PLM002'!$F:$F,$B7)=0,"",SUMIFS('PLM002'!$K:$K,'PLM002'!$C:$C,DW$4,'PLM002'!$F:$F,$B7)) | DY7: =IF(SUMIFS('PLM001-財務計算用'!$P:$P,'PLM001-財務計算用'!$J:$J,DY$4,'PLM001-財務計算用'!$A:$A,$B7)=0,"",SUMIFS('PLM001-財務計算用'!$P:$P,'PLM001-財務計算用'!$J:$J,DY$4,'PLM001-財務計算用'!$A:$A,$B7)) | DZ7: =IF(SUMIFS('PLM002'!$K:$K,'PLM002'!$C:$C,DY$4,'PLM002'!$F:$F,$B7)=0,"",SUMIFS('PLM002'!$K:$K,'PLM002'!$C:$C,DY$4,'PLM002'!$F:$F,$B7)) | EA7: =IF(SUMIFS('PLM001-財務計算用'!$P:$P,'PLM001-財務計算用'!$J:$J,EA$4,'PLM001-財務計算用'!$A:$A,$B7)=0,"",SUMIFS('PLM001-財務計算用'!$P:$P,'PLM001-財務計算用'!$J:$J,EA$4,'PLM001-財務計算用'!$A:$A,$B7)) | EB7: =IF(SUMIFS('PLM002'!$K:$K,'PLM002'!$C:$C,EA$4,'PLM002'!$F:$F,$B7)=0,"",SUMIFS('PLM002'!$K:$K,'PLM002'!$C:$C,EA$4,'PLM002'!$F:$F,$B7)) | EC7: =IF(SUMIFS('PLM001-財務計算用'!$P:$P,'PLM001-財務計算用'!$J:$J,EC$4,'PLM001-財務計算用'!$A:$A,$B7)=0,"",SUMIFS('PLM001-財務計算用'!$P:$P,'PLM001-財務計算用'!$J:$J,EC$4,'PLM001-財務計算用'!$A:$A,$B7)) | ED7: =IF(SUMIFS('PLM002'!$K:$K,'PLM002'!$C:$C,EC$4,'PLM002'!$F:$F,$B7)=0,"",SUMIFS('PLM002'!$K:$K,'PLM002'!$C:$C,EC$4,'PLM002'!$F:$F,$B7))
A8: ='PLM014'!A9 -> D-協同 | B8: D250301R1 | C8: ='PLM014'!C9 -> EPD電磁流量計技转 | D8: ="("&B8&")"&" "&C8 -> (D250301R1) EPD電磁流量計技转 | E8: ='PLM014'!E9 -> 研发一部 | F8: ='PLM014'!F9 -> 汪佳凯 | G8: ='PLM014'!G9 -> Active | H8: ='PLM014'!H9 -> 45872.667 | I8: ='PLM014'!I9 -> 46147.667 | J8: =IF(ISERROR(DATEDIF(H8,I8,"d")),"",DATEDIF(H8,I8,"d")) -> 275 | K8: =H8+(J8*0.75) -> 46078.917 | L8: =H8+(J8*0.95) -> 46133.917 | M8: =IF(ISERROR('PLM014'!L9),"",('PLM014'!L9)) -> 45873 | N8: =IF(IF(ISERROR('PLM014'!N9),"",('PLM014'!N9))=0,"",IF(ISERROR('PLM014'!N9),"",('PLM014'!N9))) | O8: =IF(ISERROR(DATEDIF(M8,N8,"d")),"",IF(DATEDIF(M8,N8,"d")=0,"",DATEDIF(M8,N8,"d"))) | P8: =IF(N8="",TODAY(),N8) -> 46044 | Q8: =IF(ISERROR(DATEDIF(M8,P8,"d")),"",IF(DATEDIF(M8,P8,"d")=0,"",DATEDIF(M8,P8,"d"))) -> 171 | R8: ='PLM014'!Q9/100 -> 0.18 | S8: =IF(AND(TODAY()>I8,R8<>100%,G8="Active"),"專案延遲 "&DATEDIF(I8,TODAY(),"d")&" 天",IF(AND(TODAY()>K8,R8<75%,G8="Active"),"專案即將異常",IF(AND(TODAY()>L8,R8<95%,G8="Active"),"專案即將異常",""))) | U8: =IF(SUMIF($Y$5:$CV$5,$U$5,Y8:CV8)=0,"未登入",SUMIF($Y$5:$CV$5,$U$5,Y8:CV8)) -> 未登入 | V8: =SUMIF($Y$5:$CV$5,$V$5,Y8:CV8) -> 0 | W8: =IF(SUMIFS('PLM001-財務計算用'!$P:$P,'PLM001-財務計算用'!$A:$A,B8)=0,"未登入",SUMIFS('PLM001-財務計算用'!$P:$P,'PLM001-財務計算用'!$A:$A,B8)) -> 779 | X8: =SUMIFS('PLM002'!$K:$K,'PLM002'!$F:$F,$B8) -> 0 | Y8: =IF(SUMIFS('PLM001-財務計算用'!$P:$P,'PLM001-財務計算用'!$J:$J,Y$4,'PLM001-財務計算用'!$A:$A,$B8)=0,"",SUMIFS('PLM001-財務計算用'!$P:$P,'PLM001-財務計算用'!$J:$J,Y$4,'PLM001-財務計算用'!$A:$A,$B8)) | Z8: =IF(SUMIFS('PLM002'!$K:$K,'PLM002'!$C:$C,Y$4,'PLM002'!$F:$F,$B8)=0,"",SUMIFS('PLM002'!$K:$K,'PLM002'!$C:$C,Y$4,'PLM002'!$F:$F,$B8)) | AA8: =IF(SUMIFS('PLM001-財務計算用'!$P:$P,'PLM001-財務計算用'!$J:$J,AA$4,'PLM001-財務計算用'!$A:$A,$B8)=0,"",SUMIFS('PLM001-財務計算用'!$P:$P,'PLM001-財務計算用'!$J:$J,AA$4,'PLM001-財務計算用'!$A:$A,$B8)) | AB8: =IF(SUMIFS('PLM002'!$K:$K,'PLM002'!$C:$C,AA$4,'PLM002'!$F:$F,$B8)=0,"",SUMIFS('PLM002'!$K:$K,'PLM002'!$C:$C,AA$4,'PLM002'!$F:$F,$B8)) | AC8: =IF(SUMIFS('PLM001-財務計算用'!$P:$P,'PLM001-財務計算用'!$J:$J,AC$4,'PLM001-財務計算用'!$A:$A,$B8)=0,"",SUMIFS('PLM001-財務計算用'!$P:$P,'PLM001-財務計算用'!$J:$J,AC$4,'PLM001-財務計算用'!$A:$A,$B8)) | AD8: =IF(SUMIFS('PLM002'!$K:$K,'PLM002'!$C:$C,AC$4,'PLM002'!$F:$F,$B8)=0,"",SUMIFS('PLM002'!$K:$K,'PLM002'!$C:$C,AC$4,'PLM002'!$F:$F,$B8)) | AE8: =IF(SUMIFS('PLM001-財務計算用'!$P:$P,'PLM001-財務計算用'!$J:$J,AE$4,'PLM001-財務計算用'!$A:$A,$B8)=0,"",SUMIFS('PLM001-財務計算用'!$P:$P,'PLM001-財務計算用'!$J:$J,AE$4,'PLM001-財務計算用'!$A:$A,$B8)) | AF8: =IF(SUMIFS('PLM002'!$K:$K,'PLM002'!$C:$C,AE$4,'PLM002'!$F:$F,$B8)=0,"",SUMIFS('PLM002'!$K:$K,'PLM002'!$C:$C,AE$4,'PLM002'!$F:$F,$B8)) | AG8: =IF(SUMIFS('PLM001-財務計算用'!$P:$P,'PLM001-財務計算用'!$J:$J,AG$4,'PLM001-財務計算用'!$A:$A,$B8)=0,"",SUMIFS('PLM001-財務計算用'!$P:$P,'PLM001-財務計算用'!$J:$J,AG$4,'PLM001-財務計算用'!$A:$A,$B8)) | AH8: =IF(SUMIFS('PLM002'!$K:$K,'PLM002'!$C:$C,AG$4,'PLM002'!$F:$F,$B8)=0,"",SUMIFS('PLM002'!$K:$K,'PLM002'!$C:$C,AG$4,'PLM002'!$F:$F,$B8)) | AI8: =IF(SUMIFS('PLM001-財務計算用'!$P:$P,'PLM001-財務計算用'!$J:$J,AI$4,'PLM001-財務計算用'!$A:$A,$B8)=0,"",SUMIFS('PLM001-財務計算用'!$P:$P,'PLM001-財務計算用'!$J:$J,AI$4,'PLM001-財務計算用'!$A:$A,$B8)) | AJ8: =IF(SUMIFS('PLM002'!$K:$K,'PLM002'!$C:$C,AI$4,'PLM002'!$F:$F,$B8)=0,"",SUMIFS('PLM002'!$K:$K,'PLM002'!$C:$C,AI$4,'PLM002'!$F:$F,$B8)) | AK8: =IF(SUMIFS('PLM001-財務計算用'!$P:$P,'PLM001-財務計算用'!$J:$J,AK$4,'PLM001-財務計算用'!$A:$A,$B8)=0,"",SUMIFS('PLM001-財務計算用'!$P:$P,'PLM001-財務計算用'!$J:$J,AK$4,'PLM001-財務計算用'!$A:$A,$B8)) | AL8: =IF(SUMIFS('PLM002'!$K:$K,'PLM002'!$C:$C,AK$4,'PLM002'!$F:$F,$B8)=0,"",SUMIFS('PLM002'!$K:$K,'PLM002'!$C:$C,AK$4,'PLM002'!$F:$F,$B8)) | AM8: =IF(SUMIFS('PLM001-財務計算用'!$P:$P,'PLM001-財務計算用'!$J:$J,AM$4,'PLM001-財務計算用'!$A:$A,$B8)=0,"",SUMIFS('PLM001-財務計算用'!$P:$P,'PLM001-財務計算用'!$J:$J,AM$4,'PLM001-財務計算用'!$A:$A,$B8)) | AN8: =IF(SUMIFS('PLM002'!$K:$K,'PLM002'!$C:$C,AM$4,'PLM002'!$F:$F,$B8)=0,"",SUMIFS('PLM002'!$K:$K,'PLM002'!$C:$C,AM$4,'PLM002'!$F:$F,$B8)) | AO8: =IF(SUMIFS('PLM001-財務計算用'!$P:$P,'PLM001-財務計算用'!$J:$J,AO$4,'PLM001-財務計算用'!$A:$A,$B8)=0,"",SUMIFS('PLM001-財務計算用'!$P:$P,'PLM001-財務計算用'!$J:$J,AO$4,'PLM001-財務計算用'!$A:$A,$B8)) | AP8: =IF(SUMIFS('PLM002'!$K:$K,'PLM002'!$C:$C,AO$4,'PLM002'!$F:$F,$B8)=0,"",SUMIFS('PLM002'!$K:$K,'PLM002'!$C:$C,AO$4,'PLM002'!$F:$F,$B8)) | AQ8: =IF(SUMIFS('PLM001-財務計算用'!$P:$P,'PLM001-財務計算用'!$J:$J,AQ$4,'PLM001-財務計算用'!$A:$A,$B8)=0,"",SUMIFS('PLM001-財務計算用'!$P:$P,'PLM001-財務計算用'!$J:$J,AQ$4,'PLM001-財務計算用'!$A:$A,$B8)) | AR8: =IF(SUMIFS('PLM002'!$K:$K,'PLM002'!$C:$C,AQ$4,'PLM002'!$F:$F,$B8)=0,"",SUMIFS('PLM002'!$K:$K,'PLM002'!$C:$C,AQ$4,'PLM002'!$F:$F,$B8)) | AS8: =IF(SUMIFS('PLM001-財務計算用'!$P:$P,'PLM001-財務計算用'!$J:$J,AS$4,'PLM001-財務計算用'!$A:$A,$B8)=0,"",SUMIFS('PLM001-財務計算用'!$P:$P,'PLM001-財務計算用'!$J:$J,AS$4,'PLM001-財務計算用'!$A:$A,$B8)) | AT8: =IF(SUMIFS('PLM002'!$K:$K,'PLM002'!$C:$C,AS$4,'PLM002'!$F:$F,$B8)=0,"",SUMIFS('PLM002'!$K:$K,'PLM002'!$C:$C,AS$4,'PLM002'!$F:$F,$B8)) | AU8: =IF(SUMIFS('PLM001-財務計算用'!$P:$P,'PLM001-財務計算用'!$J:$J,AU$4,'PLM001-財務計算用'!$A:$A,$B8)=0,"",SUMIFS('PLM001-財務計算用'!$P:$P,'PLM001-財務計算用'!$J:$J,AU$4,'PLM001-財務計算用'!$A:$A,$B8)) | AV8: =IF(SUMIFS('PLM002'!$K:$K,'PLM002'!$C:$C,AU$4,'PLM002'!$F:$F,$B8)=0,"",SUMIFS('PLM002'!$K:$K,'PLM002'!$C:$C,AU$4,'PLM002'!$F:$F,$B8)) | AW8: =IF(SUMIFS('PLM001-財務計算用'!$P:$P,'PLM001-財務計算用'!$J:$J,AW$4,'PLM001-財務計算用'!$A:$A,$B8)=0,"",SUMIFS('PLM001-財務計算用'!$P:$P,'PLM001-財務計算用'!$J:$J,AW$4,'PLM001-財務計算用'!$A:$A,$B8)) | AX8: =IF(SUMIFS('PLM002'!$K:$K,'PLM002'!$C:$C,AW$4,'PLM002'!$F:$F,$B8)=0,"",SUMIFS('PLM002'!$K:$K,'PLM002'!$C:$C,AW$4,'PLM002'!$F:$F,$B8)) | AY8: =IF(SUMIFS('PLM001-財務計算用'!$P:$P,'PLM001-財務計算用'!$J:$J,AY$4,'PLM001-財務計算用'!$A:$A,$B8)=0,"",SUMIFS('PLM001-財務計算用'!$P:$P,'PLM001-財務計算用'!$J:$J,AY$4,'PLM001-財務計算用'!$A:$A,$B8)) | AZ8: =IF(SUMIFS('PLM002'!$K:$K,'PLM002'!$C:$C,AY$4,'PLM002'!$F:$F,$B8)=0,"",SUMIFS('PLM002'!$K:$K,'PLM002'!$C:$C,AY$4,'PLM002'!$F:$F,$B8)) | BA8: =IF(SUMIFS('PLM001-財務計算用'!$P:$P,'PLM001-財務計算用'!$J:$J,BA$4,'PLM001-財務計算用'!$A:$A,$B8)=0,"",SUMIFS('PLM001-財務計算用'!$P:$P,'PLM001-財務計算用'!$J:$J,BA$4,'PLM001-財務計算用'!$A:$A,$B8)) | BB8: =IF(SUMIFS('PLM002'!$K:$K,'PLM002'!$C:$C,BA$4,'PLM002'!$F:$F,$B8)=0,"",SUMIFS('PLM002'!$K:$K,'PLM002'!$C:$C,BA$4,'PLM002'!$F:$F,$B8)) | BC8: =IF(SUMIFS('PLM001-財務計算用'!$P:$P,'PLM001-財務計算用'!$J:$J,BC$4,'PLM001-財務計算用'!$A:$A,$B8)=0,"",SUMIFS('PLM001-財務計算用'!$P:$P,'PLM001-財務計算用'!$J:$J,BC$4,'PLM001-財務計算用'!$A:$A,$B8)) | BD8: =IF(SUMIFS('PLM002'!$K:$K,'PLM002'!$C:$C,BC$4,'PLM002'!$F:$F,$B8)=0,"",SUMIFS('PLM002'!$K:$K,'PLM002'!$C:$C,BC$4,'PLM002'!$F:$F,$B8)) | BE8: =IF(SUMIFS('PLM001-財務計算用'!$P:$P,'PLM001-財務計算用'!$J:$J,BE$4,'PLM001-財務計算用'!$A:$A,$B8)=0,"",SUMIFS('PLM001-財務計算用'!$P:$P,'PLM001-財務計算用'!$J:$J,BE$4,'PLM001-財務計算用'!$A:$A,$B8)) | BF8: =IF(SUMIFS('PLM002'!$K:$K,'PLM002'!$C:$C,BE$4,'PLM002'!$F:$F,$B8)=0,"",SUMIFS('PLM002'!$K:$K,'PLM002'!$C:$C,BE$4,'PLM002'!$F:$F,$B8)) | BG8: =IF(SUMIFS('PLM001-財務計算用'!$P:$P,'PLM001-財務計算用'!$J:$J,BG$4,'PLM001-財務計算用'!$A:$A,$B8)=0,"",SUMIFS('PLM001-財務計算用'!$P:$P,'PLM001-財務計算用'!$J:$J,BG$4,'PLM001-財務計算用'!$A:$A,$B8)) | BH8: =IF(SUMIFS('PLM002'!$K:$K,'PLM002'!$C:$C,BG$4,'PLM002'!$F:$F,$B8)=0,"",SUMIFS('PLM002'!$K:$K,'PLM002'!$C:$C,BG$4,'PLM002'!$F:$F,$B8)) | BI8: =IF(SUMIFS('PLM001-財務計算用'!$P:$P,'PLM001-財務計算用'!$J:$J,BI$4,'PLM001-財務計算用'!$A:$A,$B8)=0,"",SUMIFS('PLM001-財務計算用'!$P:$P,'PLM001-財務計算用'!$J:$J,BI$4,'PLM001-財務計算用'!$A:$A,$B8)) | BJ8: =IF(SUMIFS('PLM002'!$K:$K,'PLM002'!$C:$C,BI$4,'PLM002'!$F:$F,$B8)=0,"",SUMIFS('PLM002'!$K:$K,'PLM002'!$C:$C,BI$4,'PLM002'!$F:$F,$B8)) | BK8: =IF(SUMIFS('PLM001-財務計算用'!$P:$P,'PLM001-財務計算用'!$J:$J,BK$4,'PLM001-財務計算用'!$A:$A,$B8)=0,"",SUMIFS('PLM001-財務計算用'!$P:$P,'PLM001-財務計算用'!$J:$J,BK$4,'PLM001-財務計算用'!$A:$A,$B8)) | BL8: =IF(SUMIFS('PLM002'!$K:$K,'PLM002'!$C:$C,BK$4,'PLM002'!$F:$F,$B8)=0,"",SUMIFS('PLM002'!$K:$K,'PLM002'!$C:$C,BK$4,'PLM002'!$F:$F,$B8)) | BM8: =IF(SUMIFS('PLM001-財務計算用'!$P:$P,'PLM001-財務計算用'!$J:$J,BM$4,'PLM001-財務計算用'!$A:$A,$B8)=0,"",SUMIFS('PLM001-財務計算用'!$P:$P,'PLM001-財務計算用'!$J:$J,BM$4,'PLM001-財務計算用'!$A:$A,$B8)) | BN8: =IF(SUMIFS('PLM002'!$K:$K,'PLM002'!$C:$C,BM$4,'PLM002'!$F:$F,$B8)=0,"",SUMIFS('PLM002'!$K:$K,'PLM002'!$C:$C,BM$4,'PLM002'!$F:$F,$B8)) | BO8: =IF(SUMIFS('PLM001-財務計算用'!$P:$P,'PLM001-財務計算用'!$J:$J,BO$4,'PLM001-財務計算用'!$A:$A,$B8)=0,"",SUMIFS('PLM001-財務計算用'!$P:$P,'PLM001-財務計算用'!$J:$J,BO$4,'PLM001-財務計算用'!$A:$A,$B8)) | BP8: =IF(SUMIFS('PLM002'!$K:$K,'PLM002'!$C:$C,BO$4,'PLM002'!$F:$F,$B8)=0,"",SUMIFS('PLM002'!$K:$K,'PLM002'!$C:$C,BO$4,'PLM002'!$F:$F,$B8)) | BQ8: =IF(SUMIFS('PLM001-財務計算用'!$P:$P,'PLM001-財務計算用'!$J:$J,BQ$4,'PLM001-財務計算用'!$A:$A,$B8)=0,"",SUMIFS('PLM001-財務計算用'!$P:$P,'PLM001-財務計算用'!$J:$J,BQ$4,'PLM001-財務計算用'!$A:$A,$B8)) | BR8: =IF(SUMIFS('PLM002'!$K:$K,'PLM002'!$C:$C,BQ$4,'PLM002'!$F:$F,$B8)=0,"",SUMIFS('PLM002'!$K:$K,'PLM002'!$C:$C,BQ$4,'PLM002'!$F:$F,$B8)) | BS8: =IF(SUMIFS('PLM001-財務計算用'!$P:$P,'PLM001-財務計算用'!$J:$J,BS$4,'PLM001-財務計算用'!$A:$A,$B8)=0,"",SUMIFS('PLM001-財務計算用'!$P:$P,'PLM001-財務計算用'!$J:$J,BS$4,'PLM001-財務計算用'!$A:$A,$B8)) | BT8: =IF(SUMIFS('PLM002'!$K:$K,'PLM002'!$C:$C,BS$4,'PLM002'!$F:$F,$B8)=0,"",SUMIFS('PLM002'!$K:$K,'PLM002'!$C:$C,BS$4,'PLM002'!$F:$F,$B8)) | BU8: =IF(SUMIFS('PLM001-財務計算用'!$P:$P,'PLM001-財務計算用'!$J:$J,BU$4,'PLM001-財務計算用'!$A:$A,$B8)=0,"",SUMIFS('PLM001-財務計算用'!$P:$P,'PLM001-財務計算用'!$J:$J,BU$4,'PLM001-財務計算用'!$A:$A,$B8)) | BV8: =IF(SUMIFS('PLM002'!$K:$K,'PLM002'!$C:$C,BU$4,'PLM002'!$F:$F,$B8)=0,"",SUMIFS('PLM002'!$K:$K,'PLM002'!$C:$C,BU$4,'PLM002'!$F:$F,$B8)) | BW8: =IF(SUMIFS('PLM001-財務計算用'!$P:$P,'PLM001-財務計算用'!$J:$J,BW$4,'PLM001-財務計算用'!$A:$A,$B8)=0,"",SUMIFS('PLM001-財務計算用'!$P:$P,'PLM001-財務計算用'!$J:$J,BW$4,'PLM001-財務計算用'!$A:$A,$B8)) | BX8: =IF(SUMIFS('PLM002'!$K:$K,'PLM002'!$C:$C,BW$4,'PLM002'!$F:$F,$B8)=0,"",SUMIFS('PLM002'!$K:$K,'PLM002'!$C:$C,BW$4,'PLM002'!$F:$F,$B8)) | BY8: =IF(SUMIFS('PLM001-財務計算用'!$P:$P,'PLM001-財務計算用'!$J:$J,BY$4,'PLM001-財務計算用'!$A:$A,$B8)=0,"",SUMIFS('PLM001-財務計算用'!$P:$P,'PLM001-財務計算用'!$J:$J,BY$4,'PLM001-財務計算用'!$A:$A,$B8)) | BZ8: =IF(SUMIFS('PLM002'!$K:$K,'PLM002'!$C:$C,BY$4,'PLM002'!$F:$F,$B8)=0,"",SUMIFS('PLM002'!$K:$K,'PLM002'!$C:$C,BY$4,'PLM002'!$F:$F,$B8)) | CA8: =IF(SUMIFS('PLM001-財務計算用'!$P:$P,'PLM001-財務計算用'!$J:$J,CA$4,'PLM001-財務計算用'!$A:$A,$B8)=0,"",SUMIFS('PLM001-財務計算用'!$P:$P,'PLM001-財務計算用'!$J:$J,CA$4,'PLM001-財務計算用'!$A:$A,$B8)) | CB8: =IF(SUMIFS('PLM002'!$K:$K,'PLM002'!$C:$C,CA$4,'PLM002'!$F:$F,$B8)=0,"",SUMIFS('PLM002'!$K:$K,'PLM002'!$C:$C,CA$4,'PLM002'!$F:$F,$B8)) | CC8: =IF(SUMIFS('PLM001-財務計算用'!$P:$P,'PLM001-財務計算用'!$J:$J,CC$4,'PLM001-財務計算用'!$A:$A,$B8)=0,"",SUMIFS('PLM001-財務計算用'!$P:$P,'PLM001-財務計算用'!$J:$J,CC$4,'PLM001-財務計算用'!$A:$A,$B8)) | CD8: =IF(SUMIFS('PLM002'!$K:$K,'PLM002'!$C:$C,CC$4,'PLM002'!$F:$F,$B8)=0,"",SUMIFS('PLM002'!$K:$K,'PLM002'!$C:$C,CC$4,'PLM002'!$F:$F,$B8)) | CE8: =IF(SUMIFS('PLM001-財務計算用'!$P:$P,'PLM001-財務計算用'!$J:$J,CE$4,'PLM001-財務計算用'!$A:$A,$B8)=0,"",SUMIFS('PLM001-財務計算用'!$P:$P,'PLM001-財務計算用'!$J:$J,CE$4,'PLM001-財務計算用'!$A:$A,$B8)) | CF8: =IF(SUMIFS('PLM002'!$K:$K,'PLM002'!$C:$C,CE$4,'PLM002'!$F:$F,$B8)=0,"",SUMIFS('PLM002'!$K:$K,'PLM002'!$C:$C,CE$4,'PLM002'!$F:$F,$B8)) | CG8: =IF(SUMIFS('PLM001-財務計算用'!$P:$P,'PLM001-財務計算用'!$J:$J,CG$4,'PLM001-財務計算用'!$A:$A,$B8)=0,"",SUMIFS('PLM001-財務計算用'!$P:$P,'PLM001-財務計算用'!$J:$J,CG$4,'PLM001-財務計算用'!$A:$A,$B8)) | CH8: =IF(SUMIFS('PLM002'!$K:$K,'PLM002'!$C:$C,CG$4,'PLM002'!$F:$F,$B8)=0,"",SUMIFS('PLM002'!$K:$K,'PLM002'!$C:$C,CG$4,'PLM002'!$F:$F,$B8)) | CI8: =IF(SUMIFS('PLM001-財務計算用'!$P:$P,'PLM001-財務計算用'!$J:$J,CI$4,'PLM001-財務計算用'!$A:$A,$B8)=0,"",SUMIFS('PLM001-財務計算用'!$P:$P,'PLM001-財務計算用'!$J:$J,CI$4,'PLM001-財務計算用'!$A:$A,$B8)) | CJ8: =IF(SUMIFS('PLM002'!$K:$K,'PLM002'!$C:$C,CI$4,'PLM002'!$F:$F,$B8)=0,"",SUMIFS('PLM002'!$K:$K,'PLM002'!$C:$C,CI$4,'PLM002'!$F:$F,$B8)) | CK8: =IF(SUMIFS('PLM001-財務計算用'!$P:$P,'PLM001-財務計算用'!$J:$J,CK$4,'PLM001-財務計算用'!$A:$A,$B8)=0,"",SUMIFS('PLM001-財務計算用'!$P:$P,'PLM001-財務計算用'!$J:$J,CK$4,'PLM001-財務計算用'!$A:$A,$B8)) | CL8: =IF(SUMIFS('PLM002'!$K:$K,'PLM002'!$C:$C,CK$4,'PLM002'!$F:$F,$B8)=0,"",SUMIFS('PLM002'!$K:$K,'PLM002'!$C:$C,CK$4,'PLM002'!$F:$F,$B8)) | CM8: =IF(SUMIFS('PLM001-財務計算用'!$P:$P,'PLM001-財務計算用'!$J:$J,CM$4,'PLM001-財務計算用'!$A:$A,$B8)=0,"",SUMIFS('PLM001-財務計算用'!$P:$P,'PLM001-財務計算用'!$J:$J,CM$4,'PLM001-財務計算用'!$A:$A,$B8)) | CN8: =IF(SUMIFS('PLM002'!$K:$K,'PLM002'!$C:$C,CM$4,'PLM002'!$F:$F,$B8)=0,"",SUMIFS('PLM002'!$K:$K,'PLM002'!$C:$C,CM$4,'PLM002'!$F:$F,$B8)) | CO8: =IF(SUMIFS('PLM001-財務計算用'!$P:$P,'PLM001-財務計算用'!$J:$J,CO$4,'PLM001-財務計算用'!$A:$A,$B8)=0,"",SUMIFS('PLM001-財務計算用'!$P:$P,'PLM001-財務計算用'!$J:$J,CO$4,'PLM001-財務計算用'!$A:$A,$B8)) | CP8: =IF(SUMIFS('PLM002'!$K:$K,'PLM002'!$C:$C,CO$4,'PLM002'!$F:$F,$B8)=0,"",SUMIFS('PLM002'!$K:$K,'PLM002'!$C:$C,CO$4,'PLM002'!$F:$F,$B8)) | CQ8: =IF(SUMIFS('PLM001-財務計算用'!$P:$P,'PLM001-財務計算用'!$J:$J,CQ$4,'PLM001-財務計算用'!$A:$A,$B8)=0,"",SUMIFS('PLM001-財務計算用'!$P:$P,'PLM001-財務計算用'!$J:$J,CQ$4,'PLM001-財務計算用'!$A:$A,$B8)) | CR8: =IF(SUMIFS('PLM002'!$K:$K,'PLM002'!$C:$C,CQ$4,'PLM002'!$F:$F,$B8)=0,"",SUMIFS('PLM002'!$K:$K,'PLM002'!$C:$C,CQ$4,'PLM002'!$F:$F,$B8)) | CS8: =IF(SUMIFS('PLM001-財務計算用'!$P:$P,'PLM001-財務計算用'!$J:$J,CS$4,'PLM001-財務計算用'!$A:$A,$B8)=0,"",SUMIFS('PLM001-財務計算用'!$P:$P,'PLM001-財務計算用'!$J:$J,CS$4,'PLM001-財務計算用'!$A:$A,$B8)) | CT8: =IF(SUMIFS('PLM002'!$K:$K,'PLM002'!$C:$C,CS$4,'PLM002'!$F:$F,$B8)=0,"",SUMIFS('PLM002'!$K:$K,'PLM002'!$C:$C,CS$4,'PLM002'!$F:$F,$B8)) | CU8: =IF(SUMIFS('PLM001-財務計算用'!$P:$P,'PLM001-財務計算用'!$J:$J,CU$4,'PLM001-財務計算用'!$A:$A,$B8)=0,"",SUMIFS('PLM001-財務計算用'!$P:$P,'PLM001-財務計算用'!$J:$J,CU$4,'PLM001-財務計算用'!$A:$A,$B8)) | CV8: =IF(SUMIFS('PLM002'!$K:$K,'PLM002'!$C:$C,CU$4,'PLM002'!$F:$F,$B8)=0,"",SUMIFS('PLM002'!$K:$K,'PLM002'!$C:$C,CU$4,'PLM002'!$F:$F,$B8)) | CW8: =IF(SUMIFS('PLM001-財務計算用'!$P:$P,'PLM001-財務計算用'!$J:$J,CW$4,'PLM001-財務計算用'!$A:$A,$B8)=0,"",SUMIFS('PLM001-財務計算用'!$P:$P,'PLM001-財務計算用'!$J:$J,CW$4,'PLM001-財務計算用'!$A:$A,$B8)) | CX8: =IF(SUMIFS('PLM002'!$K:$K,'PLM002'!$C:$C,CW$4,'PLM002'!$F:$F,$B8)=0,"",SUMIFS('PLM002'!$K:$K,'PLM002'!$C:$C,CW$4,'PLM002'!$F:$F,$B8)) | CY8: =IF(SUMIFS('PLM001-財務計算用'!$P:$P,'PLM001-財務計算用'!$J:$J,CY$4,'PLM001-財務計算用'!$A:$A,$B8)=0,"",SUMIFS('PLM001-財務計算用'!$P:$P,'PLM001-財務計算用'!$J:$J,CY$4,'PLM001-財務計算用'!$A:$A,$B8)) | CZ8: =IF(SUMIFS('PLM002'!$K:$K,'PLM002'!$C:$C,CY$4,'PLM002'!$F:$F,$B8)=0,"",SUMIFS('PLM002'!$K:$K,'PLM002'!$C:$C,CY$4,'PLM002'!$F:$F,$B8)) | DA8: =IF(SUMIFS('PLM001-財務計算用'!$P:$P,'PLM001-財務計算用'!$J:$J,DA$4,'PLM001-財務計算用'!$A:$A,$B8)=0,"",SUMIFS('PLM001-財務計算用'!$P:$P,'PLM001-財務計算用'!$J:$J,DA$4,'PLM001-財務計算用'!$A:$A,$B8)) | DB8: =IF(SUMIFS('PLM002'!$K:$K,'PLM002'!$C:$C,DA$4,'PLM002'!$F:$F,$B8)=0,"",SUMIFS('PLM002'!$K:$K,'PLM002'!$C:$C,DA$4,'PLM002'!$F:$F,$B8)) | DC8: =IF(SUMIFS('PLM001-財務計算用'!$P:$P,'PLM001-財務計算用'!$J:$J,DC$4,'PLM001-財務計算用'!$A:$A,$B8)=0,"",SUMIFS('PLM001-財務計算用'!$P:$P,'PLM001-財務計算用'!$J:$J,DC$4,'PLM001-財務計算用'!$A:$A,$B8)) | DD8: =IF(SUMIFS('PLM002'!$K:$K,'PLM002'!$C:$C,DC$4,'PLM002'!$F:$F,$B8)=0,"",SUMIFS('PLM002'!$K:$K,'PLM002'!$C:$C,DC$4,'PLM002'!$F:$F,$B8)) | DE8: =IF(SUMIFS('PLM001-財務計算用'!$P:$P,'PLM001-財務計算用'!$J:$J,DE$4,'PLM001-財務計算用'!$A:$A,$B8)=0,"",SUMIFS('PLM001-財務計算用'!$P:$P,'PLM001-財務計算用'!$J:$J,DE$4,'PLM001-財務計算用'!$A:$A,$B8)) | DF8: =IF(SUMIFS('PLM002'!$K:$K,'PLM002'!$C:$C,DE$4,'PLM002'!$F:$F,$B8)=0,"",SUMIFS('PLM002'!$K:$K,'PLM002'!$C:$C,DE$4,'PLM002'!$F:$F,$B8)) | DG8: =IF(SUMIFS('PLM001-財務計算用'!$P:$P,'PLM001-財務計算用'!$J:$J,DG$4,'PLM001-財務計算用'!$A:$A,$B8)=0,"",SUMIFS('PLM001-財務計算用'!$P:$P,'PLM001-財務計算用'!$J:$J,DG$4,'PLM001-財務計算用'!$A:$A,$B8)) | DH8: =IF(SUMIFS('PLM002'!$K:$K,'PLM002'!$C:$C,DG$4,'PLM002'!$F:$F,$B8)=0,"",SUMIFS('PLM002'!$K:$K,'PLM002'!$C:$C,DG$4,'PLM002'!$F:$F,$B8)) | DI8: =IF(SUMIFS('PLM001-財務計算用'!$P:$P,'PLM001-財務計算用'!$J:$J,DI$4,'PLM001-財務計算用'!$A:$A,$B8)=0,"",SUMIFS('PLM001-財務計算用'!$P:$P,'PLM001-財務計算用'!$J:$J,DI$4,'PLM001-財務計算用'!$A:$A,$B8)) | DJ8: =IF(SUMIFS('PLM002'!$K:$K,'PLM002'!$C:$C,DI$4,'PLM002'!$F:$F,$B8)=0,"",SUMIFS('PLM002'!$K:$K,'PLM002'!$C:$C,DI$4,'PLM002'!$F:$F,$B8)) | DK8: =IF(SUMIFS('PLM001-財務計算用'!$P:$P,'PLM001-財務計算用'!$J:$J,DK$4,'PLM001-財務計算用'!$A:$A,$B8)=0,"",SUMIFS('PLM001-財務計算用'!$P:$P,'PLM001-財務計算用'!$J:$J,DK$4,'PLM001-財務計算用'!$A:$A,$B8)) | DL8: =IF(SUMIFS('PLM002'!$K:$K,'PLM002'!$C:$C,DK$4,'PLM002'!$F:$F,$B8)=0,"",SUMIFS('PLM002'!$K:$K,'PLM002'!$C:$C,DK$4,'PLM002'!$F:$F,$B8)) | DM8: =IF(SUMIFS('PLM001-財務計算用'!$P:$P,'PLM001-財務計算用'!$J:$J,DM$4,'PLM001-財務計算用'!$A:$A,$B8)=0,"",SUMIFS('PLM001-財務計算用'!$P:$P,'PLM001-財務計算用'!$J:$J,DM$4,'PLM001-財務計算用'!$A:$A,$B8)) | DN8: =IF(SUMIFS('PLM002'!$K:$K,'PLM002'!$C:$C,DM$4,'PLM002'!$F:$F,$B8)=0,"",SUMIFS('PLM002'!$K:$K,'PLM002'!$C:$C,DM$4,'PLM002'!$F:$F,$B8)) | DO8: =IF(SUMIFS('PLM001-財務計算用'!$P:$P,'PLM001-財務計算用'!$J:$J,DO$4,'PLM001-財務計算用'!$A:$A,$B8)=0,"",SUMIFS('PLM001-財務計算用'!$P:$P,'PLM001-財務計算用'!$J:$J,DO$4,'PLM001-財務計算用'!$A:$A,$B8)) -> 779 | DP8: =IF(SUMIFS('PLM002'!$K:$K,'PLM002'!$C:$C,DO$4,'PLM002'!$F:$F,$B8)=0,"",SUMIFS('PLM002'!$K:$K,'PLM002'!$C:$C,DO$4,'PLM002'!$F:$F,$B8)) | DQ8: =IF(SUMIFS('PLM001-財務計算用'!$P:$P,'PLM001-財務計算用'!$J:$J,DQ$4,'PLM001-財務計算用'!$A:$A,$B8)=0,"",SUMIFS('PLM001-財務計算用'!$P:$P,'PLM001-財務計算用'!$J:$J,DQ$4,'PLM001-財務計算用'!$A:$A,$B8)) | DR8: =IF(SUMIFS('PLM002'!$K:$K,'PLM002'!$C:$C,DQ$4,'PLM002'!$F:$F,$B8)=0,"",SUMIFS('PLM002'!$K:$K,'PLM002'!$C:$C,DQ$4,'PLM002'!$F:$F,$B8)) | DS8: =IF(SUMIFS('PLM001-財務計算用'!$P:$P,'PLM001-財務計算用'!$J:$J,DS$4,'PLM001-財務計算用'!$A:$A,$B8)=0,"",SUMIFS('PLM001-財務計算用'!$P:$P,'PLM001-財務計算用'!$J:$J,DS$4,'PLM001-財務計算用'!$A:$A,$B8)) | DT8: =IF(SUMIFS('PLM002'!$K:$K,'PLM002'!$C:$C,DS$4,'PLM002'!$F:$F,$B8)=0,"",SUMIFS('PLM002'!$K:$K,'PLM002'!$C:$C,DS$4,'PLM002'!$F:$F,$B8)) | DU8: =IF(SUMIFS('PLM001-財務計算用'!$P:$P,'PLM001-財務計算用'!$J:$J,DU$4,'PLM001-財務計算用'!$A:$A,$B8)=0,"",SUMIFS('PLM001-財務計算用'!$P:$P,'PLM001-財務計算用'!$J:$J,DU$4,'PLM001-財務計算用'!$A:$A,$B8)) | DV8: =IF(SUMIFS('PLM002'!$K:$K,'PLM002'!$C:$C,DU$4,'PLM002'!$F:$F,$B8)=0,"",SUMIFS('PLM002'!$K:$K,'PLM002'!$C:$C,DU$4,'PLM002'!$F:$F,$B8)) | DW8: =IF(SUMIFS('PLM001-財務計算用'!$P:$P,'PLM001-財務計算用'!$J:$J,DW$4,'PLM001-財務計算用'!$A:$A,$B8)=0,"",SUMIFS('PLM001-財務計算用'!$P:$P,'PLM001-財務計算用'!$J:$J,DW$4,'PLM001-財務計算用'!$A:$A,$B8)) | DX8: =IF(SUMIFS('PLM002'!$K:$K,'PLM002'!$C:$C,DW$4,'PLM002'!$F:$F,$B8)=0,"",SUMIFS('PLM002'!$K:$K,'PLM002'!$C:$C,DW$4,'PLM002'!$F:$F,$B8)) | DY8: =IF(SUMIFS('PLM001-財務計算用'!$P:$P,'PLM001-財務計算用'!$J:$J,DY$4,'PLM001-財務計算用'!$A:$A,$B8)=0,"",SUMIFS('PLM001-財務計算用'!$P:$P,'PLM001-財務計算用'!$J:$J,DY$4,'PLM001-財務計算用'!$A:$A,$B8)) | DZ8: =IF(SUMIFS('PLM002'!$K:$K,'PLM002'!$C:$C,DY$4,'PLM002'!$F:$F,$B8)=0,"",SUMIFS('PLM002'!$K:$K,'PLM002'!$C:$C,DY$4,'PLM002'!$F:$F,$B8)) | EA8: =IF(SUMIFS('PLM001-財務計算用'!$P:$P,'PLM001-財務計算用'!$J:$J,EA$4,'PLM001-財務計算用'!$A:$A,$B8)=0,"",SUMIFS('PLM001-財務計算用'!$P:$P,'PLM001-財務計算用'!$J:$J,EA$4,'PLM001-財務計算用'!$A:$A,$B8)) | EB8: =IF(SUMIFS('PLM002'!$K:$K,'PLM002'!$C:$C,EA$4,'PLM002'!$F:$F,$B8)=0,"",SUMIFS('PLM002'!$K:$K,'PLM002'!$C:$C,EA$4,'PLM002'!$F:$F,$B8)) | EC8: =IF(SUMIFS('PLM001-財務計算用'!$P:$P,'PLM001-財務計算用'!$J:$J,EC$4,'PLM001-財務計算用'!$A:$A,$B8)=0,"",SUMIFS('PLM001-財務計算用'!$P:$P,'PLM001-財務計算用'!$J:$J,EC$4,'PLM001-財務計算用'!$A:$A,$B8)) | ED8: =IF(SUMIFS('PLM002'!$K:$K,'PLM002'!$C:$C,EC$4,'PLM002'!$F:$F,$B8)=0,"",SUMIFS('PLM002'!$K:$K,'PLM002'!$C:$C,EC$4,'PLM002'!$F:$F,$B8))
A9: ='PLM014'!A10 -> D-協同 | B9: D250701R1 | C9: ='PLM014'!C10 -> EGX5标准型技转 | D9: ="("&B9&")"&" "&C9 -> (D250701R1) EGX5标准型技转 | E9: ='PLM014'!E10 -> 研发一部 | F9: ='PLM014'!F10 -> 汪佳凯 | G9: ='PLM014'!G10 -> Active | H9: ='PLM014'!H10 -> 45872.667 | I9: ='PLM014'!I10 -> 46076.667 | J9: =IF(ISERROR(DATEDIF(H9,I9,"d")),"",DATEDIF(H9,I9,"d")) -> 204 | K9: =H9+(J9*0.75) -> 46025.667 | L9: =H9+(J9*0.95) -> 46066.467 | M9: =IF(ISERROR('PLM014'!L10),"",('PLM014'!L10)) -> 45873 | N9: =IF(IF(ISERROR('PLM014'!N10),"",('PLM014'!N10))=0,"",IF(ISERROR('PLM014'!N10),"",('PLM014'!N10))) | O9: =IF(ISERROR(DATEDIF(M9,N9,"d")),"",IF(DATEDIF(M9,N9,"d")=0,"",DATEDIF(M9,N9,"d"))) | P9: =IF(N9="",TODAY(),N9) -> 46044 | Q9: =IF(ISERROR(DATEDIF(M9,P9,"d")),"",IF(DATEDIF(M9,P9,"d")=0,"",DATEDIF(M9,P9,"d"))) -> 171 | R9: ='PLM014'!Q10/100 -> 0.87 | S9: =IF(AND(TODAY()>I9,R9<>100%,G9="Active"),"專案延遲 "&DATEDIF(I9,TODAY(),"d")&" 天",IF(AND(TODAY()>K9,R9<75%,G9="Active"),"專案即將異常",IF(AND(TODAY()>L9,R9<95%,G9="Active"),"專案即將異常",""))) | U9: =IF(SUMIF($Y$5:$CV$5,$U$5,Y9:CV9)=0,"未登入",SUMIF($Y$5:$CV$5,$U$5,Y9:CV9)) -> 未登入 | V9: =SUMIF($Y$5:$CV$5,$V$5,Y9:CV9) -> 0 | W9: =IF(SUMIFS('PLM001-財務計算用'!$P:$P,'PLM001-財務計算用'!$A:$A,B9)=0,"未登入",SUMIFS('PLM001-財務計算用'!$P:$P,'PLM001-財務計算用'!$A:$A,B9)) -> 839 | X9: =SUMIFS('PLM002'!$K:$K,'PLM002'!$F:$F,$B9) -> 0 | Y9: =IF(SUMIFS('PLM001-財務計算用'!$P:$P,'PLM001-財務計算用'!$J:$J,Y$4,'PLM001-財務計算用'!$A:$A,$B9)=0,"",SUMIFS('PLM001-財務計算用'!$P:$P,'PLM001-財務計算用'!$J:$J,Y$4,'PLM001-財務計算用'!$A:$A,$B9)) | Z9: =IF(SUMIFS('PLM002'!$K:$K,'PLM002'!$C:$C,Y$4,'PLM002'!$F:$F,$B9)=0,"",SUMIFS('PLM002'!$K:$K,'PLM002'!$C:$C,Y$4,'PLM002'!$F:$F,$B9)) | AA9: =IF(SUMIFS('PLM001-財務計算用'!$P:$P,'PLM001-財務計算用'!$J:$J,AA$4,'PLM001-財務計算用'!$A:$A,$B9)=0,"",SUMIFS('PLM001-財務計算用'!$P:$P,'PLM001-財務計算用'!$J:$J,AA$4,'PLM001-財務計算用'!$A:$A,$B9)) | AB9: =IF(SUMIFS('PLM002'!$K:$K,'PLM002'!$C:$C,AA$4,'PLM002'!$F:$F,$B9)=0,"",SUMIFS('PLM002'!$K:$K,'PLM002'!$C:$C,AA$4,'PLM002'!$F:$F,$B9)) | AC9: =IF(SUMIFS('PLM001-財務計算用'!$P:$P,'PLM001-財務計算用'!$J:$J,AC$4,'PLM001-財務計算用'!$A:$A,$B9)=0,"",SUMIFS('PLM001-財務計算用'!$P:$P,'PLM001-財務計算用'!$J:$J,AC$4,'PLM001-財務計算用'!$A:$A,$B9)) | AD9: =IF(SUMIFS('PLM002'!$K:$K,'PLM002'!$C:$C,AC$4,'PLM002'!$F:$F,$B9)=0,"",SUMIFS('PLM002'!$K:$K,'PLM002'!$C:$C,AC$4,'PLM002'!$F:$F,$B9)) | AE9: =IF(SUMIFS('PLM001-財務計算用'!$P:$P,'PLM001-財務計算用'!$J:$J,AE$4,'PLM001-財務計算用'!$A:$A,$B9)=0,"",SUMIFS('PLM001-財務計算用'!$P:$P,'PLM001-財務計算用'!$J:$J,AE$4,'PLM001-財務計算用'!$A:$A,$B9)) | AF9: =IF(SUMIFS('PLM002'!$K:$K,'PLM002'!$C:$C,AE$4,'PLM002'!$F:$F,$B9)=0,"",SUMIFS('PLM002'!$K:$K,'PLM002'!$C:$C,AE$4,'PLM002'!$F:$F,$B9)) | AG9: =IF(SUMIFS('PLM001-財務計算用'!$P:$P,'PLM001-財務計算用'!$J:$J,AG$4,'PLM001-財務計算用'!$A:$A,$B9)=0,"",SUMIFS('PLM001-財務計算用'!$P:$P,'PLM001-財務計算用'!$J:$J,AG$4,'PLM001-財務計算用'!$A:$A,$B9)) | AH9: =IF(SUMIFS('PLM002'!$K:$K,'PLM002'!$C:$C,AG$4,'PLM002'!$F:$F,$B9)=0,"",SUMIFS('PLM002'!$K:$K,'PLM002'!$C:$C,AG$4,'PLM002'!$F:$F,$B9)) | AI9: =IF(SUMIFS('PLM001-財務計算用'!$P:$P,'PLM001-財務計算用'!$J:$J,AI$4,'PLM001-財務計算用'!$A:$A,$B9)=0,"",SUMIFS('PLM001-財務計算用'!$P:$P,'PLM001-財務計算用'!$J:$J,AI$4,'PLM001-財務計算用'!$A:$A,$B9)) | AJ9: =IF(SUMIFS('PLM002'!$K:$K,'PLM002'!$C:$C,AI$4,'PLM002'!$F:$F,$B9)=0,"",SUMIFS('PLM002'!$K:$K,'PLM002'!$C:$C,AI$4,'PLM002'!$F:$F,$B9)) | AK9: =IF(SUMIFS('PLM001-財務計算用'!$P:$P,'PLM001-財務計算用'!$J:$J,AK$4,'PLM001-財務計算用'!$A:$A,$B9)=0,"",SUMIFS('PLM001-財務計算用'!$P:$P,'PLM001-財務計算用'!$J:$J,AK$4,'PLM001-財務計算用'!$A:$A,$B9)) | AL9: =IF(SUMIFS('PLM002'!$K:$K,'PLM002'!$C:$C,AK$4,'PLM002'!$F:$F,$B9)=0,"",SUMIFS('PLM002'!$K:$K,'PLM002'!$C:$C,AK$4,'PLM002'!$F:$F,$B9)) | AM9: =IF(SUMIFS('PLM001-財務計算用'!$P:$P,'PLM001-財務計算用'!$J:$J,AM$4,'PLM001-財務計算用'!$A:$A,$B9)=0,"",SUMIFS('PLM001-財務計算用'!$P:$P,'PLM001-財務計算用'!$J:$J,AM$4,'PLM001-財務計算用'!$A:$A,$B9)) | AN9: =IF(SUMIFS('PLM002'!$K:$K,'PLM002'!$C:$C,AM$4,'PLM002'!$F:$F,$B9)=0,"",SUMIFS('PLM002'!$K:$K,'PLM002'!$C:$C,AM$4,'PLM002'!$F:$F,$B9)) | AO9: =IF(SUMIFS('PLM001-財務計算用'!$P:$P,'PLM001-財務計算用'!$J:$J,AO$4,'PLM001-財務計算用'!$A:$A,$B9)=0,"",SUMIFS('PLM001-財務計算用'!$P:$P,'PLM001-財務計算用'!$J:$J,AO$4,'PLM001-財務計算用'!$A:$A,$B9)) | AP9: =IF(SUMIFS('PLM002'!$K:$K,'PLM002'!$C:$C,AO$4,'PLM002'!$F:$F,$B9)=0,"",SUMIFS('PLM002'!$K:$K,'PLM002'!$C:$C,AO$4,'PLM002'!$F:$F,$B9)) | AQ9: =IF(SUMIFS('PLM001-財務計算用'!$P:$P,'PLM001-財務計算用'!$J:$J,AQ$4,'PLM001-財務計算用'!$A:$A,$B9)=0,"",SUMIFS('PLM001-財務計算用'!$P:$P,'PLM001-財務計算用'!$J:$J,AQ$4,'PLM001-財務計算用'!$A:$A,$B9)) | AR9: =IF(SUMIFS('PLM002'!$K:$K,'PLM002'!$C:$C,AQ$4,'PLM002'!$F:$F,$B9)=0,"",SUMIFS('PLM002'!$K:$K,'PLM002'!$C:$C,AQ$4,'PLM002'!$F:$F,$B9)) | AS9: =IF(SUMIFS('PLM001-財務計算用'!$P:$P,'PLM001-財務計算用'!$J:$J,AS$4,'PLM001-財務計算用'!$A:$A,$B9)=0,"",SUMIFS('PLM001-財務計算用'!$P:$P,'PLM001-財務計算用'!$J:$J,AS$4,'PLM001-財務計算用'!$A:$A,$B9)) | AT9: =IF(SUMIFS('PLM002'!$K:$K,'PLM002'!$C:$C,AS$4,'PLM002'!$F:$F,$B9)=0,"",SUMIFS('PLM002'!$K:$K,'PLM002'!$C:$C,AS$4,'PLM002'!$F:$F,$B9)) | AU9: =IF(SUMIFS('PLM001-財務計算用'!$P:$P,'PLM001-財務計算用'!$J:$J,AU$4,'PLM001-財務計算用'!$A:$A,$B9)=0,"",SUMIFS('PLM001-財務計算用'!$P:$P,'PLM001-財務計算用'!$J:$J,AU$4,'PLM001-財務計算用'!$A:$A,$B9)) | AV9: =IF(SUMIFS('PLM002'!$K:$K,'PLM002'!$C:$C,AU$4,'PLM002'!$F:$F,$B9)=0,"",SUMIFS('PLM002'!$K:$K,'PLM002'!$C:$C,AU$4,'PLM002'!$F:$F,$B9)) | AW9: =IF(SUMIFS('PLM001-財務計算用'!$P:$P,'PLM001-財務計算用'!$J:$J,AW$4,'PLM001-財務計算用'!$A:$A,$B9)=0,"",SUMIFS('PLM001-財務計算用'!$P:$P,'PLM001-財務計算用'!$J:$J,AW$4,'PLM001-財務計算用'!$A:$A,$B9)) | AX9: =IF(SUMIFS('PLM002'!$K:$K,'PLM002'!$C:$C,AW$4,'PLM002'!$F:$F,$B9)=0,"",SUMIFS('PLM002'!$K:$K,'PLM002'!$C:$C,AW$4,'PLM002'!$F:$F,$B9)) | AY9: =IF(SUMIFS('PLM001-財務計算用'!$P:$P,'PLM001-財務計算用'!$J:$J,AY$4,'PLM001-財務計算用'!$A:$A,$B9)=0,"",SUMIFS('PLM001-財務計算用'!$P:$P,'PLM001-財務計算用'!$J:$J,AY$4,'PLM001-財務計算用'!$A:$A,$B9)) | AZ9: =IF(SUMIFS('PLM002'!$K:$K,'PLM002'!$C:$C,AY$4,'PLM002'!$F:$F,$B9)=0,"",SUMIFS('PLM002'!$K:$K,'PLM002'!$C:$C,AY$4,'PLM002'!$F:$F,$B9)) | BA9: =IF(SUMIFS('PLM001-財務計算用'!$P:$P,'PLM001-財務計算用'!$J:$J,BA$4,'PLM001-財務計算用'!$A:$A,$B9)=0,"",SUMIFS('PLM001-財務計算用'!$P:$P,'PLM001-財務計算用'!$J:$J,BA$4,'PLM001-財務計算用'!$A:$A,$B9)) | BB9: =IF(SUMIFS('PLM002'!$K:$K,'PLM002'!$C:$C,BA$4,'PLM002'!$F:$F,$B9)=0,"",SUMIFS('PLM002'!$K:$K,'PLM002'!$C:$C,BA$4,'PLM002'!$F:$F,$B9)) | BC9: =IF(SUMIFS('PLM001-財務計算用'!$P:$P,'PLM001-財務計算用'!$J:$J,BC$4,'PLM001-財務計算用'!$A:$A,$B9)=0,"",SUMIFS('PLM001-財務計算用'!$P:$P,'PLM001-財務計算用'!$J:$J,BC$4,'PLM001-財務計算用'!$A:$A,$B9)) | BD9: =IF(SUMIFS('PLM002'!$K:$K,'PLM002'!$C:$C,BC$4,'PLM002'!$F:$F,$B9)=0,"",SUMIFS('PLM002'!$K:$K,'PLM002'!$C:$C,BC$4,'PLM002'!$F:$F,$B9)) | BE9: =IF(SUMIFS('PLM001-財務計算用'!$P:$P,'PLM001-財務計算用'!$J:$J,BE$4,'PLM001-財務計算用'!$A:$A,$B9)=0,"",SUMIFS('PLM001-財務計算用'!$P:$P,'PLM001-財務計算用'!$J:$J,BE$4,'PLM001-財務計算用'!$A:$A,$B9)) | BF9: =IF(SUMIFS('PLM002'!$K:$K,'PLM002'!$C:$C,BE$4,'PLM002'!$F:$F,$B9)=0,"",SUMIFS('PLM002'!$K:$K,'PLM002'!$C:$C,BE$4,'PLM002'!$F:$F,$B9)) | BG9: =IF(SUMIFS('PLM001-財務計算用'!$P:$P,'PLM001-財務計算用'!$J:$J,BG$4,'PLM001-財務計算用'!$A:$A,$B9)=0,"",SUMIFS('PLM001-財務計算用'!$P:$P,'PLM001-財務計算用'!$J:$J,BG$4,'PLM001-財務計算用'!$A:$A,$B9)) | BH9: =IF(SUMIFS('PLM002'!$K:$K,'PLM002'!$C:$C,BG$4,'PLM002'!$F:$F,$B9)=0,"",SUMIFS('PLM002'!$K:$K,'PLM002'!$C:$C,BG$4,'PLM002'!$F:$F,$B9)) | BI9: =IF(SUMIFS('PLM001-財務計算用'!$P:$P,'PLM001-財務計算用'!$J:$J,BI$4,'PLM001-財務計算用'!$A:$A,$B9)=0,"",SUMIFS('PLM001-財務計算用'!$P:$P,'PLM001-財務計算用'!$J:$J,BI$4,'PLM001-財務計算用'!$A:$A,$B9)) | BJ9: =IF(SUMIFS('PLM002'!$K:$K,'PLM002'!$C:$C,BI$4,'PLM002'!$F:$F,$B9)=0,"",SUMIFS('PLM002'!$K:$K,'PLM002'!$C:$C,BI$4,'PLM002'!$F:$F,$B9)) | BK9: =IF(SUMIFS('PLM001-財務計算用'!$P:$P,'PLM001-財務計算用'!$J:$J,BK$4,'PLM001-財務計算用'!$A:$A,$B9)=0,"",SUMIFS('PLM001-財務計算用'!$P:$P,'PLM001-財務計算用'!$J:$J,BK$4,'PLM001-財務計算用'!$A:$A,$B9)) | BL9: =IF(SUMIFS('PLM002'!$K:$K,'PLM002'!$C:$C,BK$4,'PLM002'!$F:$F,$B9)=0,"",SUMIFS('PLM002'!$K:$K,'PLM002'!$C:$C,BK$4,'PLM002'!$F:$F,$B9)) | BM9: =IF(SUMIFS('PLM001-財務計算用'!$P:$P,'PLM001-財務計算用'!$J:$J,BM$4,'PLM001-財務計算用'!$A:$A,$B9)=0,"",SUMIFS('PLM001-財務計算用'!$P:$P,'PLM001-財務計算用'!$J:$J,BM$4,'PLM001-財務計算用'!$A:$A,$B9)) | BN9: =IF(SUMIFS('PLM002'!$K:$K,'PLM002'!$C:$C,BM$4,'PLM002'!$F:$F,$B9)=0,"",SUMIFS('PLM002'!$K:$K,'PLM002'!$C:$C,BM$4,'PLM002'!$F:$F,$B9)) | BO9: =IF(SUMIFS('PLM001-財務計算用'!$P:$P,'PLM001-財務計算用'!$J:$J,BO$4,'PLM001-財務計算用'!$A:$A,$B9)=0,"",SUMIFS('PLM001-財務計算用'!$P:$P,'PLM001-財務計算用'!$J:$J,BO$4,'PLM001-財務計算用'!$A:$A,$B9)) | BP9: =IF(SUMIFS('PLM002'!$K:$K,'PLM002'!$C:$C,BO$4,'PLM002'!$F:$F,$B9)=0,"",SUMIFS('PLM002'!$K:$K,'PLM002'!$C:$C,BO$4,'PLM002'!$F:$F,$B9)) | BQ9: =IF(SUMIFS('PLM001-財務計算用'!$P:$P,'PLM001-財務計算用'!$J:$J,BQ$4,'PLM001-財務計算用'!$A:$A,$B9)=0,"",SUMIFS('PLM001-財務計算用'!$P:$P,'PLM001-財務計算用'!$J:$J,BQ$4,'PLM001-財務計算用'!$A:$A,$B9)) | BR9: =IF(SUMIFS('PLM002'!$K:$K,'PLM002'!$C:$C,BQ$4,'PLM002'!$F:$F,$B9)=0,"",SUMIFS('PLM002'!$K:$K,'PLM002'!$C:$C,BQ$4,'PLM002'!$F:$F,$B9)) | BS9: =IF(SUMIFS('PLM001-財務計算用'!$P:$P,'PLM001-財務計算用'!$J:$J,BS$4,'PLM001-財務計算用'!$A:$A,$B9)=0,"",SUMIFS('PLM001-財務計算用'!$P:$P,'PLM001-財務計算用'!$J:$J,BS$4,'PLM001-財務計算用'!$A:$A,$B9)) | BT9: =IF(SUMIFS('PLM002'!$K:$K,'PLM002'!$C:$C,BS$4,'PLM002'!$F:$F,$B9)=0,"",SUMIFS('PLM002'!$K:$K,'PLM002'!$C:$C,BS$4,'PLM002'!$F:$F,$B9)) | BU9: =IF(SUMIFS('PLM001-財務計算用'!$P:$P,'PLM001-財務計算用'!$J:$J,BU$4,'PLM001-財務計算用'!$A:$A,$B9)=0,"",SUMIFS('PLM001-財務計算用'!$P:$P,'PLM001-財務計算用'!$J:$J,BU$4,'PLM001-財務計算用'!$A:$A,$B9)) | BV9: =IF(SUMIFS('PLM002'!$K:$K,'PLM002'!$C:$C,BU$4,'PLM002'!$F:$F,$B9)=0,"",SUMIFS('PLM002'!$K:$K,'PLM002'!$C:$C,BU$4,'PLM002'!$F:$F,$B9)) | BW9: =IF(SUMIFS('PLM001-財務計算用'!$P:$P,'PLM001-財務計算用'!$J:$J,BW$4,'PLM001-財務計算用'!$A:$A,$B9)=0,"",SUMIFS('PLM001-財務計算用'!$P:$P,'PLM001-財務計算用'!$J:$J,BW$4,'PLM001-財務計算用'!$A:$A,$B9)) | BX9: =IF(SUMIFS('PLM002'!$K:$K,'PLM002'!$C:$C,BW$4,'PLM002'!$F:$F,$B9)=0,"",SUMIFS('PLM002'!$K:$K,'PLM002'!$C:$C,BW$4,'PLM002'!$F:$F,$B9)) | BY9: =IF(SUMIFS('PLM001-財務計算用'!$P:$P,'PLM001-財務計算用'!$J:$J,BY$4,'PLM001-財務計算用'!$A:$A,$B9)=0,"",SUMIFS('PLM001-財務計算用'!$P:$P,'PLM001-財務計算用'!$J:$J,BY$4,'PLM001-財務計算用'!$A:$A,$B9)) | BZ9: =IF(SUMIFS('PLM002'!$K:$K,'PLM002'!$C:$C,BY$4,'PLM002'!$F:$F,$B9)=0,"",SUMIFS('PLM002'!$K:$K,'PLM002'!$C:$C,BY$4,'PLM002'!$F:$F,$B9)) | CA9: =IF(SUMIFS('PLM001-財務計算用'!$P:$P,'PLM001-財務計算用'!$J:$J,CA$4,'PLM001-財務計算用'!$A:$A,$B9)=0,"",SUMIFS('PLM001-財務計算用'!$P:$P,'PLM001-財務計算用'!$J:$J,CA$4,'PLM001-財務計算用'!$A:$A,$B9)) | CB9: =IF(SUMIFS('PLM002'!$K:$K,'PLM002'!$C:$C,CA$4,'PLM002'!$F:$F,$B9)=0,"",SUMIFS('PLM002'!$K:$K,'PLM002'!$C:$C,CA$4,'PLM002'!$F:$F,$B9)) | CC9: =IF(SUMIFS('PLM001-財務計算用'!$P:$P,'PLM001-財務計算用'!$J:$J,CC$4,'PLM001-財務計算用'!$A:$A,$B9)=0,"",SUMIFS('PLM001-財務計算用'!$P:$P,'PLM001-財務計算用'!$J:$J,CC$4,'PLM001-財務計算用'!$A:$A,$B9)) | CD9: =IF(SUMIFS('PLM002'!$K:$K,'PLM002'!$C:$C,CC$4,'PLM002'!$F:$F,$B9)=0,"",SUMIFS('PLM002'!$K:$K,'PLM002'!$C:$C,CC$4,'PLM002'!$F:$F,$B9)) | CE9: =IF(SUMIFS('PLM001-財務計算用'!$P:$P,'PLM001-財務計算用'!$J:$J,CE$4,'PLM001-財務計算用'!$A:$A,$B9)=0,"",SUMIFS('PLM001-財務計算用'!$P:$P,'PLM001-財務計算用'!$J:$J,CE$4,'PLM001-財務計算用'!$A:$A,$B9)) | CF9: =IF(SUMIFS('PLM002'!$K:$K,'PLM002'!$C:$C,CE$4,'PLM002'!$F:$F,$B9)=0,"",SUMIFS('PLM002'!$K:$K,'PLM002'!$C:$C,CE$4,'PLM002'!$F:$F,$B9)) | CG9: =IF(SUMIFS('PLM001-財務計算用'!$P:$P,'PLM001-財務計算用'!$J:$J,CG$4,'PLM001-財務計算用'!$A:$A,$B9)=0,"",SUMIFS('PLM001-財務計算用'!$P:$P,'PLM001-財務計算用'!$J:$J,CG$4,'PLM001-財務計算用'!$A:$A,$B9)) | CH9: =IF(SUMIFS('PLM002'!$K:$K,'PLM002'!$C:$C,CG$4,'PLM002'!$F:$F,$B9)=0,"",SUMIFS('PLM002'!$K:$K,'PLM002'!$C:$C,CG$4,'PLM002'!$F:$F,$B9)) | CI9: =IF(SUMIFS('PLM001-財務計算用'!$P:$P,'PLM001-財務計算用'!$J:$J,CI$4,'PLM001-財務計算用'!$A:$A,$B9)=0,"",SUMIFS('PLM001-財務計算用'!$P:$P,'PLM001-財務計算用'!$J:$J,CI$4,'PLM001-財務計算用'!$A:$A,$B9)) | CJ9: =IF(SUMIFS('PLM002'!$K:$K,'PLM002'!$C:$C,CI$4,'PLM002'!$F:$F,$B9)=0,"",SUMIFS('PLM002'!$K:$K,'PLM002'!$C:$C,CI$4,'PLM002'!$F:$F,$B9)) | CK9: =IF(SUMIFS('PLM001-財務計算用'!$P:$P,'PLM001-財務計算用'!$J:$J,CK$4,'PLM001-財務計算用'!$A:$A,$B9)=0,"",SUMIFS('PLM001-財務計算用'!$P:$P,'PLM001-財務計算用'!$J:$J,CK$4,'PLM001-財務計算用'!$A:$A,$B9)) | CL9: =IF(SUMIFS('PLM002'!$K:$K,'PLM002'!$C:$C,CK$4,'PLM002'!$F:$F,$B9)=0,"",SUMIFS('PLM002'!$K:$K,'PLM002'!$C:$C,CK$4,'PLM002'!$F:$F,$B9)) | CM9: =IF(SUMIFS('PLM001-財務計算用'!$P:$P,'PLM001-財務計算用'!$J:$J,CM$4,'PLM001-財務計算用'!$A:$A,$B9)=0,"",SUMIFS('PLM001-財務計算用'!$P:$P,'PLM001-財務計算用'!$J:$J,CM$4,'PLM001-財務計算用'!$A:$A,$B9)) | CN9: =IF(SUMIFS('PLM002'!$K:$K,'PLM002'!$C:$C,CM$4,'PLM002'!$F:$F,$B9)=0,"",SUMIFS('PLM002'!$K:$K,'PLM002'!$C:$C,CM$4,'PLM002'!$F:$F,$B9)) | CO9: =IF(SUMIFS('PLM001-財務計算用'!$P:$P,'PLM001-財務計算用'!$J:$J,CO$4,'PLM001-財務計算用'!$A:$A,$B9)=0,"",SUMIFS('PLM001-財務計算用'!$P:$P,'PLM001-財務計算用'!$J:$J,CO$4,'PLM001-財務計算用'!$A:$A,$B9)) | CP9: =IF(SUMIFS('PLM002'!$K:$K,'PLM002'!$C:$C,CO$4,'PLM002'!$F:$F,$B9)=0,"",SUMIFS('PLM002'!$K:$K,'PLM002'!$C:$C,CO$4,'PLM002'!$F:$F,$B9)) | CQ9: =IF(SUMIFS('PLM001-財務計算用'!$P:$P,'PLM001-財務計算用'!$J:$J,CQ$4,'PLM001-財務計算用'!$A:$A,$B9)=0,"",SUMIFS('PLM001-財務計算用'!$P:$P,'PLM001-財務計算用'!$J:$J,CQ$4,'PLM001-財務計算用'!$A:$A,$B9)) | CR9: =IF(SUMIFS('PLM002'!$K:$K,'PLM002'!$C:$C,CQ$4,'PLM002'!$F:$F,$B9)=0,"",SUMIFS('PLM002'!$K:$K,'PLM002'!$C:$C,CQ$4,'PLM002'!$F:$F,$B9)) | CS9: =IF(SUMIFS('PLM001-財務計算用'!$P:$P,'PLM001-財務計算用'!$J:$J,CS$4,'PLM001-財務計算用'!$A:$A,$B9)=0,"",SUMIFS('PLM001-財務計算用'!$P:$P,'PLM001-財務計算用'!$J:$J,CS$4,'PLM001-財務計算用'!$A:$A,$B9)) | CT9: =IF(SUMIFS('PLM002'!$K:$K,'PLM002'!$C:$C,CS$4,'PLM002'!$F:$F,$B9)=0,"",SUMIFS('PLM002'!$K:$K,'PLM002'!$C:$C,CS$4,'PLM002'!$F:$F,$B9)) | CU9: =IF(SUMIFS('PLM001-財務計算用'!$P:$P,'PLM001-財務計算用'!$J:$J,CU$4,'PLM001-財務計算用'!$A:$A,$B9)=0,"",SUMIFS('PLM001-財務計算用'!$P:$P,'PLM001-財務計算用'!$J:$J,CU$4,'PLM001-財務計算用'!$A:$A,$B9)) | CV9: =IF(SUMIFS('PLM002'!$K:$K,'PLM002'!$C:$C,CU$4,'PLM002'!$F:$F,$B9)=0,"",SUMIFS('PLM002'!$K:$K,'PLM002'!$C:$C,CU$4,'PLM002'!$F:$F,$B9)) | CW9: =IF(SUMIFS('PLM001-財務計算用'!$P:$P,'PLM001-財務計算用'!$J:$J,CW$4,'PLM001-財務計算用'!$A:$A,$B9)=0,"",SUMIFS('PLM001-財務計算用'!$P:$P,'PLM001-財務計算用'!$J:$J,CW$4,'PLM001-財務計算用'!$A:$A,$B9)) | CX9: =IF(SUMIFS('PLM002'!$K:$K,'PLM002'!$C:$C,CW$4,'PLM002'!$F:$F,$B9)=0,"",SUMIFS('PLM002'!$K:$K,'PLM002'!$C:$C,CW$4,'PLM002'!$F:$F,$B9)) | CY9: =IF(SUMIFS('PLM001-財務計算用'!$P:$P,'PLM001-財務計算用'!$J:$J,CY$4,'PLM001-財務計算用'!$A:$A,$B9)=0,"",SUMIFS('PLM001-財務計算用'!$P:$P,'PLM001-財務計算用'!$J:$J,CY$4,'PLM001-財務計算用'!$A:$A,$B9)) | CZ9: =IF(SUMIFS('PLM002'!$K:$K,'PLM002'!$C:$C,CY$4,'PLM002'!$F:$F,$B9)=0,"",SUMIFS('PLM002'!$K:$K,'PLM002'!$C:$C,CY$4,'PLM002'!$F:$F,$B9)) | DA9: =IF(SUMIFS('PLM001-財務計算用'!$P:$P,'PLM001-財務計算用'!$J:$J,DA$4,'PLM001-財務計算用'!$A:$A,$B9)=0,"",SUMIFS('PLM001-財務計算用'!$P:$P,'PLM001-財務計算用'!$J:$J,DA$4,'PLM001-財務計算用'!$A:$A,$B9)) | DB9: =IF(SUMIFS('PLM002'!$K:$K,'PLM002'!$C:$C,DA$4,'PLM002'!$F:$F,$B9)=0,"",SUMIFS('PLM002'!$K:$K,'PLM002'!$C:$C,DA$4,'PLM002'!$F:$F,$B9)) | DC9: =IF(SUMIFS('PLM001-財務計算用'!$P:$P,'PLM001-財務計算用'!$J:$J,DC$4,'PLM001-財務計算用'!$A:$A,$B9)=0,"",SUMIFS('PLM001-財務計算用'!$P:$P,'PLM001-財務計算用'!$J:$J,DC$4,'PLM001-財務計算用'!$A:$A,$B9)) | DD9: =IF(SUMIFS('PLM002'!$K:$K,'PLM002'!$C:$C,DC$4,'PLM002'!$F:$F,$B9)=0,"",SUMIFS('PLM002'!$K:$K,'PLM002'!$C:$C,DC$4,'PLM002'!$F:$F,$B9)) | DE9: =IF(SUMIFS('PLM001-財務計算用'!$P:$P,'PLM001-財務計算用'!$J:$J,DE$4,'PLM001-財務計算用'!$A:$A,$B9)=0,"",SUMIFS('PLM001-財務計算用'!$P:$P,'PLM001-財務計算用'!$J:$J,DE$4,'PLM001-財務計算用'!$A:$A,$B9)) | DF9: =IF(SUMIFS('PLM002'!$K:$K,'PLM002'!$C:$C,DE$4,'PLM002'!$F:$F,$B9)=0,"",SUMIFS('PLM002'!$K:$K,'PLM002'!$C:$C,DE$4,'PLM002'!$F:$F,$B9)) | DG9: =IF(SUMIFS('PLM001-財務計算用'!$P:$P,'PLM001-財務計算用'!$J:$J,DG$4,'PLM001-財務計算用'!$A:$A,$B9)=0,"",SUMIFS('PLM001-財務計算用'!$P:$P,'PLM001-財務計算用'!$J:$J,DG$4,'PLM001-財務計算用'!$A:$A,$B9)) | DH9: =IF(SUMIFS('PLM002'!$K:$K,'PLM002'!$C:$C,DG$4,'PLM002'!$F:$F,$B9)=0,"",SUMIFS('PLM002'!$K:$K,'PLM002'!$C:$C,DG$4,'PLM002'!$F:$F,$B9)) | DI9: =IF(SUMIFS('PLM001-財務計算用'!$P:$P,'PLM001-財務計算用'!$J:$J,DI$4,'PLM001-財務計算用'!$A:$A,$B9)=0,"",SUMIFS('PLM001-財務計算用'!$P:$P,'PLM001-財務計算用'!$J:$J,DI$4,'PLM001-財務計算用'!$A:$A,$B9)) | DJ9: =IF(SUMIFS('PLM002'!$K:$K,'PLM002'!$C:$C,DI$4,'PLM002'!$F:$F,$B9)=0,"",SUMIFS('PLM002'!$K:$K,'PLM002'!$C:$C,DI$4,'PLM002'!$F:$F,$B9)) | DK9: =IF(SUMIFS('PLM001-財務計算用'!$P:$P,'PLM001-財務計算用'!$J:$J,DK$4,'PLM001-財務計算用'!$A:$A,$B9)=0,"",SUMIFS('PLM001-財務計算用'!$P:$P,'PLM001-財務計算用'!$J:$J,DK$4,'PLM001-財務計算用'!$A:$A,$B9)) | DL9: =IF(SUMIFS('PLM002'!$K:$K,'PLM002'!$C:$C,DK$4,'PLM002'!$F:$F,$B9)=0,"",SUMIFS('PLM002'!$K:$K,'PLM002'!$C:$C,DK$4,'PLM002'!$F:$F,$B9)) | DM9: =IF(SUMIFS('PLM001-財務計算用'!$P:$P,'PLM001-財務計算用'!$J:$J,DM$4,'PLM001-財務計算用'!$A:$A,$B9)=0,"",SUMIFS('PLM001-財務計算用'!$P:$P,'PLM001-財務計算用'!$J:$J,DM$4,'PLM001-財務計算用'!$A:$A,$B9)) | DN9: =IF(SUMIFS('PLM002'!$K:$K,'PLM002'!$C:$C,DM$4,'PLM002'!$F:$F,$B9)=0,"",SUMIFS('PLM002'!$K:$K,'PLM002'!$C:$C,DM$4,'PLM002'!$F:$F,$B9)) | DO9: =IF(SUMIFS('PLM001-財務計算用'!$P:$P,'PLM001-財務計算用'!$J:$J,DO$4,'PLM001-財務計算用'!$A:$A,$B9)=0,"",SUMIFS('PLM001-財務計算用'!$P:$P,'PLM001-財務計算用'!$J:$J,DO$4,'PLM001-財務計算用'!$A:$A,$B9)) -> 839 | DP9: =IF(SUMIFS('PLM002'!$K:$K,'PLM002'!$C:$C,DO$4,'PLM002'!$F:$F,$B9)=0,"",SUMIFS('PLM002'!$K:$K,'PLM002'!$C:$C,DO$4,'PLM002'!$F:$F,$B9)) | DQ9: =IF(SUMIFS('PLM001-財務計算用'!$P:$P,'PLM001-財務計算用'!$J:$J,DQ$4,'PLM001-財務計算用'!$A:$A,$B9)=0,"",SUMIFS('PLM001-財務計算用'!$P:$P,'PLM001-財務計算用'!$J:$J,DQ$4,'PLM001-財務計算用'!$A:$A,$B9)) | DR9: =IF(SUMIFS('PLM002'!$K:$K,'PLM002'!$C:$C,DQ$4,'PLM002'!$F:$F,$B9)=0,"",SUMIFS('PLM002'!$K:$K,'PLM002'!$C:$C,DQ$4,'PLM002'!$F:$F,$B9)) | DS9: =IF(SUMIFS('PLM001-財務計算用'!$P:$P,'PLM001-財務計算用'!$J:$J,DS$4,'PLM001-財務計算用'!$A:$A,$B9)=0,"",SUMIFS('PLM001-財務計算用'!$P:$P,'PLM001-財務計算用'!$J:$J,DS$4,'PLM001-財務計算用'!$A:$A,$B9)) | DT9: =IF(SUMIFS('PLM002'!$K:$K,'PLM002'!$C:$C,DS$4,'PLM002'!$F:$F,$B9)=0,"",SUMIFS('PLM002'!$K:$K,'PLM002'!$C:$C,DS$4,'PLM002'!$F:$F,$B9)) | DU9: =IF(SUMIFS('PLM001-財務計算用'!$P:$P,'PLM001-財務計算用'!$J:$J,DU$4,'PLM001-財務計算用'!$A:$A,$B9)=0,"",SUMIFS('PLM001-財務計算用'!$P:$P,'PLM001-財務計算用'!$J:$J,DU$4,'PLM001-財務計算用'!$A:$A,$B9)) | DV9: =IF(SUMIFS('PLM002'!$K:$K,'PLM002'!$C:$C,DU$4,'PLM002'!$F:$F,$B9)=0,"",SUMIFS('PLM002'!$K:$K,'PLM002'!$C:$C,DU$4,'PLM002'!$F:$F,$B9)) | DW9: =IF(SUMIFS('PLM001-財務計算用'!$P:$P,'PLM001-財務計算用'!$J:$J,DW$4,'PLM001-財務計算用'!$A:$A,$B9)=0,"",SUMIFS('PLM001-財務計算用'!$P:$P,'PLM001-財務計算用'!$J:$J,DW$4,'PLM001-財務計算用'!$A:$A,$B9)) | DX9: =IF(SUMIFS('PLM002'!$K:$K,'PLM002'!$C:$C,DW$4,'PLM002'!$F:$F,$B9)=0,"",SUMIFS('PLM002'!$K:$K,'PLM002'!$C:$C,DW$4,'PLM002'!$F:$F,$B9)) | DY9: =IF(SUMIFS('PLM001-財務計算用'!$P:$P,'PLM001-財務計算用'!$J:$J,DY$4,'PLM001-財務計算用'!$A:$A,$B9)=0,"",SUMIFS('PLM001-財務計算用'!$P:$P,'PLM001-財務計算用'!$J:$J,DY$4,'PLM001-財務計算用'!$A:$A,$B9)) | DZ9: =IF(SUMIFS('PLM002'!$K:$K,'PLM002'!$C:$C,DY$4,'PLM002'!$F:$F,$B9)=0,"",SUMIFS('PLM002'!$K:$K,'PLM002'!$C:$C,DY$4,'PLM002'!$F:$F,$B9)) | EA9: =IF(SUMIFS('PLM001-財務計算用'!$P:$P,'PLM001-財務計算用'!$J:$J,EA$4,'PLM001-財務計算用'!$A:$A,$B9)=0,"",SUMIFS('PLM001-財務計算用'!$P:$P,'PLM001-財務計算用'!$J:$J,EA$4,'PLM001-財務計算用'!$A:$A,$B9)) | EB9: =IF(SUMIFS('PLM002'!$K:$K,'PLM002'!$C:$C,EA$4,'PLM002'!$F:$F,$B9)=0,"",SUMIFS('PLM002'!$K:$K,'PLM002'!$C:$C,EA$4,'PLM002'!$F:$F,$B9)) | EC9: =IF(SUMIFS('PLM001-財務計算用'!$P:$P,'PLM001-財務計算用'!$J:$J,EC$4,'PLM001-財務計算用'!$A:$A,$B9)=0,"",SUMIFS('PLM001-財務計算用'!$P:$P,'PLM001-財務計算用'!$J:$J,EC$4,'PLM001-財務計算用'!$A:$A,$B9)) | ED9: =IF(SUMIFS('PLM002'!$K:$K,'PLM002'!$C:$C,EC$4,'PLM002'!$F:$F,$B9)=0,"",SUMIFS('PLM002'!$K:$K,'PLM002'!$C:$C,EC$4,'PLM002'!$F:$F,$B9))
A10: ='PLM014'!A11 -> M-養護 | B10: D250702R1 | C10: ='PLM014'!C11 -> 2025年度-硬體模組化專案 | D10: ="("&B10&")"&" "&C10 -> (D250702R1) 2025年度-硬體模組化專案 | E10: ='PLM014'!E11 -> 研二部 | F10: ='PLM014'!F11 -> 黃胤綸 | G10: ='PLM014'!G11 -> Active | H10: ='PLM014'!H11 -> 45657.667 | I10: ='PLM014'!I11 -> 46021.667 | J10: =IF(ISERROR(DATEDIF(H10,I10,"d")),"",DATEDIF(H10,I10,"d")) -> 364 | K10: =H10+(J10*0.75) -> 45930.667 | L10: =H10+(J10*0.95) -> 46003.467 | M10: =IF(ISERROR('PLM014'!L11),"",('PLM014'!L11)) -> 45847 | N10: =IF(IF(ISERROR('PLM014'!N11),"",('PLM014'!N11))=0,"",IF(ISERROR('PLM014'!N11),"",('PLM014'!N11))) | O10: =IF(ISERROR(DATEDIF(M10,N10,"d")),"",IF(DATEDIF(M10,N10,"d")=0,"",DATEDIF(M10,N10,"d"))) | P10: =IF(N10="",TODAY(),N10) -> 46044 | Q10: =IF(ISERROR(DATEDIF(M10,P10,"d")),"",IF(DATEDIF(M10,P10,"d")=0,"",DATEDIF(M10,P10,"d"))) -> 197 | R10: ='PLM014'!Q11/100 -> 0.75 | S10: =IF(AND(TODAY()>I10,R10<>100%,G10="Active"),"專案延遲 "&DATEDIF(I10,TODAY(),"d")&" 天",IF(AND(TODAY()>K10,R10<75%,G10="Active"),"專案即將異常",IF(AND(TODAY()>L10,R10<95%,G10="Active"),"專案即將異常",""))) -> 專案延遲 23 天 | U10: =IF(SUMIF($Y$5:$CV$5,$U$5,Y10:CV10)=0,"未登入",SUMIF($Y$5:$CV$5,$U$5,Y10:CV10)) -> 488 | V10: =SUMIF($Y$5:$CV$5,$V$5,Y10:CV10) -> 589.6 | W10: =IF(SUMIFS('PLM001-財務計算用'!$P:$P,'PLM001-財務計算用'!$A:$A,B10)=0,"未登入",SUMIFS('PLM001-財務計算用'!$P:$P,'PLM001-財務計算用'!$A:$A,B10)) -> 488 | X10: =SUMIFS('PLM002'!$K:$K,'PLM002'!$F:$F,$B10) -> 589.6 | Y10: =IF(SUMIFS('PLM001-財務計算用'!$P:$P,'PLM001-財務計算用'!$J:$J,Y$4,'PLM001-財務計算用'!$A:$A,$B10)=0,"",SUMIFS('PLM001-財務計算用'!$P:$P,'PLM001-財務計算用'!$J:$J,Y$4,'PLM001-財務計算用'!$A:$A,$B10)) | Z10: =IF(SUMIFS('PLM002'!$K:$K,'PLM002'!$C:$C,Y$4,'PLM002'!$F:$F,$B10)=0,"",SUMIFS('PLM002'!$K:$K,'PLM002'!$C:$C,Y$4,'PLM002'!$F:$F,$B10)) | AA10: =IF(SUMIFS('PLM001-財務計算用'!$P:$P,'PLM001-財務計算用'!$J:$J,AA$4,'PLM001-財務計算用'!$A:$A,$B10)=0,"",SUMIFS('PLM001-財務計算用'!$P:$P,'PLM001-財務計算用'!$J:$J,AA$4,'PLM001-財務計算用'!$A:$A,$B10)) | AB10: =IF(SUMIFS('PLM002'!$K:$K,'PLM002'!$C:$C,AA$4,'PLM002'!$F:$F,$B10)=0,"",SUMIFS('PLM002'!$K:$K,'PLM002'!$C:$C,AA$4,'PLM002'!$F:$F,$B10)) | AC10: =IF(SUMIFS('PLM001-財務計算用'!$P:$P,'PLM001-財務計算用'!$J:$J,AC$4,'PLM001-財務計算用'!$A:$A,$B10)=0,"",SUMIFS('PLM001-財務計算用'!$P:$P,'PLM001-財務計算用'!$J:$J,AC$4,'PLM001-財務計算用'!$A:$A,$B10)) | AD10: =IF(SUMIFS('PLM002'!$K:$K,'PLM002'!$C:$C,AC$4,'PLM002'!$F:$F,$B10)=0,"",SUMIFS('PLM002'!$K:$K,'PLM002'!$C:$C,AC$4,'PLM002'!$F:$F,$B10)) | AE10: =IF(SUMIFS('PLM001-財務計算用'!$P:$P,'PLM001-財務計算用'!$J:$J,AE$4,'PLM001-財務計算用'!$A:$A,$B10)=0,"",SUMIFS('PLM001-財務計算用'!$P:$P,'PLM001-財務計算用'!$J:$J,AE$4,'PLM001-財務計算用'!$A:$A,$B10)) -> 40 | AF10: =IF(SUMIFS('PLM002'!$K:$K,'PLM002'!$C:$C,AE$4,'PLM002'!$F:$F,$B10)=0,"",SUMIFS('PLM002'!$K:$K,'PLM002'!$C:$C,AE$4,'PLM002'!$F:$F,$B10)) -> 2 | AG10: =IF(SUMIFS('PLM001-財務計算用'!$P:$P,'PLM001-財務計算用'!$J:$J,AG$4,'PLM001-財務計算用'!$A:$A,$B10)=0,"",SUMIFS('PLM001-財務計算用'!$P:$P,'PLM001-財務計算用'!$J:$J,AG$4,'PLM001-財務計算用'!$A:$A,$B10)) -> 24 | AH10: =IF(SUMIFS('PLM002'!$K:$K,'PLM002'!$C:$C,AG$4,'PLM002'!$F:$F,$B10)=0,"",SUMIFS('PLM002'!$K:$K,'PLM002'!$C:$C,AG$4,'PLM002'!$F:$F,$B10)) -> 189.5 | AI10: =IF(SUMIFS('PLM001-財務計算用'!$P:$P,'PLM001-財務計算用'!$J:$J,AI$4,'PLM001-財務計算用'!$A:$A,$B10)=0,"",SUMIFS('PLM001-財務計算用'!$P:$P,'PLM001-財務計算用'!$J:$J,AI$4,'PLM001-財務計算用'!$A:$A,$B10)) | AJ10: =IF(SUMIFS('PLM002'!$K:$K,'PLM002'!$C:$C,AI$4,'PLM002'!$F:$F,$B10)=0,"",SUMIFS('PLM002'!$K:$K,'PLM002'!$C:$C,AI$4,'PLM002'!$F:$F,$B10)) | AK10: =IF(SUMIFS('PLM001-財務計算用'!$P:$P,'PLM001-財務計算用'!$J:$J,AK$4,'PLM001-財務計算用'!$A:$A,$B10)=0,"",SUMIFS('PLM001-財務計算用'!$P:$P,'PLM001-財務計算用'!$J:$J,AK$4,'PLM001-財務計算用'!$A:$A,$B10)) | AL10: =IF(SUMIFS('PLM002'!$K:$K,'PLM002'!$C:$C,AK$4,'PLM002'!$F:$F,$B10)=0,"",SUMIFS('PLM002'!$K:$K,'PLM002'!$C:$C,AK$4,'PLM002'!$F:$F,$B10)) | AM10: =IF(SUMIFS('PLM001-財務計算用'!$P:$P,'PLM001-財務計算用'!$J:$J,AM$4,'PLM001-財務計算用'!$A:$A,$B10)=0,"",SUMIFS('PLM001-財務計算用'!$P:$P,'PLM001-財務計算用'!$J:$J,AM$4,'PLM001-財務計算用'!$A:$A,$B10)) | AN10: =IF(SUMIFS('PLM002'!$K:$K,'PLM002'!$C:$C,AM$4,'PLM002'!$F:$F,$B10)=0,"",SUMIFS('PLM002'!$K:$K,'PLM002'!$C:$C,AM$4,'PLM002'!$F:$F,$B10)) | AO10: =IF(SUMIFS('PLM001-財務計算用'!$P:$P,'PLM001-財務計算用'!$J:$J,AO$4,'PLM001-財務計算用'!$A:$A,$B10)=0,"",SUMIFS('PLM001-財務計算用'!$P:$P,'PLM001-財務計算用'!$J:$J,AO$4,'PLM001-財務計算用'!$A:$A,$B10)) | AP10: =IF(SUMIFS('PLM002'!$K:$K,'PLM002'!$C:$C,AO$4,'PLM002'!$F:$F,$B10)=0,"",SUMIFS('PLM002'!$K:$K,'PLM002'!$C:$C,AO$4,'PLM002'!$F:$F,$B10)) | AQ10: =IF(SUMIFS('PLM001-財務計算用'!$P:$P,'PLM001-財務計算用'!$J:$J,AQ$4,'PLM001-財務計算用'!$A:$A,$B10)=0,"",SUMIFS('PLM001-財務計算用'!$P:$P,'PLM001-財務計算用'!$J:$J,AQ$4,'PLM001-財務計算用'!$A:$A,$B10)) | AR10: =IF(SUMIFS('PLM002'!$K:$K,'PLM002'!$C:$C,AQ$4,'PLM002'!$F:$F,$B10)=0,"",SUMIFS('PLM002'!$K:$K,'PLM002'!$C:$C,AQ$4,'PLM002'!$F:$F,$B10)) | AS10: =IF(SUMIFS('PLM001-財務計算用'!$P:$P,'PLM001-財務計算用'!$J:$J,AS$4,'PLM001-財務計算用'!$A:$A,$B10)=0,"",SUMIFS('PLM001-財務計算用'!$P:$P,'PLM001-財務計算用'!$J:$J,AS$4,'PLM001-財務計算用'!$A:$A,$B10)) | AT10: =IF(SUMIFS('PLM002'!$K:$K,'PLM002'!$C:$C,AS$4,'PLM002'!$F:$F,$B10)=0,"",SUMIFS('PLM002'!$K:$K,'PLM002'!$C:$C,AS$4,'PLM002'!$F:$F,$B10)) -> 7.6 | AU10: =IF(SUMIFS('PLM001-財務計算用'!$P:$P,'PLM001-財務計算用'!$J:$J,AU$4,'PLM001-財務計算用'!$A:$A,$B10)=0,"",SUMIFS('PLM001-財務計算用'!$P:$P,'PLM001-財務計算用'!$J:$J,AU$4,'PLM001-財務計算用'!$A:$A,$B10)) -> 40 | AV10: =IF(SUMIFS('PLM002'!$K:$K,'PLM002'!$C:$C,AU$4,'PLM002'!$F:$F,$B10)=0,"",SUMIFS('PLM002'!$K:$K,'PLM002'!$C:$C,AU$4,'PLM002'!$F:$F,$B10)) -> 4 | AW10: =IF(SUMIFS('PLM001-財務計算用'!$P:$P,'PLM001-財務計算用'!$J:$J,AW$4,'PLM001-財務計算用'!$A:$A,$B10)=0,"",SUMIFS('PLM001-財務計算用'!$P:$P,'PLM001-財務計算用'!$J:$J,AW$4,'PLM001-財務計算用'!$A:$A,$B10)) -> 40 | AX10: =IF(SUMIFS('PLM002'!$K:$K,'PLM002'!$C:$C,AW$4,'PLM002'!$F:$F,$B10)=0,"",SUMIFS('PLM002'!$K:$K,'PLM002'!$C:$C,AW$4,'PLM002'!$F:$F,$B10)) -> 32 | AY10: =IF(SUMIFS('PLM001-財務計算用'!$P:$P,'PLM001-財務計算用'!$J:$J,AY$4,'PLM001-財務計算用'!$A:$A,$B10)=0,"",SUMIFS('PLM001-財務計算用'!$P:$P,'PLM001-財務計算用'!$J:$J,AY$4,'PLM001-財務計算用'!$A:$A,$B10)) -> 40 | AZ10: =IF(SUMIFS('PLM002'!$K:$K,'PLM002'!$C:$C,AY$4,'PLM002'!$F:$F,$B10)=0,"",SUMIFS('PLM002'!$K:$K,'PLM002'!$C:$C,AY$4,'PLM002'!$F:$F,$B10)) -> 33 | BA10: =IF(SUMIFS('PLM001-財務計算用'!$P:$P,'PLM001-財務計算用'!$J:$J,BA$4,'PLM001-財務計算用'!$A:$A,$B10)=0,"",SUMIFS('PLM001-財務計算用'!$P:$P,'PLM001-財務計算用'!$J:$J,BA$4,'PLM001-財務計算用'!$A:$A,$B10)) | BB10: =IF(SUMIFS('PLM002'!$K:$K,'PLM002'!$C:$C,BA$4,'PLM002'!$F:$F,$B10)=0,"",SUMIFS('PLM002'!$K:$K,'PLM002'!$C:$C,BA$4,'PLM002'!$F:$F,$B10)) | BC10: =IF(SUMIFS('PLM001-財務計算用'!$P:$P,'PLM001-財務計算用'!$J:$J,BC$4,'PLM001-財務計算用'!$A:$A,$B10)=0,"",SUMIFS('PLM001-財務計算用'!$P:$P,'PLM001-財務計算用'!$J:$J,BC$4,'PLM001-財務計算用'!$A:$A,$B10)) | BD10: =IF(SUMIFS('PLM002'!$K:$K,'PLM002'!$C:$C,BC$4,'PLM002'!$F:$F,$B10)=0,"",SUMIFS('PLM002'!$K:$K,'PLM002'!$C:$C,BC$4,'PLM002'!$F:$F,$B10)) -> 34 | BE10: =IF(SUMIFS('PLM001-財務計算用'!$P:$P,'PLM001-財務計算用'!$J:$J,BE$4,'PLM001-財務計算用'!$A:$A,$B10)=0,"",SUMIFS('PLM001-財務計算用'!$P:$P,'PLM001-財務計算用'!$J:$J,BE$4,'PLM001-財務計算用'!$A:$A,$B10)) -> 40 | BF10: =IF(SUMIFS('PLM002'!$K:$K,'PLM002'!$C:$C,BE$4,'PLM002'!$F:$F,$B10)=0,"",SUMIFS('PLM002'!$K:$K,'PLM002'!$C:$C,BE$4,'PLM002'!$F:$F,$B10)) -> 9.5 | BG10: =IF(SUMIFS('PLM001-財務計算用'!$P:$P,'PLM001-財務計算用'!$J:$J,BG$4,'PLM001-財務計算用'!$A:$A,$B10)=0,"",SUMIFS('PLM001-財務計算用'!$P:$P,'PLM001-財務計算用'!$J:$J,BG$4,'PLM001-財務計算用'!$A:$A,$B10)) -> 40 | BH10: =IF(SUMIFS('PLM002'!$K:$K,'PLM002'!$C:$C,BG$4,'PLM002'!$F:$F,$B10)=0,"",SUMIFS('PLM002'!$K:$K,'PLM002'!$C:$C,BG$4,'PLM002'!$F:$F,$B10)) -> 43.5 | BI10: =IF(SUMIFS('PLM001-財務計算用'!$P:$P,'PLM001-財務計算用'!$J:$J,BI$4,'PLM001-財務計算用'!$A:$A,$B10)=0,"",SUMIFS('PLM001-財務計算用'!$P:$P,'PLM001-財務計算用'!$J:$J,BI$4,'PLM001-財務計算用'!$A:$A,$B10)) -> 40 | BJ10: =IF(SUMIFS('PLM002'!$K:$K,'PLM002'!$C:$C,BI$4,'PLM002'!$F:$F,$B10)=0,"",SUMIFS('PLM002'!$K:$K,'PLM002'!$C:$C,BI$4,'PLM002'!$F:$F,$B10)) -> 74 | BK10: =IF(SUMIFS('PLM001-財務計算用'!$P:$P,'PLM001-財務計算用'!$J:$J,BK$4,'PLM001-財務計算用'!$A:$A,$B10)=0,"",SUMIFS('PLM001-財務計算用'!$P:$P,'PLM001-財務計算用'!$J:$J,BK$4,'PLM001-財務計算用'!$A:$A,$B10)) | BL10: =IF(SUMIFS('PLM002'!$K:$K,'PLM002'!$C:$C,BK$4,'PLM002'!$F:$F,$B10)=0,"",SUMIFS('PLM002'!$K:$K,'PLM002'!$C:$C,BK$4,'PLM002'!$F:$F,$B10)) | BM10: =IF(SUMIFS('PLM001-財務計算用'!$P:$P,'PLM001-財務計算用'!$J:$J,BM$4,'PLM001-財務計算用'!$A:$A,$B10)=0,"",SUMIFS('PLM001-財務計算用'!$P:$P,'PLM001-財務計算用'!$J:$J,BM$4,'PLM001-財務計算用'!$A:$A,$B10)) -> 40 | BN10: =IF(SUMIFS('PLM002'!$K:$K,'PLM002'!$C:$C,BM$4,'PLM002'!$F:$F,$B10)=0,"",SUMIFS('PLM002'!$K:$K,'PLM002'!$C:$C,BM$4,'PLM002'!$F:$F,$B10)) -> 57.5 | BO10: =IF(SUMIFS('PLM001-財務計算用'!$P:$P,'PLM001-財務計算用'!$J:$J,BO$4,'PLM001-財務計算用'!$A:$A,$B10)=0,"",SUMIFS('PLM001-財務計算用'!$P:$P,'PLM001-財務計算用'!$J:$J,BO$4,'PLM001-財務計算用'!$A:$A,$B10)) -> 40 | BP10: =IF(SUMIFS('PLM002'!$K:$K,'PLM002'!$C:$C,BO$4,'PLM002'!$F:$F,$B10)=0,"",SUMIFS('PLM002'!$K:$K,'PLM002'!$C:$C,BO$4,'PLM002'!$F:$F,$B10)) -> 16 | BQ10: =IF(SUMIFS('PLM001-財務計算用'!$P:$P,'PLM001-財務計算用'!$J:$J,BQ$4,'PLM001-財務計算用'!$A:$A,$B10)=0,"",SUMIFS('PLM001-財務計算用'!$P:$P,'PLM001-財務計算用'!$J:$J,BQ$4,'PLM001-財務計算用'!$A:$A,$B10)) -> 24 | BR10: =IF(SUMIFS('PLM002'!$K:$K,'PLM002'!$C:$C,BQ$4,'PLM002'!$F:$F,$B10)=0,"",SUMIFS('PLM002'!$K:$K,'PLM002'!$C:$C,BQ$4,'PLM002'!$F:$F,$B10)) -> 48 | BS10: =IF(SUMIFS('PLM001-財務計算用'!$P:$P,'PLM001-財務計算用'!$J:$J,BS$4,'PLM001-財務計算用'!$A:$A,$B10)=0,"",SUMIFS('PLM001-財務計算用'!$P:$P,'PLM001-財務計算用'!$J:$J,BS$4,'PLM001-財務計算用'!$A:$A,$B10)) | BT10: =IF(SUMIFS('PLM002'!$K:$K,'PLM002'!$C:$C,BS$4,'PLM002'!$F:$F,$B10)=0,"",SUMIFS('PLM002'!$K:$K,'PLM002'!$C:$C,BS$4,'PLM002'!$F:$F,$B10)) | BU10: =IF(SUMIFS('PLM001-財務計算用'!$P:$P,'PLM001-財務計算用'!$J:$J,BU$4,'PLM001-財務計算用'!$A:$A,$B10)=0,"",SUMIFS('PLM001-財務計算用'!$P:$P,'PLM001-財務計算用'!$J:$J,BU$4,'PLM001-財務計算用'!$A:$A,$B10)) | BV10: =IF(SUMIFS('PLM002'!$K:$K,'PLM002'!$C:$C,BU$4,'PLM002'!$F:$F,$B10)=0,"",SUMIFS('PLM002'!$K:$K,'PLM002'!$C:$C,BU$4,'PLM002'!$F:$F,$B10)) | BW10: =IF(SUMIFS('PLM001-財務計算用'!$P:$P,'PLM001-財務計算用'!$J:$J,BW$4,'PLM001-財務計算用'!$A:$A,$B10)=0,"",SUMIFS('PLM001-財務計算用'!$P:$P,'PLM001-財務計算用'!$J:$J,BW$4,'PLM001-財務計算用'!$A:$A,$B10)) | BX10: =IF(SUMIFS('PLM002'!$K:$K,'PLM002'!$C:$C,BW$4,'PLM002'!$F:$F,$B10)=0,"",SUMIFS('PLM002'!$K:$K,'PLM002'!$C:$C,BW$4,'PLM002'!$F:$F,$B10)) | BY10: =IF(SUMIFS('PLM001-財務計算用'!$P:$P,'PLM001-財務計算用'!$J:$J,BY$4,'PLM001-財務計算用'!$A:$A,$B10)=0,"",SUMIFS('PLM001-財務計算用'!$P:$P,'PLM001-財務計算用'!$J:$J,BY$4,'PLM001-財務計算用'!$A:$A,$B10)) | BZ10: =IF(SUMIFS('PLM002'!$K:$K,'PLM002'!$C:$C,BY$4,'PLM002'!$F:$F,$B10)=0,"",SUMIFS('PLM002'!$K:$K,'PLM002'!$C:$C,BY$4,'PLM002'!$F:$F,$B10)) | CA10: =IF(SUMIFS('PLM001-財務計算用'!$P:$P,'PLM001-財務計算用'!$J:$J,CA$4,'PLM001-財務計算用'!$A:$A,$B10)=0,"",SUMIFS('PLM001-財務計算用'!$P:$P,'PLM001-財務計算用'!$J:$J,CA$4,'PLM001-財務計算用'!$A:$A,$B10)) | CB10: =IF(SUMIFS('PLM002'!$K:$K,'PLM002'!$C:$C,CA$4,'PLM002'!$F:$F,$B10)=0,"",SUMIFS('PLM002'!$K:$K,'PLM002'!$C:$C,CA$4,'PLM002'!$F:$F,$B10)) | CC10: =IF(SUMIFS('PLM001-財務計算用'!$P:$P,'PLM001-財務計算用'!$J:$J,CC$4,'PLM001-財務計算用'!$A:$A,$B10)=0,"",SUMIFS('PLM001-財務計算用'!$P:$P,'PLM001-財務計算用'!$J:$J,CC$4,'PLM001-財務計算用'!$A:$A,$B10)) | CD10: =IF(SUMIFS('PLM002'!$K:$K,'PLM002'!$C:$C,CC$4,'PLM002'!$F:$F,$B10)=0,"",SUMIFS('PLM002'!$K:$K,'PLM002'!$C:$C,CC$4,'PLM002'!$F:$F,$B10)) | CE10: =IF(SUMIFS('PLM001-財務計算用'!$P:$P,'PLM001-財務計算用'!$J:$J,CE$4,'PLM001-財務計算用'!$A:$A,$B10)=0,"",SUMIFS('PLM001-財務計算用'!$P:$P,'PLM001-財務計算用'!$J:$J,CE$4,'PLM001-財務計算用'!$A:$A,$B10)) | CF10: =IF(SUMIFS('PLM002'!$K:$K,'PLM002'!$C:$C,CE$4,'PLM002'!$F:$F,$B10)=0,"",SUMIFS('PLM002'!$K:$K,'PLM002'!$C:$C,CE$4,'PLM002'!$F:$F,$B10)) | CG10: =IF(SUMIFS('PLM001-財務計算用'!$P:$P,'PLM001-財務計算用'!$J:$J,CG$4,'PLM001-財務計算用'!$A:$A,$B10)=0,"",SUMIFS('PLM001-財務計算用'!$P:$P,'PLM001-財務計算用'!$J:$J,CG$4,'PLM001-財務計算用'!$A:$A,$B10)) | CH10: =IF(SUMIFS('PLM002'!$K:$K,'PLM002'!$C:$C,CG$4,'PLM002'!$F:$F,$B10)=0,"",SUMIFS('PLM002'!$K:$K,'PLM002'!$C:$C,CG$4,'PLM002'!$F:$F,$B10)) | CI10: =IF(SUMIFS('PLM001-財務計算用'!$P:$P,'PLM001-財務計算用'!$J:$J,CI$4,'PLM001-財務計算用'!$A:$A,$B10)=0,"",SUMIFS('PLM001-財務計算用'!$P:$P,'PLM001-財務計算用'!$J:$J,CI$4,'PLM001-財務計算用'!$A:$A,$B10)) | CJ10: =IF(SUMIFS('PLM002'!$K:$K,'PLM002'!$C:$C,CI$4,'PLM002'!$F:$F,$B10)=0,"",SUMIFS('PLM002'!$K:$K,'PLM002'!$C:$C,CI$4,'PLM002'!$F:$F,$B10)) | CK10: =IF(SUMIFS('PLM001-財務計算用'!$P:$P,'PLM001-財務計算用'!$J:$J,CK$4,'PLM001-財務計算用'!$A:$A,$B10)=0,"",SUMIFS('PLM001-財務計算用'!$P:$P,'PLM001-財務計算用'!$J:$J,CK$4,'PLM001-財務計算用'!$A:$A,$B10)) | CL10: =IF(SUMIFS('PLM002'!$K:$K,'PLM002'!$C:$C,CK$4,'PLM002'!$F:$F,$B10)=0,"",SUMIFS('PLM002'!$K:$K,'PLM002'!$C:$C,CK$4,'PLM002'!$F:$F,$B10)) | CM10: =IF(SUMIFS('PLM001-財務計算用'!$P:$P,'PLM001-財務計算用'!$J:$J,CM$4,'PLM001-財務計算用'!$A:$A,$B10)=0,"",SUMIFS('PLM001-財務計算用'!$P:$P,'PLM001-財務計算用'!$J:$J,CM$4,'PLM001-財務計算用'!$A:$A,$B10)) -> 40 | CN10: =IF(SUMIFS('PLM002'!$K:$K,'PLM002'!$C:$C,CM$4,'PLM002'!$F:$F,$B10)=0,"",SUMIFS('PLM002'!$K:$K,'PLM002'!$C:$C,CM$4,'PLM002'!$F:$F,$B10)) | CO10: =IF(SUMIFS('PLM001-財務計算用'!$P:$P,'PLM001-財務計算用'!$J:$J,CO$4,'PLM001-財務計算用'!$A:$A,$B10)=0,"",SUMIFS('PLM001-財務計算用'!$P:$P,'PLM001-財務計算用'!$J:$J,CO$4,'PLM001-財務計算用'!$A:$A,$B10)) -> 40 | CP10: =IF(SUMIFS('PLM002'!$K:$K,'PLM002'!$C:$C,CO$4,'PLM002'!$F:$F,$B10)=0,"",SUMIFS('PLM002'!$K:$K,'PLM002'!$C:$C,CO$4,'PLM002'!$F:$F,$B10)) -> 34 | CQ10: =IF(SUMIFS('PLM001-財務計算用'!$P:$P,'PLM001-財務計算用'!$J:$J,CQ$4,'PLM001-財務計算用'!$A:$A,$B10)=0,"",SUMIFS('PLM001-財務計算用'!$P:$P,'PLM001-財務計算用'!$J:$J,CQ$4,'PLM001-財務計算用'!$A:$A,$B10)) | CR10: =IF(SUMIFS('PLM002'!$K:$K,'PLM002'!$C:$C,CQ$4,'PLM002'!$F:$F,$B10)=0,"",SUMIFS('PLM002'!$K:$K,'PLM002'!$C:$C,CQ$4,'PLM002'!$F:$F,$B10)) -> 5 | CS10: =IF(SUMIFS('PLM001-財務計算用'!$P:$P,'PLM001-財務計算用'!$J:$J,CS$4,'PLM001-財務計算用'!$A:$A,$B10)=0,"",SUMIFS('PLM001-財務計算用'!$P:$P,'PLM001-財務計算用'!$J:$J,CS$4,'PLM001-財務計算用'!$A:$A,$B10)) | CT10: =IF(SUMIFS('PLM002'!$K:$K,'PLM002'!$C:$C,CS$4,'PLM002'!$F:$F,$B10)=0,"",SUMIFS('PLM002'!$K:$K,'PLM002'!$C:$C,CS$4,'PLM002'!$F:$F,$B10)) | CU10: =IF(SUMIFS('PLM001-財務計算用'!$P:$P,'PLM001-財務計算用'!$J:$J,CU$4,'PLM001-財務計算用'!$A:$A,$B10)=0,"",SUMIFS('PLM001-財務計算用'!$P:$P,'PLM001-財務計算用'!$J:$J,CU$4,'PLM001-財務計算用'!$A:$A,$B10)) | CV10: =IF(SUMIFS('PLM002'!$K:$K,'PLM002'!$C:$C,CU$4,'PLM002'!$F:$F,$B10)=0,"",SUMIFS('PLM002'!$K:$K,'PLM002'!$C:$C,CU$4,'PLM002'!$F:$F,$B10)) | CW10: =IF(SUMIFS('PLM001-財務計算用'!$P:$P,'PLM001-財務計算用'!$J:$J,CW$4,'PLM001-財務計算用'!$A:$A,$B10)=0,"",SUMIFS('PLM001-財務計算用'!$P:$P,'PLM001-財務計算用'!$J:$J,CW$4,'PLM001-財務計算用'!$A:$A,$B10)) | CX10: =IF(SUMIFS('PLM002'!$K:$K,'PLM002'!$C:$C,CW$4,'PLM002'!$F:$F,$B10)=0,"",SUMIFS('PLM002'!$K:$K,'PLM002'!$C:$C,CW$4,'PLM002'!$F:$F,$B10)) | CY10: =IF(SUMIFS('PLM001-財務計算用'!$P:$P,'PLM001-財務計算用'!$J:$J,CY$4,'PLM001-財務計算用'!$A:$A,$B10)=0,"",SUMIFS('PLM001-財務計算用'!$P:$P,'PLM001-財務計算用'!$J:$J,CY$4,'PLM001-財務計算用'!$A:$A,$B10)) | CZ10: =IF(SUMIFS('PLM002'!$K:$K,'PLM002'!$C:$C,CY$4,'PLM002'!$F:$F,$B10)=0,"",SUMIFS('PLM002'!$K:$K,'PLM002'!$C:$C,CY$4,'PLM002'!$F:$F,$B10)) | DA10: =IF(SUMIFS('PLM001-財務計算用'!$P:$P,'PLM001-財務計算用'!$J:$J,DA$4,'PLM001-財務計算用'!$A:$A,$B10)=0,"",SUMIFS('PLM001-財務計算用'!$P:$P,'PLM001-財務計算用'!$J:$J,DA$4,'PLM001-財務計算用'!$A:$A,$B10)) | DB10: =IF(SUMIFS('PLM002'!$K:$K,'PLM002'!$C:$C,DA$4,'PLM002'!$F:$F,$B10)=0,"",SUMIFS('PLM002'!$K:$K,'PLM002'!$C:$C,DA$4,'PLM002'!$F:$F,$B10)) | DC10: =IF(SUMIFS('PLM001-財務計算用'!$P:$P,'PLM001-財務計算用'!$J:$J,DC$4,'PLM001-財務計算用'!$A:$A,$B10)=0,"",SUMIFS('PLM001-財務計算用'!$P:$P,'PLM001-財務計算用'!$J:$J,DC$4,'PLM001-財務計算用'!$A:$A,$B10)) | DD10: =IF(SUMIFS('PLM002'!$K:$K,'PLM002'!$C:$C,DC$4,'PLM002'!$F:$F,$B10)=0,"",SUMIFS('PLM002'!$K:$K,'PLM002'!$C:$C,DC$4,'PLM002'!$F:$F,$B10)) | DE10: =IF(SUMIFS('PLM001-財務計算用'!$P:$P,'PLM001-財務計算用'!$J:$J,DE$4,'PLM001-財務計算用'!$A:$A,$B10)=0,"",SUMIFS('PLM001-財務計算用'!$P:$P,'PLM001-財務計算用'!$J:$J,DE$4,'PLM001-財務計算用'!$A:$A,$B10)) | DF10: =IF(SUMIFS('PLM002'!$K:$K,'PLM002'!$C:$C,DE$4,'PLM002'!$F:$F,$B10)=0,"",SUMIFS('PLM002'!$K:$K,'PLM002'!$C:$C,DE$4,'PLM002'!$F:$F,$B10)) | DG10: =IF(SUMIFS('PLM001-財務計算用'!$P:$P,'PLM001-財務計算用'!$J:$J,DG$4,'PLM001-財務計算用'!$A:$A,$B10)=0,"",SUMIFS('PLM001-財務計算用'!$P:$P,'PLM001-財務計算用'!$J:$J,DG$4,'PLM001-財務計算用'!$A:$A,$B10)) | DH10: =IF(SUMIFS('PLM002'!$K:$K,'PLM002'!$C:$C,DG$4,'PLM002'!$F:$F,$B10)=0,"",SUMIFS('PLM002'!$K:$K,'PLM002'!$C:$C,DG$4,'PLM002'!$F:$F,$B10)) | DI10: =IF(SUMIFS('PLM001-財務計算用'!$P:$P,'PLM001-財務計算用'!$J:$J,DI$4,'PLM001-財務計算用'!$A:$A,$B10)=0,"",SUMIFS('PLM001-財務計算用'!$P:$P,'PLM001-財務計算用'!$J:$J,DI$4,'PLM001-財務計算用'!$A:$A,$B10)) | DJ10: =IF(SUMIFS('PLM002'!$K:$K,'PLM002'!$C:$C,DI$4,'PLM002'!$F:$F,$B10)=0,"",SUMIFS('PLM002'!$K:$K,'PLM002'!$C:$C,DI$4,'PLM002'!$F:$F,$B10)) | DK10: =IF(SUMIFS('PLM001-財務計算用'!$P:$P,'PLM001-財務計算用'!$J:$J,DK$4,'PLM001-財務計算用'!$A:$A,$B10)=0,"",SUMIFS('PLM001-財務計算用'!$P:$P,'PLM001-財務計算用'!$J:$J,DK$4,'PLM001-財務計算用'!$A:$A,$B10)) | DL10: =IF(SUMIFS('PLM002'!$K:$K,'PLM002'!$C:$C,DK$4,'PLM002'!$F:$F,$B10)=0,"",SUMIFS('PLM002'!$K:$K,'PLM002'!$C:$C,DK$4,'PLM002'!$F:$F,$B10)) | DM10: =IF(SUMIFS('PLM001-財務計算用'!$P:$P,'PLM001-財務計算用'!$J:$J,DM$4,'PLM001-財務計算用'!$A:$A,$B10)=0,"",SUMIFS('PLM001-財務計算用'!$P:$P,'PLM001-財務計算用'!$J:$J,DM$4,'PLM001-財務計算用'!$A:$A,$B10)) | DN10: =IF(SUMIFS('PLM002'!$K:$K,'PLM002'!$C:$C,DM$4,'PLM002'!$F:$F,$B10)=0,"",SUMIFS('PLM002'!$K:$K,'PLM002'!$C:$C,DM$4,'PLM002'!$F:$F,$B10)) | DO10: =IF(SUMIFS('PLM001-財務計算用'!$P:$P,'PLM001-財務計算用'!$J:$J,DO$4,'PLM001-財務計算用'!$A:$A,$B10)=0,"",SUMIFS('PLM001-財務計算用'!$P:$P,'PLM001-財務計算用'!$J:$J,DO$4,'PLM001-財務計算用'!$A:$A,$B10)) | DP10: =IF(SUMIFS('PLM002'!$K:$K,'PLM002'!$C:$C,DO$4,'PLM002'!$F:$F,$B10)=0,"",SUMIFS('PLM002'!$K:$K,'PLM002'!$C:$C,DO$4,'PLM002'!$F:$F,$B10)) | DQ10: =IF(SUMIFS('PLM001-財務計算用'!$P:$P,'PLM001-財務計算用'!$J:$J,DQ$4,'PLM001-財務計算用'!$A:$A,$B10)=0,"",SUMIFS('PLM001-財務計算用'!$P:$P,'PLM001-財務計算用'!$J:$J,DQ$4,'PLM001-財務計算用'!$A:$A,$B10)) | DR10: =IF(SUMIFS('PLM002'!$K:$K,'PLM002'!$C:$C,DQ$4,'PLM002'!$F:$F,$B10)=0,"",SUMIFS('PLM002'!$K:$K,'PLM002'!$C:$C,DQ$4,'PLM002'!$F:$F,$B10)) | DS10: =IF(SUMIFS('PLM001-財務計算用'!$P:$P,'PLM001-財務計算用'!$J:$J,DS$4,'PLM001-財務計算用'!$A:$A,$B10)=0,"",SUMIFS('PLM001-財務計算用'!$P:$P,'PLM001-財務計算用'!$J:$J,DS$4,'PLM001-財務計算用'!$A:$A,$B10)) | DT10: =IF(SUMIFS('PLM002'!$K:$K,'PLM002'!$C:$C,DS$4,'PLM002'!$F:$F,$B10)=0,"",SUMIFS('PLM002'!$K:$K,'PLM002'!$C:$C,DS$4,'PLM002'!$F:$F,$B10)) | DU10: =IF(SUMIFS('PLM001-財務計算用'!$P:$P,'PLM001-財務計算用'!$J:$J,DU$4,'PLM001-財務計算用'!$A:$A,$B10)=0,"",SUMIFS('PLM001-財務計算用'!$P:$P,'PLM001-財務計算用'!$J:$J,DU$4,'PLM001-財務計算用'!$A:$A,$B10)) | DV10: =IF(SUMIFS('PLM002'!$K:$K,'PLM002'!$C:$C,DU$4,'PLM002'!$F:$F,$B10)=0,"",SUMIFS('PLM002'!$K:$K,'PLM002'!$C:$C,DU$4,'PLM002'!$F:$F,$B10)) | DW10: =IF(SUMIFS('PLM001-財務計算用'!$P:$P,'PLM001-財務計算用'!$J:$J,DW$4,'PLM001-財務計算用'!$A:$A,$B10)=0,"",SUMIFS('PLM001-財務計算用'!$P:$P,'PLM001-財務計算用'!$J:$J,DW$4,'PLM001-財務計算用'!$A:$A,$B10)) | DX10: =IF(SUMIFS('PLM002'!$K:$K,'PLM002'!$C:$C,DW$4,'PLM002'!$F:$F,$B10)=0,"",SUMIFS('PLM002'!$K:$K,'PLM002'!$C:$C,DW$4,'PLM002'!$F:$F,$B10)) | DY10: =IF(SUMIFS('PLM001-財務計算用'!$P:$P,'PLM001-財務計算用'!$J:$J,DY$4,'PLM001-財務計算用'!$A:$A,$B10)=0,"",SUMIFS('PLM001-財務計算用'!$P:$P,'PLM001-財務計算用'!$J:$J,DY$4,'PLM001-財務計算用'!$A:$A,$B10)) | DZ10: =IF(SUMIFS('PLM002'!$K:$K,'PLM002'!$C:$C,DY$4,'PLM002'!$F:$F,$B10)=0,"",SUMIFS('PLM002'!$K:$K,'PLM002'!$C:$C,DY$4,'PLM002'!$F:$F,$B10)) | EA10: =IF(SUMIFS('PLM001-財務計算用'!$P:$P,'PLM001-財務計算用'!$J:$J,EA$4,'PLM001-財務計算用'!$A:$A,$B10)=0,"",SUMIFS('PLM001-財務計算用'!$P:$P,'PLM001-財務計算用'!$J:$J,EA$4,'PLM001-財務計算用'!$A:$A,$B10)) | EB10: =IF(SUMIFS('PLM002'!$K:$K,'PLM002'!$C:$C,EA$4,'PLM002'!$F:$F,$B10)=0,"",SUMIFS('PLM002'!$K:$K,'PLM002'!$C:$C,EA$4,'PLM002'!$F:$F,$B10)) | EC10: =IF(SUMIFS('PLM001-財務計算用'!$P:$P,'PLM001-財務計算用'!$J:$J,EC$4,'PLM001-財務計算用'!$A:$A,$B10)=0,"",SUMIFS('PLM001-財務計算用'!$P:$P,'PLM001-財務計算用'!$J:$J,EC$4,'PLM001-財務計算用'!$A:$A,$B10)) | ED10: =IF(SUMIFS('PLM002'!$K:$K,'PLM002'!$C:$C,EC$4,'PLM002'!$F:$F,$B10)=0,"",SUMIFS('PLM002'!$K:$K,'PLM002'!$C:$C,EC$4,'PLM002'!$F:$F,$B10))
A11: ='PLM014'!A12 -> D-協同 | B11: D250703R1 | C11: ='PLM014'!C12 -> EPH連板電測治具 | D11: ="("&B11&")"&" "&C11 -> (D250703R1) EPH連板電測治具 | E11: ='PLM014'!E12 -> 研發一處 | F11: ='PLM014'!F12 -> 賴慶樺 | G11: ='PLM014'!G12 -> Active | H11: ='PLM014'!H12 -> 45862.667 | I11: ='PLM014'!I12 -> 46051.667 | J11: =IF(ISERROR(DATEDIF(H11,I11,"d")),"",DATEDIF(H11,I11,"d")) -> 189 | K11: =H11+(J11*0.75) -> 46004.417 | L11: =H11+(J11*0.95) -> 46042.217 | M11: =IF(ISERROR('PLM014'!L12),"",('PLM014'!L12)) -> 45866 | N11: =IF(IF(ISERROR('PLM014'!N12),"",('PLM014'!N12))=0,"",IF(ISERROR('PLM014'!N12),"",('PLM014'!N12))) | O11: =IF(ISERROR(DATEDIF(M11,N11,"d")),"",IF(DATEDIF(M11,N11,"d")=0,"",DATEDIF(M11,N11,"d"))) | P11: =IF(N11="",TODAY(),N11) -> 46044 | Q11: =IF(ISERROR(DATEDIF(M11,P11,"d")),"",IF(DATEDIF(M11,P11,"d")=0,"",DATEDIF(M11,P11,"d"))) -> 178 | R11: ='PLM014'!Q12/100 -> 0.58 | S11: =IF(AND(TODAY()>I11,R11<>100%,G11="Active"),"專案延遲 "&DATEDIF(I11,TODAY(),"d")&" 天",IF(AND(TODAY()>K11,R11<75%,G11="Active"),"專案即將異常",IF(AND(TODAY()>L11,R11<95%,G11="Active"),"專案即將異常",""))) -> 專案即將異常 | U11: =IF(SUMIF($Y$5:$CV$5,$U$5,Y11:CV11)=0,"未登入",SUMIF($Y$5:$CV$5,$U$5,Y11:CV11)) -> 未登入 | V11: =SUMIF($Y$5:$CV$5,$V$5,Y11:CV11) -> 76 | W11: =IF(SUMIFS('PLM001-財務計算用'!$P:$P,'PLM001-財務計算用'!$A:$A,B11)=0,"未登入",SUMIFS('PLM001-財務計算用'!$P:$P,'PLM001-財務計算用'!$A:$A,B11)) -> 未登入 | X11: =SUMIFS('PLM002'!$K:$K,'PLM002'!$F:$F,$B11) -> 76 | Y11: =IF(SUMIFS('PLM001-財務計算用'!$P:$P,'PLM001-財務計算用'!$J:$J,Y$4,'PLM001-財務計算用'!$A:$A,$B11)=0,"",SUMIFS('PLM001-財務計算用'!$P:$P,'PLM001-財務計算用'!$J:$J,Y$4,'PLM001-財務計算用'!$A:$A,$B11)) | Z11: =IF(SUMIFS('PLM002'!$K:$K,'PLM002'!$C:$C,Y$4,'PLM002'!$F:$F,$B11)=0,"",SUMIFS('PLM002'!$K:$K,'PLM002'!$C:$C,Y$4,'PLM002'!$F:$F,$B11)) | AA11: =IF(SUMIFS('PLM001-財務計算用'!$P:$P,'PLM001-財務計算用'!$J:$J,AA$4,'PLM001-財務計算用'!$A:$A,$B11)=0,"",SUMIFS('PLM001-財務計算用'!$P:$P,'PLM001-財務計算用'!$J:$J,AA$4,'PLM001-財務計算用'!$A:$A,$B11)) | AB11: =IF(SUMIFS('PLM002'!$K:$K,'PLM002'!$C:$C,AA$4,'PLM002'!$F:$F,$B11)=0,"",SUMIFS('PLM002'!$K:$K,'PLM002'!$C:$C,AA$4,'PLM002'!$F:$F,$B11)) | AC11: =IF(SUMIFS('PLM001-財務計算用'!$P:$P,'PLM001-財務計算用'!$J:$J,AC$4,'PLM001-財務計算用'!$A:$A,$B11)=0,"",SUMIFS('PLM001-財務計算用'!$P:$P,'PLM001-財務計算用'!$J:$J,AC$4,'PLM001-財務計算用'!$A:$A,$B11)) | AD11: =IF(SUMIFS('PLM002'!$K:$K,'PLM002'!$C:$C,AC$4,'PLM002'!$F:$F,$B11)=0,"",SUMIFS('PLM002'!$K:$K,'PLM002'!$C:$C,AC$4,'PLM002'!$F:$F,$B11)) | AE11: =IF(SUMIFS('PLM001-財務計算用'!$P:$P,'PLM001-財務計算用'!$J:$J,AE$4,'PLM001-財務計算用'!$A:$A,$B11)=0,"",SUMIFS('PLM001-財務計算用'!$P:$P,'PLM001-財務計算用'!$J:$J,AE$4,'PLM001-財務計算用'!$A:$A,$B11)) | AF11: =IF(SUMIFS('PLM002'!$K:$K,'PLM002'!$C:$C,AE$4,'PLM002'!$F:$F,$B11)=0,"",SUMIFS('PLM002'!$K:$K,'PLM002'!$C:$C,AE$4,'PLM002'!$F:$F,$B11)) -> 76 | AG11: =IF(SUMIFS('PLM001-財務計算用'!$P:$P,'PLM001-財務計算用'!$J:$J,AG$4,'PLM001-財務計算用'!$A:$A,$B11)=0,"",SUMIFS('PLM001-財務計算用'!$P:$P,'PLM001-財務計算用'!$J:$J,AG$4,'PLM001-財務計算用'!$A:$A,$B11)) | AH11: =IF(SUMIFS('PLM002'!$K:$K,'PLM002'!$C:$C,AG$4,'PLM002'!$F:$F,$B11)=0,"",SUMIFS('PLM002'!$K:$K,'PLM002'!$C:$C,AG$4,'PLM002'!$F:$F,$B11)) | AI11: =IF(SUMIFS('PLM001-財務計算用'!$P:$P,'PLM001-財務計算用'!$J:$J,AI$4,'PLM001-財務計算用'!$A:$A,$B11)=0,"",SUMIFS('PLM001-財務計算用'!$P:$P,'PLM001-財務計算用'!$J:$J,AI$4,'PLM001-財務計算用'!$A:$A,$B11)) | AJ11: =IF(SUMIFS('PLM002'!$K:$K,'PLM002'!$C:$C,AI$4,'PLM002'!$F:$F,$B11)=0,"",SUMIFS('PLM002'!$K:$K,'PLM002'!$C:$C,AI$4,'PLM002'!$F:$F,$B11)) | AK11: =IF(SUMIFS('PLM001-財務計算用'!$P:$P,'PLM001-財務計算用'!$J:$J,AK$4,'PLM001-財務計算用'!$A:$A,$B11)=0,"",SUMIFS('PLM001-財務計算用'!$P:$P,'PLM001-財務計算用'!$J:$J,AK$4,'PLM001-財務計算用'!$A:$A,$B11)) | AL11: =IF(SUMIFS('PLM002'!$K:$K,'PLM002'!$C:$C,AK$4,'PLM002'!$F:$F,$B11)=0,"",SUMIFS('PLM002'!$K:$K,'PLM002'!$C:$C,AK$4,'PLM002'!$F:$F,$B11)) | AM11: =IF(SUMIFS('PLM001-財務計算用'!$P:$P,'PLM001-財務計算用'!$J:$J,AM$4,'PLM001-財務計算用'!$A:$A,$B11)=0,"",SUMIFS('PLM001-財務計算用'!$P:$P,'PLM001-財務計算用'!$J:$J,AM$4,'PLM001-財務計算用'!$A:$A,$B11)) | AN11: =IF(SUMIFS('PLM002'!$K:$K,'PLM002'!$C:$C,AM$4,'PLM002'!$F:$F,$B11)=0,"",SUMIFS('PLM002'!$K:$K,'PLM002'!$C:$C,AM$4,'PLM002'!$F:$F,$B11)) | AO11: =IF(SUMIFS('PLM001-財務計算用'!$P:$P,'PLM001-財務計算用'!$J:$J,AO$4,'PLM001-財務計算用'!$A:$A,$B11)=0,"",SUMIFS('PLM001-財務計算用'!$P:$P,'PLM001-財務計算用'!$J:$J,AO$4,'PLM001-財務計算用'!$A:$A,$B11)) | AP11: =IF(SUMIFS('PLM002'!$K:$K,'PLM002'!$C:$C,AO$4,'PLM002'!$F:$F,$B11)=0,"",SUMIFS('PLM002'!$K:$K,'PLM002'!$C:$C,AO$4,'PLM002'!$F:$F,$B11)) | AQ11: =IF(SUMIFS('PLM001-財務計算用'!$P:$P,'PLM001-財務計算用'!$J:$J,AQ$4,'PLM001-財務計算用'!$A:$A,$B11)=0,"",SUMIFS('PLM001-財務計算用'!$P:$P,'PLM001-財務計算用'!$J:$J,AQ$4,'PLM001-財務計算用'!$A:$A,$B11)) | AR11: =IF(SUMIFS('PLM002'!$K:$K,'PLM002'!$C:$C,AQ$4,'PLM002'!$F:$F,$B11)=0,"",SUMIFS('PLM002'!$K:$K,'PLM002'!$C:$C,AQ$4,'PLM002'!$F:$F,$B11)) | AS11: =IF(SUMIFS('PLM001-財務計算用'!$P:$P,'PLM001-財務計算用'!$J:$J,AS$4,'PLM001-財務計算用'!$A:$A,$B11)=0,"",SUMIFS('PLM001-財務計算用'!$P:$P,'PLM001-財務計算用'!$J:$J,AS$4,'PLM001-財務計算用'!$A:$A,$B11)) | AT11: =IF(SUMIFS('PLM002'!$K:$K,'PLM002'!$C:$C,AS$4,'PLM002'!$F:$F,$B11)=0,"",SUMIFS('PLM002'!$K:$K,'PLM002'!$C:$C,AS$4,'PLM002'!$F:$F,$B11)) | AU11: =IF(SUMIFS('PLM001-財務計算用'!$P:$P,'PLM001-財務計算用'!$J:$J,AU$4,'PLM001-財務計算用'!$A:$A,$B11)=0,"",SUMIFS('PLM001-財務計算用'!$P:$P,'PLM001-財務計算用'!$J:$J,AU$4,'PLM001-財務計算用'!$A:$A,$B11)) | AV11: =IF(SUMIFS('PLM002'!$K:$K,'PLM002'!$C:$C,AU$4,'PLM002'!$F:$F,$B11)=0,"",SUMIFS('PLM002'!$K:$K,'PLM002'!$C:$C,AU$4,'PLM002'!$F:$F,$B11)) | AW11: =IF(SUMIFS('PLM001-財務計算用'!$P:$P,'PLM001-財務計算用'!$J:$J,AW$4,'PLM001-財務計算用'!$A:$A,$B11)=0,"",SUMIFS('PLM001-財務計算用'!$P:$P,'PLM001-財務計算用'!$J:$J,AW$4,'PLM001-財務計算用'!$A:$A,$B11)) | AX11: =IF(SUMIFS('PLM002'!$K:$K,'PLM002'!$C:$C,AW$4,'PLM002'!$F:$F,$B11)=0,"",SUMIFS('PLM002'!$K:$K,'PLM002'!$C:$C,AW$4,'PLM002'!$F:$F,$B11)) | AY11: =IF(SUMIFS('PLM001-財務計算用'!$P:$P,'PLM001-財務計算用'!$J:$J,AY$4,'PLM001-財務計算用'!$A:$A,$B11)=0,"",SUMIFS('PLM001-財務計算用'!$P:$P,'PLM001-財務計算用'!$J:$J,AY$4,'PLM001-財務計算用'!$A:$A,$B11)) | AZ11: =IF(SUMIFS('PLM002'!$K:$K,'PLM002'!$C:$C,AY$4,'PLM002'!$F:$F,$B11)=0,"",SUMIFS('PLM002'!$K:$K,'PLM002'!$C:$C,AY$4,'PLM002'!$F:$F,$B11)) | BA11: =IF(SUMIFS('PLM001-財務計算用'!$P:$P,'PLM001-財務計算用'!$J:$J,BA$4,'PLM001-財務計算用'!$A:$A,$B11)=0,"",SUMIFS('PLM001-財務計算用'!$P:$P,'PLM001-財務計算用'!$J:$J,BA$4,'PLM001-財務計算用'!$A:$A,$B11)) | BB11: =IF(SUMIFS('PLM002'!$K:$K,'PLM002'!$C:$C,BA$4,'PLM002'!$F:$F,$B11)=0,"",SUMIFS('PLM002'!$K:$K,'PLM002'!$C:$C,BA$4,'PLM002'!$F:$F,$B11)) | BC11: =IF(SUMIFS('PLM001-財務計算用'!$P:$P,'PLM001-財務計算用'!$J:$J,BC$4,'PLM001-財務計算用'!$A:$A,$B11)=0,"",SUMIFS('PLM001-財務計算用'!$P:$P,'PLM001-財務計算用'!$J:$J,BC$4,'PLM001-財務計算用'!$A:$A,$B11)) | BD11: =IF(SUMIFS('PLM002'!$K:$K,'PLM002'!$C:$C,BC$4,'PLM002'!$F:$F,$B11)=0,"",SUMIFS('PLM002'!$K:$K,'PLM002'!$C:$C,BC$4,'PLM002'!$F:$F,$B11)) | BE11: =IF(SUMIFS('PLM001-財務計算用'!$P:$P,'PLM001-財務計算用'!$J:$J,BE$4,'PLM001-財務計算用'!$A:$A,$B11)=0,"",SUMIFS('PLM001-財務計算用'!$P:$P,'PLM001-財務計算用'!$J:$J,BE$4,'PLM001-財務計算用'!$A:$A,$B11)) | BF11: =IF(SUMIFS('PLM002'!$K:$K,'PLM002'!$C:$C,BE$4,'PLM002'!$F:$F,$B11)=0,"",SUMIFS('PLM002'!$K:$K,'PLM002'!$C:$C,BE$4,'PLM002'!$F:$F,$B11)) | BG11: =IF(SUMIFS('PLM001-財務計算用'!$P:$P,'PLM001-財務計算用'!$J:$J,BG$4,'PLM001-財務計算用'!$A:$A,$B11)=0,"",SUMIFS('PLM001-財務計算用'!$P:$P,'PLM001-財務計算用'!$J:$J,BG$4,'PLM001-財務計算用'!$A:$A,$B11)) | BH11: =IF(SUMIFS('PLM002'!$K:$K,'PLM002'!$C:$C,BG$4,'PLM002'!$F:$F,$B11)=0,"",SUMIFS('PLM002'!$K:$K,'PLM002'!$C:$C,BG$4,'PLM002'!$F:$F,$B11)) | BI11: =IF(SUMIFS('PLM001-財務計算用'!$P:$P,'PLM001-財務計算用'!$J:$J,BI$4,'PLM001-財務計算用'!$A:$A,$B11)=0,"",SUMIFS('PLM001-財務計算用'!$P:$P,'PLM001-財務計算用'!$J:$J,BI$4,'PLM001-財務計算用'!$A:$A,$B11)) | BJ11: =IF(SUMIFS('PLM002'!$K:$K,'PLM002'!$C:$C,BI$4,'PLM002'!$F:$F,$B11)=0,"",SUMIFS('PLM002'!$K:$K,'PLM002'!$C:$C,BI$4,'PLM002'!$F:$F,$B11)) | BK11: =IF(SUMIFS('PLM001-財務計算用'!$P:$P,'PLM001-財務計算用'!$J:$J,BK$4,'PLM001-財務計算用'!$A:$A,$B11)=0,"",SUMIFS('PLM001-財務計算用'!$P:$P,'PLM001-財務計算用'!$J:$J,BK$4,'PLM001-財務計算用'!$A:$A,$B11)) | BL11: =IF(SUMIFS('PLM002'!$K:$K,'PLM002'!$C:$C,BK$4,'PLM002'!$F:$F,$B11)=0,"",SUMIFS('PLM002'!$K:$K,'PLM002'!$C:$C,BK$4,'PLM002'!$F:$F,$B11)) | BM11: =IF(SUMIFS('PLM001-財務計算用'!$P:$P,'PLM001-財務計算用'!$J:$J,BM$4,'PLM001-財務計算用'!$A:$A,$B11)=0,"",SUMIFS('PLM001-財務計算用'!$P:$P,'PLM001-財務計算用'!$J:$J,BM$4,'PLM001-財務計算用'!$A:$A,$B11)) | BN11: =IF(SUMIFS('PLM002'!$K:$K,'PLM002'!$C:$C,BM$4,'PLM002'!$F:$F,$B11)=0,"",SUMIFS('PLM002'!$K:$K,'PLM002'!$C:$C,BM$4,'PLM002'!$F:$F,$B11)) | BO11: =IF(SUMIFS('PLM001-財務計算用'!$P:$P,'PLM001-財務計算用'!$J:$J,BO$4,'PLM001-財務計算用'!$A:$A,$B11)=0,"",SUMIFS('PLM001-財務計算用'!$P:$P,'PLM001-財務計算用'!$J:$J,BO$4,'PLM001-財務計算用'!$A:$A,$B11)) | BP11: =IF(SUMIFS('PLM002'!$K:$K,'PLM002'!$C:$C,BO$4,'PLM002'!$F:$F,$B11)=0,"",SUMIFS('PLM002'!$K:$K,'PLM002'!$C:$C,BO$4,'PLM002'!$F:$F,$B11)) | BQ11: =IF(SUMIFS('PLM001-財務計算用'!$P:$P,'PLM001-財務計算用'!$J:$J,BQ$4,'PLM001-財務計算用'!$A:$A,$B11)=0,"",SUMIFS('PLM001-財務計算用'!$P:$P,'PLM001-財務計算用'!$J:$J,BQ$4,'PLM001-財務計算用'!$A:$A,$B11)) | BR11: =IF(SUMIFS('PLM002'!$K:$K,'PLM002'!$C:$C,BQ$4,'PLM002'!$F:$F,$B11)=0,"",SUMIFS('PLM002'!$K:$K,'PLM002'!$C:$C,BQ$4,'PLM002'!$F:$F,$B11)) | BS11: =IF(SUMIFS('PLM001-財務計算用'!$P:$P,'PLM001-財務計算用'!$J:$J,BS$4,'PLM001-財務計算用'!$A:$A,$B11)=0,"",SUMIFS('PLM001-財務計算用'!$P:$P,'PLM001-財務計算用'!$J:$J,BS$4,'PLM001-財務計算用'!$A:$A,$B11)) | BT11: =IF(SUMIFS('PLM002'!$K:$K,'PLM002'!$C:$C,BS$4,'PLM002'!$F:$F,$B11)=0,"",SUMIFS('PLM002'!$K:$K,'PLM002'!$C:$C,BS$4,'PLM002'!$F:$F,$B11)) | BU11: =IF(SUMIFS('PLM001-財務計算用'!$P:$P,'PLM001-財務計算用'!$J:$J,BU$4,'PLM001-財務計算用'!$A:$A,$B11)=0,"",SUMIFS('PLM001-財務計算用'!$P:$P,'PLM001-財務計算用'!$J:$J,BU$4,'PLM001-財務計算用'!$A:$A,$B11)) | BV11: =IF(SUMIFS('PLM002'!$K:$K,'PLM002'!$C:$C,BU$4,'PLM002'!$F:$F,$B11)=0,"",SUMIFS('PLM002'!$K:$K,'PLM002'!$C:$C,BU$4,'PLM002'!$F:$F,$B11)) | BW11: =IF(SUMIFS('PLM001-財務計算用'!$P:$P,'PLM001-財務計算用'!$J:$J,BW$4,'PLM001-財務計算用'!$A:$A,$B11)=0,"",SUMIFS('PLM001-財務計算用'!$P:$P,'PLM001-財務計算用'!$J:$J,BW$4,'PLM001-財務計算用'!$A:$A,$B11)) | BX11: =IF(SUMIFS('PLM002'!$K:$K,'PLM002'!$C:$C,BW$4,'PLM002'!$F:$F,$B11)=0,"",SUMIFS('PLM002'!$K:$K,'PLM002'!$C:$C,BW$4,'PLM002'!$F:$F,$B11)) | BY11: =IF(SUMIFS('PLM001-財務計算用'!$P:$P,'PLM001-財務計算用'!$J:$J,BY$4,'PLM001-財務計算用'!$A:$A,$B11)=0,"",SUMIFS('PLM001-財務計算用'!$P:$P,'PLM001-財務計算用'!$J:$J,BY$4,'PLM001-財務計算用'!$A:$A,$B11)) | BZ11: =IF(SUMIFS('PLM002'!$K:$K,'PLM002'!$C:$C,BY$4,'PLM002'!$F:$F,$B11)=0,"",SUMIFS('PLM002'!$K:$K,'PLM002'!$C:$C,BY$4,'PLM002'!$F:$F,$B11)) | CA11: =IF(SUMIFS('PLM001-財務計算用'!$P:$P,'PLM001-財務計算用'!$J:$J,CA$4,'PLM001-財務計算用'!$A:$A,$B11)=0,"",SUMIFS('PLM001-財務計算用'!$P:$P,'PLM001-財務計算用'!$J:$J,CA$4,'PLM001-財務計算用'!$A:$A,$B11)) | CB11: =IF(SUMIFS('PLM002'!$K:$K,'PLM002'!$C:$C,CA$4,'PLM002'!$F:$F,$B11)=0,"",SUMIFS('PLM002'!$K:$K,'PLM002'!$C:$C,CA$4,'PLM002'!$F:$F,$B11)) | CC11: =IF(SUMIFS('PLM001-財務計算用'!$P:$P,'PLM001-財務計算用'!$J:$J,CC$4,'PLM001-財務計算用'!$A:$A,$B11)=0,"",SUMIFS('PLM001-財務計算用'!$P:$P,'PLM001-財務計算用'!$J:$J,CC$4,'PLM001-財務計算用'!$A:$A,$B11)) | CD11: =IF(SUMIFS('PLM002'!$K:$K,'PLM002'!$C:$C,CC$4,'PLM002'!$F:$F,$B11)=0,"",SUMIFS('PLM002'!$K:$K,'PLM002'!$C:$C,CC$4,'PLM002'!$F:$F,$B11)) | CE11: =IF(SUMIFS('PLM001-財務計算用'!$P:$P,'PLM001-財務計算用'!$J:$J,CE$4,'PLM001-財務計算用'!$A:$A,$B11)=0,"",SUMIFS('PLM001-財務計算用'!$P:$P,'PLM001-財務計算用'!$J:$J,CE$4,'PLM001-財務計算用'!$A:$A,$B11)) | CF11: =IF(SUMIFS('PLM002'!$K:$K,'PLM002'!$C:$C,CE$4,'PLM002'!$F:$F,$B11)=0,"",SUMIFS('PLM002'!$K:$K,'PLM002'!$C:$C,CE$4,'PLM002'!$F:$F,$B11)) | CG11: =IF(SUMIFS('PLM001-財務計算用'!$P:$P,'PLM001-財務計算用'!$J:$J,CG$4,'PLM001-財務計算用'!$A:$A,$B11)=0,"",SUMIFS('PLM001-財務計算用'!$P:$P,'PLM001-財務計算用'!$J:$J,CG$4,'PLM001-財務計算用'!$A:$A,$B11)) | CH11: =IF(SUMIFS('PLM002'!$K:$K,'PLM002'!$C:$C,CG$4,'PLM002'!$F:$F,$B11)=0,"",SUMIFS('PLM002'!$K:$K,'PLM002'!$C:$C,CG$4,'PLM002'!$F:$F,$B11)) | CI11: =IF(SUMIFS('PLM001-財務計算用'!$P:$P,'PLM001-財務計算用'!$J:$J,CI$4,'PLM001-財務計算用'!$A:$A,$B11)=0,"",SUMIFS('PLM001-財務計算用'!$P:$P,'PLM001-財務計算用'!$J:$J,CI$4,'PLM001-財務計算用'!$A:$A,$B11)) | CJ11: =IF(SUMIFS('PLM002'!$K:$K,'PLM002'!$C:$C,CI$4,'PLM002'!$F:$F,$B11)=0,"",SUMIFS('PLM002'!$K:$K,'PLM002'!$C:$C,CI$4,'PLM002'!$F:$F,$B11)) | CK11: =IF(SUMIFS('PLM001-財務計算用'!$P:$P,'PLM001-財務計算用'!$J:$J,CK$4,'PLM001-財務計算用'!$A:$A,$B11)=0,"",SUMIFS('PLM001-財務計算用'!$P:$P,'PLM001-財務計算用'!$J:$J,CK$4,'PLM001-財務計算用'!$A:$A,$B11)) | CL11: =IF(SUMIFS('PLM002'!$K:$K,'PLM002'!$C:$C,CK$4,'PLM002'!$F:$F,$B11)=0,"",SUMIFS('PLM002'!$K:$K,'PLM002'!$C:$C,CK$4,'PLM002'!$F:$F,$B11)) | CM11: =IF(SUMIFS('PLM001-財務計算用'!$P:$P,'PLM001-財務計算用'!$J:$J,CM$4,'PLM001-財務計算用'!$A:$A,$B11)=0,"",SUMIFS('PLM001-財務計算用'!$P:$P,'PLM001-財務計算用'!$J:$J,CM$4,'PLM001-財務計算用'!$A:$A,$B11)) | CN11: =IF(SUMIFS('PLM002'!$K:$K,'PLM002'!$C:$C,CM$4,'PLM002'!$F:$F,$B11)=0,"",SUMIFS('PLM002'!$K:$K,'PLM002'!$C:$C,CM$4,'PLM002'!$F:$F,$B11)) | CO11: =IF(SUMIFS('PLM001-財務計算用'!$P:$P,'PLM001-財務計算用'!$J:$J,CO$4,'PLM001-財務計算用'!$A:$A,$B11)=0,"",SUMIFS('PLM001-財務計算用'!$P:$P,'PLM001-財務計算用'!$J:$J,CO$4,'PLM001-財務計算用'!$A:$A,$B11)) | CP11: =IF(SUMIFS('PLM002'!$K:$K,'PLM002'!$C:$C,CO$4,'PLM002'!$F:$F,$B11)=0,"",SUMIFS('PLM002'!$K:$K,'PLM002'!$C:$C,CO$4,'PLM002'!$F:$F,$B11)) | CQ11: =IF(SUMIFS('PLM001-財務計算用'!$P:$P,'PLM001-財務計算用'!$J:$J,CQ$4,'PLM001-財務計算用'!$A:$A,$B11)=0,"",SUMIFS('PLM001-財務計算用'!$P:$P,'PLM001-財務計算用'!$J:$J,CQ$4,'PLM001-財務計算用'!$A:$A,$B11)) | CR11: =IF(SUMIFS('PLM002'!$K:$K,'PLM002'!$C:$C,CQ$4,'PLM002'!$F:$F,$B11)=0,"",SUMIFS('PLM002'!$K:$K,'PLM002'!$C:$C,CQ$4,'PLM002'!$F:$F,$B11)) | CS11: =IF(SUMIFS('PLM001-財務計算用'!$P:$P,'PLM001-財務計算用'!$J:$J,CS$4,'PLM001-財務計算用'!$A:$A,$B11)=0,"",SUMIFS('PLM001-財務計算用'!$P:$P,'PLM001-財務計算用'!$J:$J,CS$4,'PLM001-財務計算用'!$A:$A,$B11)) | CT11: =IF(SUMIFS('PLM002'!$K:$K,'PLM002'!$C:$C,CS$4,'PLM002'!$F:$F,$B11)=0,"",SUMIFS('PLM002'!$K:$K,'PLM002'!$C:$C,CS$4,'PLM002'!$F:$F,$B11)) | CU11: =IF(SUMIFS('PLM001-財務計算用'!$P:$P,'PLM001-財務計算用'!$J:$J,CU$4,'PLM001-財務計算用'!$A:$A,$B11)=0,"",SUMIFS('PLM001-財務計算用'!$P:$P,'PLM001-財務計算用'!$J:$J,CU$4,'PLM001-財務計算用'!$A:$A,$B11)) | CV11: =IF(SUMIFS('PLM002'!$K:$K,'PLM002'!$C:$C,CU$4,'PLM002'!$F:$F,$B11)=0,"",SUMIFS('PLM002'!$K:$K,'PLM002'!$C:$C,CU$4,'PLM002'!$F:$F,$B11)) | CW11: =IF(SUMIFS('PLM001-財務計算用'!$P:$P,'PLM001-財務計算用'!$J:$J,CW$4,'PLM001-財務計算用'!$A:$A,$B11)=0,"",SUMIFS('PLM001-財務計算用'!$P:$P,'PLM001-財務計算用'!$J:$J,CW$4,'PLM001-財務計算用'!$A:$A,$B11)) | CX11: =IF(SUMIFS('PLM002'!$K:$K,'PLM002'!$C:$C,CW$4,'PLM002'!$F:$F,$B11)=0,"",SUMIFS('PLM002'!$K:$K,'PLM002'!$C:$C,CW$4,'PLM002'!$F:$F,$B11)) | CY11: =IF(SUMIFS('PLM001-財務計算用'!$P:$P,'PLM001-財務計算用'!$J:$J,CY$4,'PLM001-財務計算用'!$A:$A,$B11)=0,"",SUMIFS('PLM001-財務計算用'!$P:$P,'PLM001-財務計算用'!$J:$J,CY$4,'PLM001-財務計算用'!$A:$A,$B11)) | CZ11: =IF(SUMIFS('PLM002'!$K:$K,'PLM002'!$C:$C,CY$4,'PLM002'!$F:$F,$B11)=0,"",SUMIFS('PLM002'!$K:$K,'PLM002'!$C:$C,CY$4,'PLM002'!$F:$F,$B11)) | DA11: =IF(SUMIFS('PLM001-財務計算用'!$P:$P,'PLM001-財務計算用'!$J:$J,DA$4,'PLM001-財務計算用'!$A:$A,$B11)=0,"",SUMIFS('PLM001-財務計算用'!$P:$P,'PLM001-財務計算用'!$J:$J,DA$4,'PLM001-財務計算用'!$A:$A,$B11)) | DB11: =IF(SUMIFS('PLM002'!$K:$K,'PLM002'!$C:$C,DA$4,'PLM002'!$F:$F,$B11)=0,"",SUMIFS('PLM002'!$K:$K,'PLM002'!$C:$C,DA$4,'PLM002'!$F:$F,$B11)) | DC11: =IF(SUMIFS('PLM001-財務計算用'!$P:$P,'PLM001-財務計算用'!$J:$J,DC$4,'PLM001-財務計算用'!$A:$A,$B11)=0,"",SUMIFS('PLM001-財務計算用'!$P:$P,'PLM001-財務計算用'!$J:$J,DC$4,'PLM001-財務計算用'!$A:$A,$B11)) | DD11: =IF(SUMIFS('PLM002'!$K:$K,'PLM002'!$C:$C,DC$4,'PLM002'!$F:$F,$B11)=0,"",SUMIFS('PLM002'!$K:$K,'PLM002'!$C:$C,DC$4,'PLM002'!$F:$F,$B11)) | DE11: =IF(SUMIFS('PLM001-財務計算用'!$P:$P,'PLM001-財務計算用'!$J:$J,DE$4,'PLM001-財務計算用'!$A:$A,$B11)=0,"",SUMIFS('PLM001-財務計算用'!$P:$P,'PLM001-財務計算用'!$J:$J,DE$4,'PLM001-財務計算用'!$A:$A,$B11)) | DF11: =IF(SUMIFS('PLM002'!$K:$K,'PLM002'!$C:$C,DE$4,'PLM002'!$F:$F,$B11)=0,"",SUMIFS('PLM002'!$K:$K,'PLM002'!$C:$C,DE$4,'PLM002'!$F:$F,$B11)) | DG11: =IF(SUMIFS('PLM001-財務計算用'!$P:$P,'PLM001-財務計算用'!$J:$J,DG$4,'PLM001-財務計算用'!$A:$A,$B11)=0,"",SUMIFS('PLM001-財務計算用'!$P:$P,'PLM001-財務計算用'!$J:$J,DG$4,'PLM001-財務計算用'!$A:$A,$B11)) | DH11: =IF(SUMIFS('PLM002'!$K:$K,'PLM002'!$C:$C,DG$4,'PLM002'!$F:$F,$B11)=0,"",SUMIFS('PLM002'!$K:$K,'PLM002'!$C:$C,DG$4,'PLM002'!$F:$F,$B11)) | DI11: =IF(SUMIFS('PLM001-財務計算用'!$P:$P,'PLM001-財務計算用'!$J:$J,DI$4,'PLM001-財務計算用'!$A:$A,$B11)=0,"",SUMIFS('PLM001-財務計算用'!$P:$P,'PLM001-財務計算用'!$J:$J,DI$4,'PLM001-財務計算用'!$A:$A,$B11)) | DJ11: =IF(SUMIFS('PLM002'!$K:$K,'PLM002'!$C:$C,DI$4,'PLM002'!$F:$F,$B11)=0,"",SUMIFS('PLM002'!$K:$K,'PLM002'!$C:$C,DI$4,'PLM002'!$F:$F,$B11)) | DK11: =IF(SUMIFS('PLM001-財務計算用'!$P:$P,'PLM001-財務計算用'!$J:$J,DK$4,'PLM001-財務計算用'!$A:$A,$B11)=0,"",SUMIFS('PLM001-財務計算用'!$P:$P,'PLM001-財務計算用'!$J:$J,DK$4,'PLM001-財務計算用'!$A:$A,$B11)) | DL11: =IF(SUMIFS('PLM002'!$K:$K,'PLM002'!$C:$C,DK$4,'PLM002'!$F:$F,$B11)=0,"",SUMIFS('PLM002'!$K:$K,'PLM002'!$C:$C,DK$4,'PLM002'!$F:$F,$B11)) | DM11: =IF(SUMIFS('PLM001-財務計算用'!$P:$P,'PLM001-財務計算用'!$J:$J,DM$4,'PLM001-財務計算用'!$A:$A,$B11)=0,"",SUMIFS('PLM001-財務計算用'!$P:$P,'PLM001-財務計算用'!$J:$J,DM$4,'PLM001-財務計算用'!$A:$A,$B11)) | DN11: =IF(SUMIFS('PLM002'!$K:$K,'PLM002'!$C:$C,DM$4,'PLM002'!$F:$F,$B11)=0,"",SUMIFS('PLM002'!$K:$K,'PLM002'!$C:$C,DM$4,'PLM002'!$F:$F,$B11)) | DO11: =IF(SUMIFS('PLM001-財務計算用'!$P:$P,'PLM001-財務計算用'!$J:$J,DO$4,'PLM001-財務計算用'!$A:$A,$B11)=0,"",SUMIFS('PLM001-財務計算用'!$P:$P,'PLM001-財務計算用'!$J:$J,DO$4,'PLM001-財務計算用'!$A:$A,$B11)) | DP11: =IF(SUMIFS('PLM002'!$K:$K,'PLM002'!$C:$C,DO$4,'PLM002'!$F:$F,$B11)=0,"",SUMIFS('PLM002'!$K:$K,'PLM002'!$C:$C,DO$4,'PLM002'!$F:$F,$B11)) | DQ11: =IF(SUMIFS('PLM001-財務計算用'!$P:$P,'PLM001-財務計算用'!$J:$J,DQ$4,'PLM001-財務計算用'!$A:$A,$B11)=0,"",SUMIFS('PLM001-財務計算用'!$P:$P,'PLM001-財務計算用'!$J:$J,DQ$4,'PLM001-財務計算用'!$A:$A,$B11)) | DR11: =IF(SUMIFS('PLM002'!$K:$K,'PLM002'!$C:$C,DQ$4,'PLM002'!$F:$F,$B11)=0,"",SUMIFS('PLM002'!$K:$K,'PLM002'!$C:$C,DQ$4,'PLM002'!$F:$F,$B11)) | DS11: =IF(SUMIFS('PLM001-財務計算用'!$P:$P,'PLM001-財務計算用'!$J:$J,DS$4,'PLM001-財務計算用'!$A:$A,$B11)=0,"",SUMIFS('PLM001-財務計算用'!$P:$P,'PLM001-財務計算用'!$J:$J,DS$4,'PLM001-財務計算用'!$A:$A,$B11)) | DT11: =IF(SUMIFS('PLM002'!$K:$K,'PLM002'!$C:$C,DS$4,'PLM002'!$F:$F,$B11)=0,"",SUMIFS('PLM002'!$K:$K,'PLM002'!$C:$C,DS$4,'PLM002'!$F:$F,$B11)) | DU11: =IF(SUMIFS('PLM001-財務計算用'!$P:$P,'PLM001-財務計算用'!$J:$J,DU$4,'PLM001-財務計算用'!$A:$A,$B11)=0,"",SUMIFS('PLM001-財務計算用'!$P:$P,'PLM001-財務計算用'!$J:$J,DU$4,'PLM001-財務計算用'!$A:$A,$B11)) | DV11: =IF(SUMIFS('PLM002'!$K:$K,'PLM002'!$C:$C,DU$4,'PLM002'!$F:$F,$B11)=0,"",SUMIFS('PLM002'!$K:$K,'PLM002'!$C:$C,DU$4,'PLM002'!$F:$F,$B11)) | DW11: =IF(SUMIFS('PLM001-財務計算用'!$P:$P,'PLM001-財務計算用'!$J:$J,DW$4,'PLM001-財務計算用'!$A:$A,$B11)=0,"",SUMIFS('PLM001-財務計算用'!$P:$P,'PLM001-財務計算用'!$J:$J,DW$4,'PLM001-財務計算用'!$A:$A,$B11)) | DX11: =IF(SUMIFS('PLM002'!$K:$K,'PLM002'!$C:$C,DW$4,'PLM002'!$F:$F,$B11)=0,"",SUMIFS('PLM002'!$K:$K,'PLM002'!$C:$C,DW$4,'PLM002'!$F:$F,$B11)) | DY11: =IF(SUMIFS('PLM001-財務計算用'!$P:$P,'PLM001-財務計算用'!$J:$J,DY$4,'PLM001-財務計算用'!$A:$A,$B11)=0,"",SUMIFS('PLM001-財務計算用'!$P:$P,'PLM001-財務計算用'!$J:$J,DY$4,'PLM001-財務計算用'!$A:$A,$B11)) | DZ11: =IF(SUMIFS('PLM002'!$K:$K,'PLM002'!$C:$C,DY$4,'PLM002'!$F:$F,$B11)=0,"",SUMIFS('PLM002'!$K:$K,'PLM002'!$C:$C,DY$4,'PLM002'!$F:$F,$B11)) | EA11: =IF(SUMIFS('PLM001-財務計算用'!$P:$P,'PLM001-財務計算用'!$J:$J,EA$4,'PLM001-財務計算用'!$A:$A,$B11)=0,"",SUMIFS('PLM001-財務計算用'!$P:$P,'PLM001-財務計算用'!$J:$J,EA$4,'PLM001-財務計算用'!$A:$A,$B11)) | EB11: =IF(SUMIFS('PLM002'!$K:$K,'PLM002'!$C:$C,EA$4,'PLM002'!$F:$F,$B11)=0,"",SUMIFS('PLM002'!$K:$K,'PLM002'!$C:$C,EA$4,'PLM002'!$F:$F,$B11)) | EC11: =IF(SUMIFS('PLM001-財務計算用'!$P:$P,'PLM001-財務計算用'!$J:$J,EC$4,'PLM001-財務計算用'!$A:$A,$B11)=0,"",SUMIFS('PLM001-財務計算用'!$P:$P,'PLM001-財務計算用'!$J:$J,EC$4,'PLM001-財務計算用'!$A:$A,$B11)) | ED11: =IF(SUMIFS('PLM002'!$K:$K,'PLM002'!$C:$C,EC$4,'PLM002'!$F:$F,$B11)=0,"",SUMIFS('PLM002'!$K:$K,'PLM002'!$C:$C,EC$4,'PLM002'!$F:$F,$B11))
A12: ='PLM014'!A13 -> D-協同 | B12: D250801R1 | C12: ='PLM014'!C13 -> SCX6标准/加长型技转 | D12: ="("&B12&")"&" "&C12 -> (D250801R1) SCX6标准/加长型技转 | E12: ='PLM014'!E13 -> 研发一部 | F12: ='PLM014'!F13 -> 郑仁春 | G12: ='PLM014'!G13 -> Active | H12: ='PLM014'!H13 -> 45869.667 | I12: ='PLM014'!I13 -> 45970.667 | J12: =IF(ISERROR(DATEDIF(H12,I12,"d")),"",DATEDIF(H12,I12,"d")) -> 101 | K12: =H12+(J12*0.75) -> 45945.417 | L12: =H12+(J12*0.95) -> 45965.617 | M12: =IF(ISERROR('PLM014'!L13),"",('PLM014'!L13)) -> 45870 | N12: =IF(IF(ISERROR('PLM014'!N13),"",('PLM014'!N13))=0,"",IF(ISERROR('PLM014'!N13),"",('PLM014'!N13))) | O12: =IF(ISERROR(DATEDIF(M12,N12,"d")),"",IF(DATEDIF(M12,N12,"d")=0,"",DATEDIF(M12,N12,"d"))) | P12: =IF(N12="",TODAY(),N12) -> 46044 | Q12: =IF(ISERROR(DATEDIF(M12,P12,"d")),"",IF(DATEDIF(M12,P12,"d")=0,"",DATEDIF(M12,P12,"d"))) -> 174 | R12: ='PLM014'!Q13/100 -> 0.33 | S12: =IF(AND(TODAY()>I12,R12<>100%,G12="Active"),"專案延遲 "&DATEDIF(I12,TODAY(),"d")&" 天",IF(AND(TODAY()>K12,R12<75%,G12="Active"),"專案即將異常",IF(AND(TODAY()>L12,R12<95%,G12="Active"),"專案即將異常",""))) -> 專案延遲 74 天 | U12: =IF(SUMIF($Y$5:$CV$5,$U$5,Y12:CV12)=0,"未登入",SUMIF($Y$5:$CV$5,$U$5,Y12:CV12)) -> 未登入 | V12: =SUMIF($Y$5:$CV$5,$V$5,Y12:CV12) -> 0 | W12: =IF(SUMIFS('PLM001-財務計算用'!$P:$P,'PLM001-財務計算用'!$A:$A,B12)=0,"未登入",SUMIFS('PLM001-財務計算用'!$P:$P,'PLM001-財務計算用'!$A:$A,B12)) -> 未登入 | X12: =SUMIFS('PLM002'!$K:$K,'PLM002'!$F:$F,$B12) -> 0 | Y12: =IF(SUMIFS('PLM001-財務計算用'!$P:$P,'PLM001-財務計算用'!$J:$J,Y$4,'PLM001-財務計算用'!$A:$A,$B12)=0,"",SUMIFS('PLM001-財務計算用'!$P:$P,'PLM001-財務計算用'!$J:$J,Y$4,'PLM001-財務計算用'!$A:$A,$B12)) | Z12: =IF(SUMIFS('PLM002'!$K:$K,'PLM002'!$C:$C,Y$4,'PLM002'!$F:$F,$B12)=0,"",SUMIFS('PLM002'!$K:$K,'PLM002'!$C:$C,Y$4,'PLM002'!$F:$F,$B12)) | AA12: =IF(SUMIFS('PLM001-財務計算用'!$P:$P,'PLM001-財務計算用'!$J:$J,AA$4,'PLM001-財務計算用'!$A:$A,$B12)=0,"",SUMIFS('PLM001-財務計算用'!$P:$P,'PLM001-財務計算用'!$J:$J,AA$4,'PLM001-財務計算用'!$A:$A,$B12)) | AB12: =IF(SUMIFS('PLM002'!$K:$K,'PLM002'!$C:$C,AA$4,'PLM002'!$F:$F,$B12)=0,"",SUMIFS('PLM002'!$K:$K,'PLM002'!$C:$C,AA$4,'PLM002'!$F:$F,$B12)) | AC12: =IF(SUMIFS('PLM001-財務計算用'!$P:$P,'PLM001-財務計算用'!$J:$J,AC$4,'PLM001-財務計算用'!$A:$A,$B12)=0,"",SUMIFS('PLM001-財務計算用'!$P:$P,'PLM001-財務計算用'!$J:$J,AC$4,'PLM001-財務計算用'!$A:$A,$B12)) | AD12: =IF(SUMIFS('PLM002'!$K:$K,'PLM002'!$C:$C,AC$4,'PLM002'!$F:$F,$B12)=0,"",SUMIFS('PLM002'!$K:$K,'PLM002'!$C:$C,AC$4,'PLM002'!$F:$F,$B12)) | AE12: =IF(SUMIFS('PLM001-財務計算用'!$P:$P,'PLM001-財務計算用'!$J:$J,AE$4,'PLM001-財務計算用'!$A:$A,$B12)=0,"",SUMIFS('PLM001-財務計算用'!$P:$P,'PLM001-財務計算用'!$J:$J,AE$4,'PLM001-財務計算用'!$A:$A,$B12)) | AF12: =IF(SUMIFS('PLM002'!$K:$K,'PLM002'!$C:$C,AE$4,'PLM002'!$F:$F,$B12)=0,"",SUMIFS('PLM002'!$K:$K,'PLM002'!$C:$C,AE$4,'PLM002'!$F:$F,$B12)) | AG12: =IF(SUMIFS('PLM001-財務計算用'!$P:$P,'PLM001-財務計算用'!$J:$J,AG$4,'PLM001-財務計算用'!$A:$A,$B12)=0,"",SUMIFS('PLM001-財務計算用'!$P:$P,'PLM001-財務計算用'!$J:$J,AG$4,'PLM001-財務計算用'!$A:$A,$B12)) | AH12: =IF(SUMIFS('PLM002'!$K:$K,'PLM002'!$C:$C,AG$4,'PLM002'!$F:$F,$B12)=0,"",SUMIFS('PLM002'!$K:$K,'PLM002'!$C:$C,AG$4,'PLM002'!$F:$F,$B12)) | AI12: =IF(SUMIFS('PLM001-財務計算用'!$P:$P,'PLM001-財務計算用'!$J:$J,AI$4,'PLM001-財務計算用'!$A:$A,$B12)=0,"",SUMIFS('PLM001-財務計算用'!$P:$P,'PLM001-財務計算用'!$J:$J,AI$4,'PLM001-財務計算用'!$A:$A,$B12)) | AJ12: =IF(SUMIFS('PLM002'!$K:$K,'PLM002'!$C:$C,AI$4,'PLM002'!$F:$F,$B12)=0,"",SUMIFS('PLM002'!$K:$K,'PLM002'!$C:$C,AI$4,'PLM002'!$F:$F,$B12)) | AK12: =IF(SUMIFS('PLM001-財務計算用'!$P:$P,'PLM001-財務計算用'!$J:$J,AK$4,'PLM001-財務計算用'!$A:$A,$B12)=0,"",SUMIFS('PLM001-財務計算用'!$P:$P,'PLM001-財務計算用'!$J:$J,AK$4,'PLM001-財務計算用'!$A:$A,$B12)) | AL12: =IF(SUMIFS('PLM002'!$K:$K,'PLM002'!$C:$C,AK$4,'PLM002'!$F:$F,$B12)=0,"",SUMIFS('PLM002'!$K:$K,'PLM002'!$C:$C,AK$4,'PLM002'!$F:$F,$B12)) | AM12: =IF(SUMIFS('PLM001-財務計算用'!$P:$P,'PLM001-財務計算用'!$J:$J,AM$4,'PLM001-財務計算用'!$A:$A,$B12)=0,"",SUMIFS('PLM001-財務計算用'!$P:$P,'PLM001-財務計算用'!$J:$J,AM$4,'PLM001-財務計算用'!$A:$A,$B12)) | AN12: =IF(SUMIFS('PLM002'!$K:$K,'PLM002'!$C:$C,AM$4,'PLM002'!$F:$F,$B12)=0,"",SUMIFS('PLM002'!$K:$K,'PLM002'!$C:$C,AM$4,'PLM002'!$F:$F,$B12)) | AO12: =IF(SUMIFS('PLM001-財務計算用'!$P:$P,'PLM001-財務計算用'!$J:$J,AO$4,'PLM001-財務計算用'!$A:$A,$B12)=0,"",SUMIFS('PLM001-財務計算用'!$P:$P,'PLM001-財務計算用'!$J:$J,AO$4,'PLM001-財務計算用'!$A:$A,$B12)) | AP12: =IF(SUMIFS('PLM002'!$K:$K,'PLM002'!$C:$C,AO$4,'PLM002'!$F:$F,$B12)=0,"",SUMIFS('PLM002'!$K:$K,'PLM002'!$C:$C,AO$4,'PLM002'!$F:$F,$B12)) | AQ12: =IF(SUMIFS('PLM001-財務計算用'!$P:$P,'PLM001-財務計算用'!$J:$J,AQ$4,'PLM001-財務計算用'!$A:$A,$B12)=0,"",SUMIFS('PLM001-財務計算用'!$P:$P,'PLM001-財務計算用'!$J:$J,AQ$4,'PLM001-財務計算用'!$A:$A,$B12)) | AR12: =IF(SUMIFS('PLM002'!$K:$K,'PLM002'!$C:$C,AQ$4,'PLM002'!$F:$F,$B12)=0,"",SUMIFS('PLM002'!$K:$K,'PLM002'!$C:$C,AQ$4,'PLM002'!$F:$F,$B12)) | AS12: =IF(SUMIFS('PLM001-財務計算用'!$P:$P,'PLM001-財務計算用'!$J:$J,AS$4,'PLM001-財務計算用'!$A:$A,$B12)=0,"",SUMIFS('PLM001-財務計算用'!$P:$P,'PLM001-財務計算用'!$J:$J,AS$4,'PLM001-財務計算用'!$A:$A,$B12)) | AT12: =IF(SUMIFS('PLM002'!$K:$K,'PLM002'!$C:$C,AS$4,'PLM002'!$F:$F,$B12)=0,"",SUMIFS('PLM002'!$K:$K,'PLM002'!$C:$C,AS$4,'PLM002'!$F:$F,$B12)) | AU12: =IF(SUMIFS('PLM001-財務計算用'!$P:$P,'PLM001-財務計算用'!$J:$J,AU$4,'PLM001-財務計算用'!$A:$A,$B12)=0,"",SUMIFS('PLM001-財務計算用'!$P:$P,'PLM001-財務計算用'!$J:$J,AU$4,'PLM001-財務計算用'!$A:$A,$B12)) | AV12: =IF(SUMIFS('PLM002'!$K:$K,'PLM002'!$C:$C,AU$4,'PLM002'!$F:$F,$B12)=0,"",SUMIFS('PLM002'!$K:$K,'PLM002'!$C:$C,AU$4,'PLM002'!$F:$F,$B12)) | AW12: =IF(SUMIFS('PLM001-財務計算用'!$P:$P,'PLM001-財務計算用'!$J:$J,AW$4,'PLM001-財務計算用'!$A:$A,$B12)=0,"",SUMIFS('PLM001-財務計算用'!$P:$P,'PLM001-財務計算用'!$J:$J,AW$4,'PLM001-財務計算用'!$A:$A,$B12)) | AX12: =IF(SUMIFS('PLM002'!$K:$K,'PLM002'!$C:$C,AW$4,'PLM002'!$F:$F,$B12)=0,"",SUMIFS('PLM002'!$K:$K,'PLM002'!$C:$C,AW$4,'PLM002'!$F:$F,$B12)) | AY12: =IF(SUMIFS('PLM001-財務計算用'!$P:$P,'PLM001-財務計算用'!$J:$J,AY$4,'PLM001-財務計算用'!$A:$A,$B12)=0,"",SUMIFS('PLM001-財務計算用'!$P:$P,'PLM001-財務計算用'!$J:$J,AY$4,'PLM001-財務計算用'!$A:$A,$B12)) | AZ12: =IF(SUMIFS('PLM002'!$K:$K,'PLM002'!$C:$C,AY$4,'PLM002'!$F:$F,$B12)=0,"",SUMIFS('PLM002'!$K:$K,'PLM002'!$C:$C,AY$4,'PLM002'!$F:$F,$B12)) | BA12: =IF(SUMIFS('PLM001-財務計算用'!$P:$P,'PLM001-財務計算用'!$J:$J,BA$4,'PLM001-財務計算用'!$A:$A,$B12)=0,"",SUMIFS('PLM001-財務計算用'!$P:$P,'PLM001-財務計算用'!$J:$J,BA$4,'PLM001-財務計算用'!$A:$A,$B12)) | BB12: =IF(SUMIFS('PLM002'!$K:$K,'PLM002'!$C:$C,BA$4,'PLM002'!$F:$F,$B12)=0,"",SUMIFS('PLM002'!$K:$K,'PLM002'!$C:$C,BA$4,'PLM002'!$F:$F,$B12)) | BC12: =IF(SUMIFS('PLM001-財務計算用'!$P:$P,'PLM001-財務計算用'!$J:$J,BC$4,'PLM001-財務計算用'!$A:$A,$B12)=0,"",SUMIFS('PLM001-財務計算用'!$P:$P,'PLM001-財務計算用'!$J:$J,BC$4,'PLM001-財務計算用'!$A:$A,$B12)) | BD12: =IF(SUMIFS('PLM002'!$K:$K,'PLM002'!$C:$C,BC$4,'PLM002'!$F:$F,$B12)=0,"",SUMIFS('PLM002'!$K:$K,'PLM002'!$C:$C,BC$4,'PLM002'!$F:$F,$B12)) | BE12: =IF(SUMIFS('PLM001-財務計算用'!$P:$P,'PLM001-財務計算用'!$J:$J,BE$4,'PLM001-財務計算用'!$A:$A,$B12)=0,"",SUMIFS('PLM001-財務計算用'!$P:$P,'PLM001-財務計算用'!$J:$J,BE$4,'PLM001-財務計算用'!$A:$A,$B12)) | BF12: =IF(SUMIFS('PLM002'!$K:$K,'PLM002'!$C:$C,BE$4,'PLM002'!$F:$F,$B12)=0,"",SUMIFS('PLM002'!$K:$K,'PLM002'!$C:$C,BE$4,'PLM002'!$F:$F,$B12)) | BG12: =IF(SUMIFS('PLM001-財務計算用'!$P:$P,'PLM001-財務計算用'!$J:$J,BG$4,'PLM001-財務計算用'!$A:$A,$B12)=0,"",SUMIFS('PLM001-財務計算用'!$P:$P,'PLM001-財務計算用'!$J:$J,BG$4,'PLM001-財務計算用'!$A:$A,$B12)) | BH12: =IF(SUMIFS('PLM002'!$K:$K,'PLM002'!$C:$C,BG$4,'PLM002'!$F:$F,$B12)=0,"",SUMIFS('PLM002'!$K:$K,'PLM002'!$C:$C,BG$4,'PLM002'!$F:$F,$B12)) | BI12: =IF(SUMIFS('PLM001-財務計算用'!$P:$P,'PLM001-財務計算用'!$J:$J,BI$4,'PLM001-財務計算用'!$A:$A,$B12)=0,"",SUMIFS('PLM001-財務計算用'!$P:$P,'PLM001-財務計算用'!$J:$J,BI$4,'PLM001-財務計算用'!$A:$A,$B12)) | BJ12: =IF(SUMIFS('PLM002'!$K:$K,'PLM002'!$C:$C,BI$4,'PLM002'!$F:$F,$B12)=0,"",SUMIFS('PLM002'!$K:$K,'PLM002'!$C:$C,BI$4,'PLM002'!$F:$F,$B12)) | BK12: =IF(SUMIFS('PLM001-財務計算用'!$P:$P,'PLM001-財務計算用'!$J:$J,BK$4,'PLM001-財務計算用'!$A:$A,$B12)=0,"",SUMIFS('PLM001-財務計算用'!$P:$P,'PLM001-財務計算用'!$J:$J,BK$4,'PLM001-財務計算用'!$A:$A,$B12)) | BL12: =IF(SUMIFS('PLM002'!$K:$K,'PLM002'!$C:$C,BK$4,'PLM002'!$F:$F,$B12)=0,"",SUMIFS('PLM002'!$K:$K,'PLM002'!$C:$C,BK$4,'PLM002'!$F:$F,$B12)) | BM12: =IF(SUMIFS('PLM001-財務計算用'!$P:$P,'PLM001-財務計算用'!$J:$J,BM$4,'PLM001-財務計算用'!$A:$A,$B12)=0,"",SUMIFS('PLM001-財務計算用'!$P:$P,'PLM001-財務計算用'!$J:$J,BM$4,'PLM001-財務計算用'!$A:$A,$B12)) | BN12: =IF(SUMIFS('PLM002'!$K:$K,'PLM002'!$C:$C,BM$4,'PLM002'!$F:$F,$B12)=0,"",SUMIFS('PLM002'!$K:$K,'PLM002'!$C:$C,BM$4,'PLM002'!$F:$F,$B12)) | BO12: =IF(SUMIFS('PLM001-財務計算用'!$P:$P,'PLM001-財務計算用'!$J:$J,BO$4,'PLM001-財務計算用'!$A:$A,$B12)=0,"",SUMIFS('PLM001-財務計算用'!$P:$P,'PLM001-財務計算用'!$J:$J,BO$4,'PLM001-財務計算用'!$A:$A,$B12)) | BP12: =IF(SUMIFS('PLM002'!$K:$K,'PLM002'!$C:$C,BO$4,'PLM002'!$F:$F,$B12)=0,"",SUMIFS('PLM002'!$K:$K,'PLM002'!$C:$C,BO$4,'PLM002'!$F:$F,$B12)) | BQ12: =IF(SUMIFS('PLM001-財務計算用'!$P:$P,'PLM001-財務計算用'!$J:$J,BQ$4,'PLM001-財務計算用'!$A:$A,$B12)=0,"",SUMIFS('PLM001-財務計算用'!$P:$P,'PLM001-財務計算用'!$J:$J,BQ$4,'PLM001-財務計算用'!$A:$A,$B12)) | BR12: =IF(SUMIFS('PLM002'!$K:$K,'PLM002'!$C:$C,BQ$4,'PLM002'!$F:$F,$B12)=0,"",SUMIFS('PLM002'!$K:$K,'PLM002'!$C:$C,BQ$4,'PLM002'!$F:$F,$B12)) | BS12: =IF(SUMIFS('PLM001-財務計算用'!$P:$P,'PLM001-財務計算用'!$J:$J,BS$4,'PLM001-財務計算用'!$A:$A,$B12)=0,"",SUMIFS('PLM001-財務計算用'!$P:$P,'PLM001-財務計算用'!$J:$J,BS$4,'PLM001-財務計算用'!$A:$A,$B12)) | BT12: =IF(SUMIFS('PLM002'!$K:$K,'PLM002'!$C:$C,BS$4,'PLM002'!$F:$F,$B12)=0,"",SUMIFS('PLM002'!$K:$K,'PLM002'!$C:$C,BS$4,'PLM002'!$F:$F,$B12)) | BU12: =IF(SUMIFS('PLM001-財務計算用'!$P:$P,'PLM001-財務計算用'!$J:$J,BU$4,'PLM001-財務計算用'!$A:$A,$B12)=0,"",SUMIFS('PLM001-財務計算用'!$P:$P,'PLM001-財務計算用'!$J:$J,BU$4,'PLM001-財務計算用'!$A:$A,$B12)) | BV12: =IF(SUMIFS('PLM002'!$K:$K,'PLM002'!$C:$C,BU$4,'PLM002'!$F:$F,$B12)=0,"",SUMIFS('PLM002'!$K:$K,'PLM002'!$C:$C,BU$4,'PLM002'!$F:$F,$B12)) | BW12: =IF(SUMIFS('PLM001-財務計算用'!$P:$P,'PLM001-財務計算用'!$J:$J,BW$4,'PLM001-財務計算用'!$A:$A,$B12)=0,"",SUMIFS('PLM001-財務計算用'!$P:$P,'PLM001-財務計算用'!$J:$J,BW$4,'PLM001-財務計算用'!$A:$A,$B12)) | BX12: =IF(SUMIFS('PLM002'!$K:$K,'PLM002'!$C:$C,BW$4,'PLM002'!$F:$F,$B12)=0,"",SUMIFS('PLM002'!$K:$K,'PLM002'!$C:$C,BW$4,'PLM002'!$F:$F,$B12)) | BY12: =IF(SUMIFS('PLM001-財務計算用'!$P:$P,'PLM001-財務計算用'!$J:$J,BY$4,'PLM001-財務計算用'!$A:$A,$B12)=0,"",SUMIFS('PLM001-財務計算用'!$P:$P,'PLM001-財務計算用'!$J:$J,BY$4,'PLM001-財務計算用'!$A:$A,$B12)) | BZ12: =IF(SUMIFS('PLM002'!$K:$K,'PLM002'!$C:$C,BY$4,'PLM002'!$F:$F,$B12)=0,"",SUMIFS('PLM002'!$K:$K,'PLM002'!$C:$C,BY$4,'PLM002'!$F:$F,$B12)) | CA12: =IF(SUMIFS('PLM001-財務計算用'!$P:$P,'PLM001-財務計算用'!$J:$J,CA$4,'PLM001-財務計算用'!$A:$A,$B12)=0,"",SUMIFS('PLM001-財務計算用'!$P:$P,'PLM001-財務計算用'!$J:$J,CA$4,'PLM001-財務計算用'!$A:$A,$B12)) | CB12: =IF(SUMIFS('PLM002'!$K:$K,'PLM002'!$C:$C,CA$4,'PLM002'!$F:$F,$B12)=0,"",SUMIFS('PLM002'!$K:$K,'PLM002'!$C:$C,CA$4,'PLM002'!$F:$F,$B12)) | CC12: =IF(SUMIFS('PLM001-財務計算用'!$P:$P,'PLM001-財務計算用'!$J:$J,CC$4,'PLM001-財務計算用'!$A:$A,$B12)=0,"",SUMIFS('PLM001-財務計算用'!$P:$P,'PLM001-財務計算用'!$J:$J,CC$4,'PLM001-財務計算用'!$A:$A,$B12)) | CD12: =IF(SUMIFS('PLM002'!$K:$K,'PLM002'!$C:$C,CC$4,'PLM002'!$F:$F,$B12)=0,"",SUMIFS('PLM002'!$K:$K,'PLM002'!$C:$C,CC$4,'PLM002'!$F:$F,$B12)) | CE12: =IF(SUMIFS('PLM001-財務計算用'!$P:$P,'PLM001-財務計算用'!$J:$J,CE$4,'PLM001-財務計算用'!$A:$A,$B12)=0,"",SUMIFS('PLM001-財務計算用'!$P:$P,'PLM001-財務計算用'!$J:$J,CE$4,'PLM001-財務計算用'!$A:$A,$B12)) | CF12: =IF(SUMIFS('PLM002'!$K:$K,'PLM002'!$C:$C,CE$4,'PLM002'!$F:$F,$B12)=0,"",SUMIFS('PLM002'!$K:$K,'PLM002'!$C:$C,CE$4,'PLM002'!$F:$F,$B12)) | CG12: =IF(SUMIFS('PLM001-財務計算用'!$P:$P,'PLM001-財務計算用'!$J:$J,CG$4,'PLM001-財務計算用'!$A:$A,$B12)=0,"",SUMIFS('PLM001-財務計算用'!$P:$P,'PLM001-財務計算用'!$J:$J,CG$4,'PLM001-財務計算用'!$A:$A,$B12)) | CH12: =IF(SUMIFS('PLM002'!$K:$K,'PLM002'!$C:$C,CG$4,'PLM002'!$F:$F,$B12)=0,"",SUMIFS('PLM002'!$K:$K,'PLM002'!$C:$C,CG$4,'PLM002'!$F:$F,$B12)) | CI12: =IF(SUMIFS('PLM001-財務計算用'!$P:$P,'PLM001-財務計算用'!$J:$J,CI$4,'PLM001-財務計算用'!$A:$A,$B12)=0,"",SUMIFS('PLM001-財務計算用'!$P:$P,'PLM001-財務計算用'!$J:$J,CI$4,'PLM001-財務計算用'!$A:$A,$B12)) | CJ12: =IF(SUMIFS('PLM002'!$K:$K,'PLM002'!$C:$C,CI$4,'PLM002'!$F:$F,$B12)=0,"",SUMIFS('PLM002'!$K:$K,'PLM002'!$C:$C,CI$4,'PLM002'!$F:$F,$B12)) | CK12: =IF(SUMIFS('PLM001-財務計算用'!$P:$P,'PLM001-財務計算用'!$J:$J,CK$4,'PLM001-財務計算用'!$A:$A,$B12)=0,"",SUMIFS('PLM001-財務計算用'!$P:$P,'PLM001-財務計算用'!$J:$J,CK$4,'PLM001-財務計算用'!$A:$A,$B12)) | CL12: =IF(SUMIFS('PLM002'!$K:$K,'PLM002'!$C:$C,CK$4,'PLM002'!$F:$F,$B12)=0,"",SUMIFS('PLM002'!$K:$K,'PLM002'!$C:$C,CK$4,'PLM002'!$F:$F,$B12)) | CM12: =IF(SUMIFS('PLM001-財務計算用'!$P:$P,'PLM001-財務計算用'!$J:$J,CM$4,'PLM001-財務計算用'!$A:$A,$B12)=0,"",SUMIFS('PLM001-財務計算用'!$P:$P,'PLM001-財務計算用'!$J:$J,CM$4,'PLM001-財務計算用'!$A:$A,$B12)) | CN12: =IF(SUMIFS('PLM002'!$K:$K,'PLM002'!$C:$C,CM$4,'PLM002'!$F:$F,$B12)=0,"",SUMIFS('PLM002'!$K:$K,'PLM002'!$C:$C,CM$4,'PLM002'!$F:$F,$B12)) | CO12: =IF(SUMIFS('PLM001-財務計算用'!$P:$P,'PLM001-財務計算用'!$J:$J,CO$4,'PLM001-財務計算用'!$A:$A,$B12)=0,"",SUMIFS('PLM001-財務計算用'!$P:$P,'PLM001-財務計算用'!$J:$J,CO$4,'PLM001-財務計算用'!$A:$A,$B12)) | CP12: =IF(SUMIFS('PLM002'!$K:$K,'PLM002'!$C:$C,CO$4,'PLM002'!$F:$F,$B12)=0,"",SUMIFS('PLM002'!$K:$K,'PLM002'!$C:$C,CO$4,'PLM002'!$F:$F,$B12)) | CQ12: =IF(SUMIFS('PLM001-財務計算用'!$P:$P,'PLM001-財務計算用'!$J:$J,CQ$4,'PLM001-財務計算用'!$A:$A,$B12)=0,"",SUMIFS('PLM001-財務計算用'!$P:$P,'PLM001-財務計算用'!$J:$J,CQ$4,'PLM001-財務計算用'!$A:$A,$B12)) | CR12: =IF(SUMIFS('PLM002'!$K:$K,'PLM002'!$C:$C,CQ$4,'PLM002'!$F:$F,$B12)=0,"",SUMIFS('PLM002'!$K:$K,'PLM002'!$C:$C,CQ$4,'PLM002'!$F:$F,$B12)) | CS12: =IF(SUMIFS('PLM001-財務計算用'!$P:$P,'PLM001-財務計算用'!$J:$J,CS$4,'PLM001-財務計算用'!$A:$A,$B12)=0,"",SUMIFS('PLM001-財務計算用'!$P:$P,'PLM001-財務計算用'!$J:$J,CS$4,'PLM001-財務計算用'!$A:$A,$B12)) | CT12: =IF(SUMIFS('PLM002'!$K:$K,'PLM002'!$C:$C,CS$4,'PLM002'!$F:$F,$B12)=0,"",SUMIFS('PLM002'!$K:$K,'PLM002'!$C:$C,CS$4,'PLM002'!$F:$F,$B12)) | CU12: =IF(SUMIFS('PLM001-財務計算用'!$P:$P,'PLM001-財務計算用'!$J:$J,CU$4,'PLM001-財務計算用'!$A:$A,$B12)=0,"",SUMIFS('PLM001-財務計算用'!$P:$P,'PLM001-財務計算用'!$J:$J,CU$4,'PLM001-財務計算用'!$A:$A,$B12)) | CV12: =IF(SUMIFS('PLM002'!$K:$K,'PLM002'!$C:$C,CU$4,'PLM002'!$F:$F,$B12)=0,"",SUMIFS('PLM002'!$K:$K,'PLM002'!$C:$C,CU$4,'PLM002'!$F:$F,$B12)) | CW12: =IF(SUMIFS('PLM001-財務計算用'!$P:$P,'PLM001-財務計算用'!$J:$J,CW$4,'PLM001-財務計算用'!$A:$A,$B12)=0,"",SUMIFS('PLM001-財務計算用'!$P:$P,'PLM001-財務計算用'!$J:$J,CW$4,'PLM001-財務計算用'!$A:$A,$B12)) | CX12: =IF(SUMIFS('PLM002'!$K:$K,'PLM002'!$C:$C,CW$4,'PLM002'!$F:$F,$B12)=0,"",SUMIFS('PLM002'!$K:$K,'PLM002'!$C:$C,CW$4,'PLM002'!$F:$F,$B12)) | CY12: =IF(SUMIFS('PLM001-財務計算用'!$P:$P,'PLM001-財務計算用'!$J:$J,CY$4,'PLM001-財務計算用'!$A:$A,$B12)=0,"",SUMIFS('PLM001-財務計算用'!$P:$P,'PLM001-財務計算用'!$J:$J,CY$4,'PLM001-財務計算用'!$A:$A,$B12)) | CZ12: =IF(SUMIFS('PLM002'!$K:$K,'PLM002'!$C:$C,CY$4,'PLM002'!$F:$F,$B12)=0,"",SUMIFS('PLM002'!$K:$K,'PLM002'!$C:$C,CY$4,'PLM002'!$F:$F,$B12)) | DA12: =IF(SUMIFS('PLM001-財務計算用'!$P:$P,'PLM001-財務計算用'!$J:$J,DA$4,'PLM001-財務計算用'!$A:$A,$B12)=0,"",SUMIFS('PLM001-財務計算用'!$P:$P,'PLM001-財務計算用'!$J:$J,DA$4,'PLM001-財務計算用'!$A:$A,$B12)) | DB12: =IF(SUMIFS('PLM002'!$K:$K,'PLM002'!$C:$C,DA$4,'PLM002'!$F:$F,$B12)=0,"",SUMIFS('PLM002'!$K:$K,'PLM002'!$C:$C,DA$4,'PLM002'!$F:$F,$B12)) | DC12: =IF(SUMIFS('PLM001-財務計算用'!$P:$P,'PLM001-財務計算用'!$J:$J,DC$4,'PLM001-財務計算用'!$A:$A,$B12)=0,"",SUMIFS('PLM001-財務計算用'!$P:$P,'PLM001-財務計算用'!$J:$J,DC$4,'PLM001-財務計算用'!$A:$A,$B12)) | DD12: =IF(SUMIFS('PLM002'!$K:$K,'PLM002'!$C:$C,DC$4,'PLM002'!$F:$F,$B12)=0,"",SUMIFS('PLM002'!$K:$K,'PLM002'!$C:$C,DC$4,'PLM002'!$F:$F,$B12)) | DE12: =IF(SUMIFS('PLM001-財務計算用'!$P:$P,'PLM001-財務計算用'!$J:$J,DE$4,'PLM001-財務計算用'!$A:$A,$B12)=0,"",SUMIFS('PLM001-財務計算用'!$P:$P,'PLM001-財務計算用'!$J:$J,DE$4,'PLM001-財務計算用'!$A:$A,$B12)) | DF12: =IF(SUMIFS('PLM002'!$K:$K,'PLM002'!$C:$C,DE$4,'PLM002'!$F:$F,$B12)=0,"",SUMIFS('PLM002'!$K:$K,'PLM002'!$C:$C,DE$4,'PLM002'!$F:$F,$B12)) | DG12: =IF(SUMIFS('PLM001-財務計算用'!$P:$P,'PLM001-財務計算用'!$J:$J,DG$4,'PLM001-財務計算用'!$A:$A,$B12)=0,"",SUMIFS('PLM001-財務計算用'!$P:$P,'PLM001-財務計算用'!$J:$J,DG$4,'PLM001-財務計算用'!$A:$A,$B12)) | DH12: =IF(SUMIFS('PLM002'!$K:$K,'PLM002'!$C:$C,DG$4,'PLM002'!$F:$F,$B12)=0,"",SUMIFS('PLM002'!$K:$K,'PLM002'!$C:$C,DG$4,'PLM002'!$F:$F,$B12)) | DI12: =IF(SUMIFS('PLM001-財務計算用'!$P:$P,'PLM001-財務計算用'!$J:$J,DI$4,'PLM001-財務計算用'!$A:$A,$B12)=0,"",SUMIFS('PLM001-財務計算用'!$P:$P,'PLM001-財務計算用'!$J:$J,DI$4,'PLM001-財務計算用'!$A:$A,$B12)) | DJ12: =IF(SUMIFS('PLM002'!$K:$K,'PLM002'!$C:$C,DI$4,'PLM002'!$F:$F,$B12)=0,"",SUMIFS('PLM002'!$K:$K,'PLM002'!$C:$C,DI$4,'PLM002'!$F:$F,$B12)) | DK12: =IF(SUMIFS('PLM001-財務計算用'!$P:$P,'PLM001-財務計算用'!$J:$J,DK$4,'PLM001-財務計算用'!$A:$A,$B12)=0,"",SUMIFS('PLM001-財務計算用'!$P:$P,'PLM001-財務計算用'!$J:$J,DK$4,'PLM001-財務計算用'!$A:$A,$B12)) | DL12: =IF(SUMIFS('PLM002'!$K:$K,'PLM002'!$C:$C,DK$4,'PLM002'!$F:$F,$B12)=0,"",SUMIFS('PLM002'!$K:$K,'PLM002'!$C:$C,DK$4,'PLM002'!$F:$F,$B12)) | DM12: =IF(SUMIFS('PLM001-財務計算用'!$P:$P,'PLM001-財務計算用'!$J:$J,DM$4,'PLM001-財務計算用'!$A:$A,$B12)=0,"",SUMIFS('PLM001-財務計算用'!$P:$P,'PLM001-財務計算用'!$J:$J,DM$4,'PLM001-財務計算用'!$A:$A,$B12)) | DN12: =IF(SUMIFS('PLM002'!$K:$K,'PLM002'!$C:$C,DM$4,'PLM002'!$F:$F,$B12)=0,"",SUMIFS('PLM002'!$K:$K,'PLM002'!$C:$C,DM$4,'PLM002'!$F:$F,$B12)) | DO12: =IF(SUMIFS('PLM001-財務計算用'!$P:$P,'PLM001-財務計算用'!$J:$J,DO$4,'PLM001-財務計算用'!$A:$A,$B12)=0,"",SUMIFS('PLM001-財務計算用'!$P:$P,'PLM001-財務計算用'!$J:$J,DO$4,'PLM001-財務計算用'!$A:$A,$B12)) | DP12: =IF(SUMIFS('PLM002'!$K:$K,'PLM002'!$C:$C,DO$4,'PLM002'!$F:$F,$B12)=0,"",SUMIFS('PLM002'!$K:$K,'PLM002'!$C:$C,DO$4,'PLM002'!$F:$F,$B12)) | DQ12: =IF(SUMIFS('PLM001-財務計算用'!$P:$P,'PLM001-財務計算用'!$J:$J,DQ$4,'PLM001-財務計算用'!$A:$A,$B12)=0,"",SUMIFS('PLM001-財務計算用'!$P:$P,'PLM001-財務計算用'!$J:$J,DQ$4,'PLM001-財務計算用'!$A:$A,$B12)) | DR12: =IF(SUMIFS('PLM002'!$K:$K,'PLM002'!$C:$C,DQ$4,'PLM002'!$F:$F,$B12)=0,"",SUMIFS('PLM002'!$K:$K,'PLM002'!$C:$C,DQ$4,'PLM002'!$F:$F,$B12)) | DS12: =IF(SUMIFS('PLM001-財務計算用'!$P:$P,'PLM001-財務計算用'!$J:$J,DS$4,'PLM001-財務計算用'!$A:$A,$B12)=0,"",SUMIFS('PLM001-財務計算用'!$P:$P,'PLM001-財務計算用'!$J:$J,DS$4,'PLM001-財務計算用'!$A:$A,$B12)) | DT12: =IF(SUMIFS('PLM002'!$K:$K,'PLM002'!$C:$C,DS$4,'PLM002'!$F:$F,$B12)=0,"",SUMIFS('PLM002'!$K:$K,'PLM002'!$C:$C,DS$4,'PLM002'!$F:$F,$B12)) | DU12: =IF(SUMIFS('PLM001-財務計算用'!$P:$P,'PLM001-財務計算用'!$J:$J,DU$4,'PLM001-財務計算用'!$A:$A,$B12)=0,"",SUMIFS('PLM001-財務計算用'!$P:$P,'PLM001-財務計算用'!$J:$J,DU$4,'PLM001-財務計算用'!$A:$A,$B12)) | DV12: =IF(SUMIFS('PLM002'!$K:$K,'PLM002'!$C:$C,DU$4,'PLM002'!$F:$F,$B12)=0,"",SUMIFS('PLM002'!$K:$K,'PLM002'!$C:$C,DU$4,'PLM002'!$F:$F,$B12)) | DW12: =IF(SUMIFS('PLM001-財務計算用'!$P:$P,'PLM001-財務計算用'!$J:$J,DW$4,'PLM001-財務計算用'!$A:$A,$B12)=0,"",SUMIFS('PLM001-財務計算用'!$P:$P,'PLM001-財務計算用'!$J:$J,DW$4,'PLM001-財務計算用'!$A:$A,$B12)) | DX12: =IF(SUMIFS('PLM002'!$K:$K,'PLM002'!$C:$C,DW$4,'PLM002'!$F:$F,$B12)=0,"",SUMIFS('PLM002'!$K:$K,'PLM002'!$C:$C,DW$4,'PLM002'!$F:$F,$B12)) | DY12: =IF(SUMIFS('PLM001-財務計算用'!$P:$P,'PLM001-財務計算用'!$J:$J,DY$4,'PLM001-財務計算用'!$A:$A,$B12)=0,"",SUMIFS('PLM001-財務計算用'!$P:$P,'PLM001-財務計算用'!$J:$J,DY$4,'PLM001-財務計算用'!$A:$A,$B12)) | DZ12: =IF(SUMIFS('PLM002'!$K:$K,'PLM002'!$C:$C,DY$4,'PLM002'!$F:$F,$B12)=0,"",SUMIFS('PLM002'!$K:$K,'PLM002'!$C:$C,DY$4,'PLM002'!$F:$F,$B12)) | EA12: =IF(SUMIFS('PLM001-財務計算用'!$P:$P,'PLM001-財務計算用'!$J:$J,EA$4,'PLM001-財務計算用'!$A:$A,$B12)=0,"",SUMIFS('PLM001-財務計算用'!$P:$P,'PLM001-財務計算用'!$J:$J,EA$4,'PLM001-財務計算用'!$A:$A,$B12)) | EB12: =IF(SUMIFS('PLM002'!$K:$K,'PLM002'!$C:$C,EA$4,'PLM002'!$F:$F,$B12)=0,"",SUMIFS('PLM002'!$K:$K,'PLM002'!$C:$C,EA$4,'PLM002'!$F:$F,$B12)) | EC12: =IF(SUMIFS('PLM001-財務計算用'!$P:$P,'PLM001-財務計算用'!$J:$J,EC$4,'PLM001-財務計算用'!$A:$A,$B12)=0,"",SUMIFS('PLM001-財務計算用'!$P:$P,'PLM001-財務計算用'!$J:$J,EC$4,'PLM001-財務計算用'!$A:$A,$B12)) | ED12: =IF(SUMIFS('PLM002'!$K:$K,'PLM002'!$C:$C,EC$4,'PLM002'!$F:$F,$B12)=0,"",SUMIFS('PLM002'!$K:$K,'PLM002'!$C:$C,EC$4,'PLM002'!$F:$F,$B12))
A13: ='PLM014'!A14 -> D-協同 | B13: D250802R1 | C13: ='PLM014'!C14 -> 申請量桶量槽製作資格 | D13: ="("&B13&")"&" "&C13 -> (D250802R1) 申請量桶量槽製作資格 | E13: ='PLM014'!E14 -> 研一部 | F13: ='PLM014'!F14 -> 何昆達 | G13: ='PLM014'!G14 -> Active | H13: ='PLM014'!H14 -> 45886.667 | I13: ='PLM014'!I14 -> 46049.667 | J13: =IF(ISERROR(DATEDIF(H13,I13,"d")),"",DATEDIF(H13,I13,"d")) -> 163 | K13: =H13+(J13*0.75) -> 46008.917 | L13: =H13+(J13*0.95) -> 46041.517 | M13: =IF(ISERROR('PLM014'!L14),"",('PLM014'!L14)) -> 45887 | N13: =IF(IF(ISERROR('PLM014'!N14),"",('PLM014'!N14))=0,"",IF(ISERROR('PLM014'!N14),"",('PLM014'!N14))) | O13: =IF(ISERROR(DATEDIF(M13,N13,"d")),"",IF(DATEDIF(M13,N13,"d")=0,"",DATEDIF(M13,N13,"d"))) | P13: =IF(N13="",TODAY(),N13) -> 46044 | Q13: =IF(ISERROR(DATEDIF(M13,P13,"d")),"",IF(DATEDIF(M13,P13,"d")=0,"",DATEDIF(M13,P13,"d"))) -> 157 | R13: ='PLM014'!Q14/100 -> 0.78 | S13: =IF(AND(TODAY()>I13,R13<>100%,G13="Active"),"專案延遲 "&DATEDIF(I13,TODAY(),"d")&" 天",IF(AND(TODAY()>K13,R13<75%,G13="Active"),"專案即將異常",IF(AND(TODAY()>L13,R13<95%,G13="Active"),"專案即將異常",""))) -> 專案即將異常 | U13: =IF(SUMIF($Y$5:$CV$5,$U$5,Y13:CV13)=0,"未登入",SUMIF($Y$5:$CV$5,$U$5,Y13:CV13)) -> 184 | V13: =SUMIF($Y$5:$CV$5,$V$5,Y13:CV13) -> 172.7 | W13: =IF(SUMIFS('PLM001-財務計算用'!$P:$P,'PLM001-財務計算用'!$A:$A,B13)=0,"未登入",SUMIFS('PLM001-財務計算用'!$P:$P,'PLM001-財務計算用'!$A:$A,B13)) -> 184 | X13: =SUMIFS('PLM002'!$K:$K,'PLM002'!$F:$F,$B13) -> 172.7 | Y13: =IF(SUMIFS('PLM001-財務計算用'!$P:$P,'PLM001-財務計算用'!$J:$J,Y$4,'PLM001-財務計算用'!$A:$A,$B13)=0,"",SUMIFS('PLM001-財務計算用'!$P:$P,'PLM001-財務計算用'!$J:$J,Y$4,'PLM001-財務計算用'!$A:$A,$B13)) | Z13: =IF(SUMIFS('PLM002'!$K:$K,'PLM002'!$C:$C,Y$4,'PLM002'!$F:$F,$B13)=0,"",SUMIFS('PLM002'!$K:$K,'PLM002'!$C:$C,Y$4,'PLM002'!$F:$F,$B13)) | AA13: =IF(SUMIFS('PLM001-財務計算用'!$P:$P,'PLM001-財務計算用'!$J:$J,AA$4,'PLM001-財務計算用'!$A:$A,$B13)=0,"",SUMIFS('PLM001-財務計算用'!$P:$P,'PLM001-財務計算用'!$J:$J,AA$4,'PLM001-財務計算用'!$A:$A,$B13)) | AB13: =IF(SUMIFS('PLM002'!$K:$K,'PLM002'!$C:$C,AA$4,'PLM002'!$F:$F,$B13)=0,"",SUMIFS('PLM002'!$K:$K,'PLM002'!$C:$C,AA$4,'PLM002'!$F:$F,$B13)) | AC13: =IF(SUMIFS('PLM001-財務計算用'!$P:$P,'PLM001-財務計算用'!$J:$J,AC$4,'PLM001-財務計算用'!$A:$A,$B13)=0,"",SUMIFS('PLM001-財務計算用'!$P:$P,'PLM001-財務計算用'!$J:$J,AC$4,'PLM001-財務計算用'!$A:$A,$B13)) | AD13: =IF(SUMIFS('PLM002'!$K:$K,'PLM002'!$C:$C,AC$4,'PLM002'!$F:$F,$B13)=0,"",SUMIFS('PLM002'!$K:$K,'PLM002'!$C:$C,AC$4,'PLM002'!$F:$F,$B13)) | AE13: =IF(SUMIFS('PLM001-財務計算用'!$P:$P,'PLM001-財務計算用'!$J:$J,AE$4,'PLM001-財務計算用'!$A:$A,$B13)=0,"",SUMIFS('PLM001-財務計算用'!$P:$P,'PLM001-財務計算用'!$J:$J,AE$4,'PLM001-財務計算用'!$A:$A,$B13)) | AF13: =IF(SUMIFS('PLM002'!$K:$K,'PLM002'!$C:$C,AE$4,'PLM002'!$F:$F,$B13)=0,"",SUMIFS('PLM002'!$K:$K,'PLM002'!$C:$C,AE$4,'PLM002'!$F:$F,$B13)) | AG13: =IF(SUMIFS('PLM001-財務計算用'!$P:$P,'PLM001-財務計算用'!$J:$J,AG$4,'PLM001-財務計算用'!$A:$A,$B13)=0,"",SUMIFS('PLM001-財務計算用'!$P:$P,'PLM001-財務計算用'!$J:$J,AG$4,'PLM001-財務計算用'!$A:$A,$B13)) | AH13: =IF(SUMIFS('PLM002'!$K:$K,'PLM002'!$C:$C,AG$4,'PLM002'!$F:$F,$B13)=0,"",SUMIFS('PLM002'!$K:$K,'PLM002'!$C:$C,AG$4,'PLM002'!$F:$F,$B13)) | AI13: =IF(SUMIFS('PLM001-財務計算用'!$P:$P,'PLM001-財務計算用'!$J:$J,AI$4,'PLM001-財務計算用'!$A:$A,$B13)=0,"",SUMIFS('PLM001-財務計算用'!$P:$P,'PLM001-財務計算用'!$J:$J,AI$4,'PLM001-財務計算用'!$A:$A,$B13)) | AJ13: =IF(SUMIFS('PLM002'!$K:$K,'PLM002'!$C:$C,AI$4,'PLM002'!$F:$F,$B13)=0,"",SUMIFS('PLM002'!$K:$K,'PLM002'!$C:$C,AI$4,'PLM002'!$F:$F,$B13)) | AK13: =IF(SUMIFS('PLM001-財務計算用'!$P:$P,'PLM001-財務計算用'!$J:$J,AK$4,'PLM001-財務計算用'!$A:$A,$B13)=0,"",SUMIFS('PLM001-財務計算用'!$P:$P,'PLM001-財務計算用'!$J:$J,AK$4,'PLM001-財務計算用'!$A:$A,$B13)) | AL13: =IF(SUMIFS('PLM002'!$K:$K,'PLM002'!$C:$C,AK$4,'PLM002'!$F:$F,$B13)=0,"",SUMIFS('PLM002'!$K:$K,'PLM002'!$C:$C,AK$4,'PLM002'!$F:$F,$B13)) | AM13: =IF(SUMIFS('PLM001-財務計算用'!$P:$P,'PLM001-財務計算用'!$J:$J,AM$4,'PLM001-財務計算用'!$A:$A,$B13)=0,"",SUMIFS('PLM001-財務計算用'!$P:$P,'PLM001-財務計算用'!$J:$J,AM$4,'PLM001-財務計算用'!$A:$A,$B13)) | AN13: =IF(SUMIFS('PLM002'!$K:$K,'PLM002'!$C:$C,AM$4,'PLM002'!$F:$F,$B13)=0,"",SUMIFS('PLM002'!$K:$K,'PLM002'!$C:$C,AM$4,'PLM002'!$F:$F,$B13)) | AO13: =IF(SUMIFS('PLM001-財務計算用'!$P:$P,'PLM001-財務計算用'!$J:$J,AO$4,'PLM001-財務計算用'!$A:$A,$B13)=0,"",SUMIFS('PLM001-財務計算用'!$P:$P,'PLM001-財務計算用'!$J:$J,AO$4,'PLM001-財務計算用'!$A:$A,$B13)) | AP13: =IF(SUMIFS('PLM002'!$K:$K,'PLM002'!$C:$C,AO$4,'PLM002'!$F:$F,$B13)=0,"",SUMIFS('PLM002'!$K:$K,'PLM002'!$C:$C,AO$4,'PLM002'!$F:$F,$B13)) | AQ13: =IF(SUMIFS('PLM001-財務計算用'!$P:$P,'PLM001-財務計算用'!$J:$J,AQ$4,'PLM001-財務計算用'!$A:$A,$B13)=0,"",SUMIFS('PLM001-財務計算用'!$P:$P,'PLM001-財務計算用'!$J:$J,AQ$4,'PLM001-財務計算用'!$A:$A,$B13)) | AR13: =IF(SUMIFS('PLM002'!$K:$K,'PLM002'!$C:$C,AQ$4,'PLM002'!$F:$F,$B13)=0,"",SUMIFS('PLM002'!$K:$K,'PLM002'!$C:$C,AQ$4,'PLM002'!$F:$F,$B13)) | AS13: =IF(SUMIFS('PLM001-財務計算用'!$P:$P,'PLM001-財務計算用'!$J:$J,AS$4,'PLM001-財務計算用'!$A:$A,$B13)=0,"",SUMIFS('PLM001-財務計算用'!$P:$P,'PLM001-財務計算用'!$J:$J,AS$4,'PLM001-財務計算用'!$A:$A,$B13)) | AT13: =IF(SUMIFS('PLM002'!$K:$K,'PLM002'!$C:$C,AS$4,'PLM002'!$F:$F,$B13)=0,"",SUMIFS('PLM002'!$K:$K,'PLM002'!$C:$C,AS$4,'PLM002'!$F:$F,$B13)) -> 23.7 | AU13: =IF(SUMIFS('PLM001-財務計算用'!$P:$P,'PLM001-財務計算用'!$J:$J,AU$4,'PLM001-財務計算用'!$A:$A,$B13)=0,"",SUMIFS('PLM001-財務計算用'!$P:$P,'PLM001-財務計算用'!$J:$J,AU$4,'PLM001-財務計算用'!$A:$A,$B13)) -> 184 | AV13: =IF(SUMIFS('PLM002'!$K:$K,'PLM002'!$C:$C,AU$4,'PLM002'!$F:$F,$B13)=0,"",SUMIFS('PLM002'!$K:$K,'PLM002'!$C:$C,AU$4,'PLM002'!$F:$F,$B13)) -> 149 | AW13: =IF(SUMIFS('PLM001-財務計算用'!$P:$P,'PLM001-財務計算用'!$J:$J,AW$4,'PLM001-財務計算用'!$A:$A,$B13)=0,"",SUMIFS('PLM001-財務計算用'!$P:$P,'PLM001-財務計算用'!$J:$J,AW$4,'PLM001-財務計算用'!$A:$A,$B13)) | AX13: =IF(SUMIFS('PLM002'!$K:$K,'PLM002'!$C:$C,AW$4,'PLM002'!$F:$F,$B13)=0,"",SUMIFS('PLM002'!$K:$K,'PLM002'!$C:$C,AW$4,'PLM002'!$F:$F,$B13)) | AY13: =IF(SUMIFS('PLM001-財務計算用'!$P:$P,'PLM001-財務計算用'!$J:$J,AY$4,'PLM001-財務計算用'!$A:$A,$B13)=0,"",SUMIFS('PLM001-財務計算用'!$P:$P,'PLM001-財務計算用'!$J:$J,AY$4,'PLM001-財務計算用'!$A:$A,$B13)) | AZ13: =IF(SUMIFS('PLM002'!$K:$K,'PLM002'!$C:$C,AY$4,'PLM002'!$F:$F,$B13)=0,"",SUMIFS('PLM002'!$K:$K,'PLM002'!$C:$C,AY$4,'PLM002'!$F:$F,$B13)) | BA13: =IF(SUMIFS('PLM001-財務計算用'!$P:$P,'PLM001-財務計算用'!$J:$J,BA$4,'PLM001-財務計算用'!$A:$A,$B13)=0,"",SUMIFS('PLM001-財務計算用'!$P:$P,'PLM001-財務計算用'!$J:$J,BA$4,'PLM001-財務計算用'!$A:$A,$B13)) | BB13: =IF(SUMIFS('PLM002'!$K:$K,'PLM002'!$C:$C,BA$4,'PLM002'!$F:$F,$B13)=0,"",SUMIFS('PLM002'!$K:$K,'PLM002'!$C:$C,BA$4,'PLM002'!$F:$F,$B13)) | BC13: =IF(SUMIFS('PLM001-財務計算用'!$P:$P,'PLM001-財務計算用'!$J:$J,BC$4,'PLM001-財務計算用'!$A:$A,$B13)=0,"",SUMIFS('PLM001-財務計算用'!$P:$P,'PLM001-財務計算用'!$J:$J,BC$4,'PLM001-財務計算用'!$A:$A,$B13)) | BD13: =IF(SUMIFS('PLM002'!$K:$K,'PLM002'!$C:$C,BC$4,'PLM002'!$F:$F,$B13)=0,"",SUMIFS('PLM002'!$K:$K,'PLM002'!$C:$C,BC$4,'PLM002'!$F:$F,$B13)) | BE13: =IF(SUMIFS('PLM001-財務計算用'!$P:$P,'PLM001-財務計算用'!$J:$J,BE$4,'PLM001-財務計算用'!$A:$A,$B13)=0,"",SUMIFS('PLM001-財務計算用'!$P:$P,'PLM001-財務計算用'!$J:$J,BE$4,'PLM001-財務計算用'!$A:$A,$B13)) | BF13: =IF(SUMIFS('PLM002'!$K:$K,'PLM002'!$C:$C,BE$4,'PLM002'!$F:$F,$B13)=0,"",SUMIFS('PLM002'!$K:$K,'PLM002'!$C:$C,BE$4,'PLM002'!$F:$F,$B13)) | BG13: =IF(SUMIFS('PLM001-財務計算用'!$P:$P,'PLM001-財務計算用'!$J:$J,BG$4,'PLM001-財務計算用'!$A:$A,$B13)=0,"",SUMIFS('PLM001-財務計算用'!$P:$P,'PLM001-財務計算用'!$J:$J,BG$4,'PLM001-財務計算用'!$A:$A,$B13)) | BH13: =IF(SUMIFS('PLM002'!$K:$K,'PLM002'!$C:$C,BG$4,'PLM002'!$F:$F,$B13)=0,"",SUMIFS('PLM002'!$K:$K,'PLM002'!$C:$C,BG$4,'PLM002'!$F:$F,$B13)) | BI13: =IF(SUMIFS('PLM001-財務計算用'!$P:$P,'PLM001-財務計算用'!$J:$J,BI$4,'PLM001-財務計算用'!$A:$A,$B13)=0,"",SUMIFS('PLM001-財務計算用'!$P:$P,'PLM001-財務計算用'!$J:$J,BI$4,'PLM001-財務計算用'!$A:$A,$B13)) | BJ13: =IF(SUMIFS('PLM002'!$K:$K,'PLM002'!$C:$C,BI$4,'PLM002'!$F:$F,$B13)=0,"",SUMIFS('PLM002'!$K:$K,'PLM002'!$C:$C,BI$4,'PLM002'!$F:$F,$B13)) | BK13: =IF(SUMIFS('PLM001-財務計算用'!$P:$P,'PLM001-財務計算用'!$J:$J,BK$4,'PLM001-財務計算用'!$A:$A,$B13)=0,"",SUMIFS('PLM001-財務計算用'!$P:$P,'PLM001-財務計算用'!$J:$J,BK$4,'PLM001-財務計算用'!$A:$A,$B13)) | BL13: =IF(SUMIFS('PLM002'!$K:$K,'PLM002'!$C:$C,BK$4,'PLM002'!$F:$F,$B13)=0,"",SUMIFS('PLM002'!$K:$K,'PLM002'!$C:$C,BK$4,'PLM002'!$F:$F,$B13)) | BM13: =IF(SUMIFS('PLM001-財務計算用'!$P:$P,'PLM001-財務計算用'!$J:$J,BM$4,'PLM001-財務計算用'!$A:$A,$B13)=0,"",SUMIFS('PLM001-財務計算用'!$P:$P,'PLM001-財務計算用'!$J:$J,BM$4,'PLM001-財務計算用'!$A:$A,$B13)) | BN13: =IF(SUMIFS('PLM002'!$K:$K,'PLM002'!$C:$C,BM$4,'PLM002'!$F:$F,$B13)=0,"",SUMIFS('PLM002'!$K:$K,'PLM002'!$C:$C,BM$4,'PLM002'!$F:$F,$B13)) | BO13: =IF(SUMIFS('PLM001-財務計算用'!$P:$P,'PLM001-財務計算用'!$J:$J,BO$4,'PLM001-財務計算用'!$A:$A,$B13)=0,"",SUMIFS('PLM001-財務計算用'!$P:$P,'PLM001-財務計算用'!$J:$J,BO$4,'PLM001-財務計算用'!$A:$A,$B13)) | BP13: =IF(SUMIFS('PLM002'!$K:$K,'PLM002'!$C:$C,BO$4,'PLM002'!$F:$F,$B13)=0,"",SUMIFS('PLM002'!$K:$K,'PLM002'!$C:$C,BO$4,'PLM002'!$F:$F,$B13)) | BQ13: =IF(SUMIFS('PLM001-財務計算用'!$P:$P,'PLM001-財務計算用'!$J:$J,BQ$4,'PLM001-財務計算用'!$A:$A,$B13)=0,"",SUMIFS('PLM001-財務計算用'!$P:$P,'PLM001-財務計算用'!$J:$J,BQ$4,'PLM001-財務計算用'!$A:$A,$B13)) | BR13: =IF(SUMIFS('PLM002'!$K:$K,'PLM002'!$C:$C,BQ$4,'PLM002'!$F:$F,$B13)=0,"",SUMIFS('PLM002'!$K:$K,'PLM002'!$C:$C,BQ$4,'PLM002'!$F:$F,$B13)) | BS13: =IF(SUMIFS('PLM001-財務計算用'!$P:$P,'PLM001-財務計算用'!$J:$J,BS$4,'PLM001-財務計算用'!$A:$A,$B13)=0,"",SUMIFS('PLM001-財務計算用'!$P:$P,'PLM001-財務計算用'!$J:$J,BS$4,'PLM001-財務計算用'!$A:$A,$B13)) | BT13: =IF(SUMIFS('PLM002'!$K:$K,'PLM002'!$C:$C,BS$4,'PLM002'!$F:$F,$B13)=0,"",SUMIFS('PLM002'!$K:$K,'PLM002'!$C:$C,BS$4,'PLM002'!$F:$F,$B13)) | BU13: =IF(SUMIFS('PLM001-財務計算用'!$P:$P,'PLM001-財務計算用'!$J:$J,BU$4,'PLM001-財務計算用'!$A:$A,$B13)=0,"",SUMIFS('PLM001-財務計算用'!$P:$P,'PLM001-財務計算用'!$J:$J,BU$4,'PLM001-財務計算用'!$A:$A,$B13)) | BV13: =IF(SUMIFS('PLM002'!$K:$K,'PLM002'!$C:$C,BU$4,'PLM002'!$F:$F,$B13)=0,"",SUMIFS('PLM002'!$K:$K,'PLM002'!$C:$C,BU$4,'PLM002'!$F:$F,$B13)) | BW13: =IF(SUMIFS('PLM001-財務計算用'!$P:$P,'PLM001-財務計算用'!$J:$J,BW$4,'PLM001-財務計算用'!$A:$A,$B13)=0,"",SUMIFS('PLM001-財務計算用'!$P:$P,'PLM001-財務計算用'!$J:$J,BW$4,'PLM001-財務計算用'!$A:$A,$B13)) | BX13: =IF(SUMIFS('PLM002'!$K:$K,'PLM002'!$C:$C,BW$4,'PLM002'!$F:$F,$B13)=0,"",SUMIFS('PLM002'!$K:$K,'PLM002'!$C:$C,BW$4,'PLM002'!$F:$F,$B13)) | BY13: =IF(SUMIFS('PLM001-財務計算用'!$P:$P,'PLM001-財務計算用'!$J:$J,BY$4,'PLM001-財務計算用'!$A:$A,$B13)=0,"",SUMIFS('PLM001-財務計算用'!$P:$P,'PLM001-財務計算用'!$J:$J,BY$4,'PLM001-財務計算用'!$A:$A,$B13)) | BZ13: =IF(SUMIFS('PLM002'!$K:$K,'PLM002'!$C:$C,BY$4,'PLM002'!$F:$F,$B13)=0,"",SUMIFS('PLM002'!$K:$K,'PLM002'!$C:$C,BY$4,'PLM002'!$F:$F,$B13)) | CA13: =IF(SUMIFS('PLM001-財務計算用'!$P:$P,'PLM001-財務計算用'!$J:$J,CA$4,'PLM001-財務計算用'!$A:$A,$B13)=0,"",SUMIFS('PLM001-財務計算用'!$P:$P,'PLM001-財務計算用'!$J:$J,CA$4,'PLM001-財務計算用'!$A:$A,$B13)) | CB13: =IF(SUMIFS('PLM002'!$K:$K,'PLM002'!$C:$C,CA$4,'PLM002'!$F:$F,$B13)=0,"",SUMIFS('PLM002'!$K:$K,'PLM002'!$C:$C,CA$4,'PLM002'!$F:$F,$B13)) | CC13: =IF(SUMIFS('PLM001-財務計算用'!$P:$P,'PLM001-財務計算用'!$J:$J,CC$4,'PLM001-財務計算用'!$A:$A,$B13)=0,"",SUMIFS('PLM001-財務計算用'!$P:$P,'PLM001-財務計算用'!$J:$J,CC$4,'PLM001-財務計算用'!$A:$A,$B13)) | CD13: =IF(SUMIFS('PLM002'!$K:$K,'PLM002'!$C:$C,CC$4,'PLM002'!$F:$F,$B13)=0,"",SUMIFS('PLM002'!$K:$K,'PLM002'!$C:$C,CC$4,'PLM002'!$F:$F,$B13)) | CE13: =IF(SUMIFS('PLM001-財務計算用'!$P:$P,'PLM001-財務計算用'!$J:$J,CE$4,'PLM001-財務計算用'!$A:$A,$B13)=0,"",SUMIFS('PLM001-財務計算用'!$P:$P,'PLM001-財務計算用'!$J:$J,CE$4,'PLM001-財務計算用'!$A:$A,$B13)) | CF13: =IF(SUMIFS('PLM002'!$K:$K,'PLM002'!$C:$C,CE$4,'PLM002'!$F:$F,$B13)=0,"",SUMIFS('PLM002'!$K:$K,'PLM002'!$C:$C,CE$4,'PLM002'!$F:$F,$B13)) | CG13: =IF(SUMIFS('PLM001-財務計算用'!$P:$P,'PLM001-財務計算用'!$J:$J,CG$4,'PLM001-財務計算用'!$A:$A,$B13)=0,"",SUMIFS('PLM001-財務計算用'!$P:$P,'PLM001-財務計算用'!$J:$J,CG$4,'PLM001-財務計算用'!$A:$A,$B13)) | CH13: =IF(SUMIFS('PLM002'!$K:$K,'PLM002'!$C:$C,CG$4,'PLM002'!$F:$F,$B13)=0,"",SUMIFS('PLM002'!$K:$K,'PLM002'!$C:$C,CG$4,'PLM002'!$F:$F,$B13)) | CI13: =IF(SUMIFS('PLM001-財務計算用'!$P:$P,'PLM001-財務計算用'!$J:$J,CI$4,'PLM001-財務計算用'!$A:$A,$B13)=0,"",SUMIFS('PLM001-財務計算用'!$P:$P,'PLM001-財務計算用'!$J:$J,CI$4,'PLM001-財務計算用'!$A:$A,$B13)) | CJ13: =IF(SUMIFS('PLM002'!$K:$K,'PLM002'!$C:$C,CI$4,'PLM002'!$F:$F,$B13)=0,"",SUMIFS('PLM002'!$K:$K,'PLM002'!$C:$C,CI$4,'PLM002'!$F:$F,$B13)) | CK13: =IF(SUMIFS('PLM001-財務計算用'!$P:$P,'PLM001-財務計算用'!$J:$J,CK$4,'PLM001-財務計算用'!$A:$A,$B13)=0,"",SUMIFS('PLM001-財務計算用'!$P:$P,'PLM001-財務計算用'!$J:$J,CK$4,'PLM001-財務計算用'!$A:$A,$B13)) | CL13: =IF(SUMIFS('PLM002'!$K:$K,'PLM002'!$C:$C,CK$4,'PLM002'!$F:$F,$B13)=0,"",SUMIFS('PLM002'!$K:$K,'PLM002'!$C:$C,CK$4,'PLM002'!$F:$F,$B13)) | CM13: =IF(SUMIFS('PLM001-財務計算用'!$P:$P,'PLM001-財務計算用'!$J:$J,CM$4,'PLM001-財務計算用'!$A:$A,$B13)=0,"",SUMIFS('PLM001-財務計算用'!$P:$P,'PLM001-財務計算用'!$J:$J,CM$4,'PLM001-財務計算用'!$A:$A,$B13)) | CN13: =IF(SUMIFS('PLM002'!$K:$K,'PLM002'!$C:$C,CM$4,'PLM002'!$F:$F,$B13)=0,"",SUMIFS('PLM002'!$K:$K,'PLM002'!$C:$C,CM$4,'PLM002'!$F:$F,$B13)) | CO13: =IF(SUMIFS('PLM001-財務計算用'!$P:$P,'PLM001-財務計算用'!$J:$J,CO$4,'PLM001-財務計算用'!$A:$A,$B13)=0,"",SUMIFS('PLM001-財務計算用'!$P:$P,'PLM001-財務計算用'!$J:$J,CO$4,'PLM001-財務計算用'!$A:$A,$B13)) | CP13: =IF(SUMIFS('PLM002'!$K:$K,'PLM002'!$C:$C,CO$4,'PLM002'!$F:$F,$B13)=0,"",SUMIFS('PLM002'!$K:$K,'PLM002'!$C:$C,CO$4,'PLM002'!$F:$F,$B13)) | CQ13: =IF(SUMIFS('PLM001-財務計算用'!$P:$P,'PLM001-財務計算用'!$J:$J,CQ$4,'PLM001-財務計算用'!$A:$A,$B13)=0,"",SUMIFS('PLM001-財務計算用'!$P:$P,'PLM001-財務計算用'!$J:$J,CQ$4,'PLM001-財務計算用'!$A:$A,$B13)) | CR13: =IF(SUMIFS('PLM002'!$K:$K,'PLM002'!$C:$C,CQ$4,'PLM002'!$F:$F,$B13)=0,"",SUMIFS('PLM002'!$K:$K,'PLM002'!$C:$C,CQ$4,'PLM002'!$F:$F,$B13)) | CS13: =IF(SUMIFS('PLM001-財務計算用'!$P:$P,'PLM001-財務計算用'!$J:$J,CS$4,'PLM001-財務計算用'!$A:$A,$B13)=0,"",SUMIFS('PLM001-財務計算用'!$P:$P,'PLM001-財務計算用'!$J:$J,CS$4,'PLM001-財務計算用'!$A:$A,$B13)) | CT13: =IF(SUMIFS('PLM002'!$K:$K,'PLM002'!$C:$C,CS$4,'PLM002'!$F:$F,$B13)=0,"",SUMIFS('PLM002'!$K:$K,'PLM002'!$C:$C,CS$4,'PLM002'!$F:$F,$B13)) | CU13: =IF(SUMIFS('PLM001-財務計算用'!$P:$P,'PLM001-財務計算用'!$J:$J,CU$4,'PLM001-財務計算用'!$A:$A,$B13)=0,"",SUMIFS('PLM001-財務計算用'!$P:$P,'PLM001-財務計算用'!$J:$J,CU$4,'PLM001-財務計算用'!$A:$A,$B13)) | CV13: =IF(SUMIFS('PLM002'!$K:$K,'PLM002'!$C:$C,CU$4,'PLM002'!$F:$F,$B13)=0,"",SUMIFS('PLM002'!$K:$K,'PLM002'!$C:$C,CU$4,'PLM002'!$F:$F,$B13)) | CW13: =IF(SUMIFS('PLM001-財務計算用'!$P:$P,'PLM001-財務計算用'!$J:$J,CW$4,'PLM001-財務計算用'!$A:$A,$B13)=0,"",SUMIFS('PLM001-財務計算用'!$P:$P,'PLM001-財務計算用'!$J:$J,CW$4,'PLM001-財務計算用'!$A:$A,$B13)) | CX13: =IF(SUMIFS('PLM002'!$K:$K,'PLM002'!$C:$C,CW$4,'PLM002'!$F:$F,$B13)=0,"",SUMIFS('PLM002'!$K:$K,'PLM002'!$C:$C,CW$4,'PLM002'!$F:$F,$B13)) | CY13: =IF(SUMIFS('PLM001-財務計算用'!$P:$P,'PLM001-財務計算用'!$J:$J,CY$4,'PLM001-財務計算用'!$A:$A,$B13)=0,"",SUMIFS('PLM001-財務計算用'!$P:$P,'PLM001-財務計算用'!$J:$J,CY$4,'PLM001-財務計算用'!$A:$A,$B13)) | CZ13: =IF(SUMIFS('PLM002'!$K:$K,'PLM002'!$C:$C,CY$4,'PLM002'!$F:$F,$B13)=0,"",SUMIFS('PLM002'!$K:$K,'PLM002'!$C:$C,CY$4,'PLM002'!$F:$F,$B13)) | DA13: =IF(SUMIFS('PLM001-財務計算用'!$P:$P,'PLM001-財務計算用'!$J:$J,DA$4,'PLM001-財務計算用'!$A:$A,$B13)=0,"",SUMIFS('PLM001-財務計算用'!$P:$P,'PLM001-財務計算用'!$J:$J,DA$4,'PLM001-財務計算用'!$A:$A,$B13)) | DB13: =IF(SUMIFS('PLM002'!$K:$K,'PLM002'!$C:$C,DA$4,'PLM002'!$F:$F,$B13)=0,"",SUMIFS('PLM002'!$K:$K,'PLM002'!$C:$C,DA$4,'PLM002'!$F:$F,$B13)) | DC13: =IF(SUMIFS('PLM001-財務計算用'!$P:$P,'PLM001-財務計算用'!$J:$J,DC$4,'PLM001-財務計算用'!$A:$A,$B13)=0,"",SUMIFS('PLM001-財務計算用'!$P:$P,'PLM001-財務計算用'!$J:$J,DC$4,'PLM001-財務計算用'!$A:$A,$B13)) | DD13: =IF(SUMIFS('PLM002'!$K:$K,'PLM002'!$C:$C,DC$4,'PLM002'!$F:$F,$B13)=0,"",SUMIFS('PLM002'!$K:$K,'PLM002'!$C:$C,DC$4,'PLM002'!$F:$F,$B13)) | DE13: =IF(SUMIFS('PLM001-財務計算用'!$P:$P,'PLM001-財務計算用'!$J:$J,DE$4,'PLM001-財務計算用'!$A:$A,$B13)=0,"",SUMIFS('PLM001-財務計算用'!$P:$P,'PLM001-財務計算用'!$J:$J,DE$4,'PLM001-財務計算用'!$A:$A,$B13)) | DF13: =IF(SUMIFS('PLM002'!$K:$K,'PLM002'!$C:$C,DE$4,'PLM002'!$F:$F,$B13)=0,"",SUMIFS('PLM002'!$K:$K,'PLM002'!$C:$C,DE$4,'PLM002'!$F:$F,$B13)) | DG13: =IF(SUMIFS('PLM001-財務計算用'!$P:$P,'PLM001-財務計算用'!$J:$J,DG$4,'PLM001-財務計算用'!$A:$A,$B13)=0,"",SUMIFS('PLM001-財務計算用'!$P:$P,'PLM001-財務計算用'!$J:$J,DG$4,'PLM001-財務計算用'!$A:$A,$B13)) | DH13: =IF(SUMIFS('PLM002'!$K:$K,'PLM002'!$C:$C,DG$4,'PLM002'!$F:$F,$B13)=0,"",SUMIFS('PLM002'!$K:$K,'PLM002'!$C:$C,DG$4,'PLM002'!$F:$F,$B13)) | DI13: =IF(SUMIFS('PLM001-財務計算用'!$P:$P,'PLM001-財務計算用'!$J:$J,DI$4,'PLM001-財務計算用'!$A:$A,$B13)=0,"",SUMIFS('PLM001-財務計算用'!$P:$P,'PLM001-財務計算用'!$J:$J,DI$4,'PLM001-財務計算用'!$A:$A,$B13)) | DJ13: =IF(SUMIFS('PLM002'!$K:$K,'PLM002'!$C:$C,DI$4,'PLM002'!$F:$F,$B13)=0,"",SUMIFS('PLM002'!$K:$K,'PLM002'!$C:$C,DI$4,'PLM002'!$F:$F,$B13)) | DK13: =IF(SUMIFS('PLM001-財務計算用'!$P:$P,'PLM001-財務計算用'!$J:$J,DK$4,'PLM001-財務計算用'!$A:$A,$B13)=0,"",SUMIFS('PLM001-財務計算用'!$P:$P,'PLM001-財務計算用'!$J:$J,DK$4,'PLM001-財務計算用'!$A:$A,$B13)) | DL13: =IF(SUMIFS('PLM002'!$K:$K,'PLM002'!$C:$C,DK$4,'PLM002'!$F:$F,$B13)=0,"",SUMIFS('PLM002'!$K:$K,'PLM002'!$C:$C,DK$4,'PLM002'!$F:$F,$B13)) | DM13: =IF(SUMIFS('PLM001-財務計算用'!$P:$P,'PLM001-財務計算用'!$J:$J,DM$4,'PLM001-財務計算用'!$A:$A,$B13)=0,"",SUMIFS('PLM001-財務計算用'!$P:$P,'PLM001-財務計算用'!$J:$J,DM$4,'PLM001-財務計算用'!$A:$A,$B13)) | DN13: =IF(SUMIFS('PLM002'!$K:$K,'PLM002'!$C:$C,DM$4,'PLM002'!$F:$F,$B13)=0,"",SUMIFS('PLM002'!$K:$K,'PLM002'!$C:$C,DM$4,'PLM002'!$F:$F,$B13)) | DO13: =IF(SUMIFS('PLM001-財務計算用'!$P:$P,'PLM001-財務計算用'!$J:$J,DO$4,'PLM001-財務計算用'!$A:$A,$B13)=0,"",SUMIFS('PLM001-財務計算用'!$P:$P,'PLM001-財務計算用'!$J:$J,DO$4,'PLM001-財務計算用'!$A:$A,$B13)) | DP13: =IF(SUMIFS('PLM002'!$K:$K,'PLM002'!$C:$C,DO$4,'PLM002'!$F:$F,$B13)=0,"",SUMIFS('PLM002'!$K:$K,'PLM002'!$C:$C,DO$4,'PLM002'!$F:$F,$B13)) | DQ13: =IF(SUMIFS('PLM001-財務計算用'!$P:$P,'PLM001-財務計算用'!$J:$J,DQ$4,'PLM001-財務計算用'!$A:$A,$B13)=0,"",SUMIFS('PLM001-財務計算用'!$P:$P,'PLM001-財務計算用'!$J:$J,DQ$4,'PLM001-財務計算用'!$A:$A,$B13)) | DR13: =IF(SUMIFS('PLM002'!$K:$K,'PLM002'!$C:$C,DQ$4,'PLM002'!$F:$F,$B13)=0,"",SUMIFS('PLM002'!$K:$K,'PLM002'!$C:$C,DQ$4,'PLM002'!$F:$F,$B13)) | DS13: =IF(SUMIFS('PLM001-財務計算用'!$P:$P,'PLM001-財務計算用'!$J:$J,DS$4,'PLM001-財務計算用'!$A:$A,$B13)=0,"",SUMIFS('PLM001-財務計算用'!$P:$P,'PLM001-財務計算用'!$J:$J,DS$4,'PLM001-財務計算用'!$A:$A,$B13)) | DT13: =IF(SUMIFS('PLM002'!$K:$K,'PLM002'!$C:$C,DS$4,'PLM002'!$F:$F,$B13)=0,"",SUMIFS('PLM002'!$K:$K,'PLM002'!$C:$C,DS$4,'PLM002'!$F:$F,$B13)) | DU13: =IF(SUMIFS('PLM001-財務計算用'!$P:$P,'PLM001-財務計算用'!$J:$J,DU$4,'PLM001-財務計算用'!$A:$A,$B13)=0,"",SUMIFS('PLM001-財務計算用'!$P:$P,'PLM001-財務計算用'!$J:$J,DU$4,'PLM001-財務計算用'!$A:$A,$B13)) | DV13: =IF(SUMIFS('PLM002'!$K:$K,'PLM002'!$C:$C,DU$4,'PLM002'!$F:$F,$B13)=0,"",SUMIFS('PLM002'!$K:$K,'PLM002'!$C:$C,DU$4,'PLM002'!$F:$F,$B13)) | DW13: =IF(SUMIFS('PLM001-財務計算用'!$P:$P,'PLM001-財務計算用'!$J:$J,DW$4,'PLM001-財務計算用'!$A:$A,$B13)=0,"",SUMIFS('PLM001-財務計算用'!$P:$P,'PLM001-財務計算用'!$J:$J,DW$4,'PLM001-財務計算用'!$A:$A,$B13)) | DX13: =IF(SUMIFS('PLM002'!$K:$K,'PLM002'!$C:$C,DW$4,'PLM002'!$F:$F,$B13)=0,"",SUMIFS('PLM002'!$K:$K,'PLM002'!$C:$C,DW$4,'PLM002'!$F:$F,$B13)) | DY13: =IF(SUMIFS('PLM001-財務計算用'!$P:$P,'PLM001-財務計算用'!$J:$J,DY$4,'PLM001-財務計算用'!$A:$A,$B13)=0,"",SUMIFS('PLM001-財務計算用'!$P:$P,'PLM001-財務計算用'!$J:$J,DY$4,'PLM001-財務計算用'!$A:$A,$B13)) | DZ13: =IF(SUMIFS('PLM002'!$K:$K,'PLM002'!$C:$C,DY$4,'PLM002'!$F:$F,$B13)=0,"",SUMIFS('PLM002'!$K:$K,'PLM002'!$C:$C,DY$4,'PLM002'!$F:$F,$B13)) | EA13: =IF(SUMIFS('PLM001-財務計算用'!$P:$P,'PLM001-財務計算用'!$J:$J,EA$4,'PLM001-財務計算用'!$A:$A,$B13)=0,"",SUMIFS('PLM001-財務計算用'!$P:$P,'PLM001-財務計算用'!$J:$J,EA$4,'PLM001-財務計算用'!$A:$A,$B13)) | EB13: =IF(SUMIFS('PLM002'!$K:$K,'PLM002'!$C:$C,EA$4,'PLM002'!$F:$F,$B13)=0,"",SUMIFS('PLM002'!$K:$K,'PLM002'!$C:$C,EA$4,'PLM002'!$F:$F,$B13)) | EC13: =IF(SUMIFS('PLM001-財務計算用'!$P:$P,'PLM001-財務計算用'!$J:$J,EC$4,'PLM001-財務計算用'!$A:$A,$B13)=0,"",SUMIFS('PLM001-財務計算用'!$P:$P,'PLM001-財務計算用'!$J:$J,EC$4,'PLM001-財務計算用'!$A:$A,$B13)) | ED13: =IF(SUMIFS('PLM002'!$K:$K,'PLM002'!$C:$C,EC$4,'PLM002'!$F:$F,$B13)=0,"",SUMIFS('PLM002'!$K:$K,'PLM002'!$C:$C,EC$4,'PLM002'!$F:$F,$B13))
